{
  "aktualisiert": "2026-06-12T19:55:27.383089+00:00",
  "aktien": [
    {
      "wkn": "A1J84E",
      "name": "AbbVie",
      "ticker": "ABBV",
      "currency": "EUR",
      "price": 196.57,
      "change_1d_pct": 1.23,
      "change_1w_pct": 0.14,
      "change_1m_pct": 9.13,
      "change_1y_pct": 22.1,
      "week52_high": 211.49,
      "week52_low": 157.0,
      "div_yield": null,
      "div_rate": 5.98,
      "market_cap": "402.0B",
      "pe_ratio": 111.0,
      "sparkline": [
        178.4817,
        179.8294,
        178.0584,
        177.1254,
        175.1212,
        174.119,
        175.1816,
        179.5703,
        180.1232,
        182.0842,
        181.7559,
        180.9093,
        184.6673,
        183.406,
        185.3065,
        186.3432,
        184.1144,
        186.0841,
        188.8745,
        188.0883,
        183.9502,
        186.0841,
        187.5786,
        194.3257,
        196.304,
        192.7102,
        194.7403,
        194.3343,
        194.1788,
        196.5718
      ],
      "analyst_rating": "Kaufen",
      "analyst_target": 219.04,
      "analyst_count": 29,
      "news": [
        {
          "titel": "JNJ hat die Messlatte höher gelegt: Warum stagniert die Aktie trotzdem?",
          "einordnung": "Aktionäre sollten prüfen, ob die Stagnation der Aktie trotz positiver Branchenentwicklungen auf spezifische Unternehmensherausforderungen oder eine Unterbewertung hindeutet.",
          "url": "https://www.trefis.com/articles/602698/jnj-raised-the-bar-so-why-is-the-stock-standing-still/2026-06-12",
          "quelle": "Trefis",
          "datum": "12.06.2026"
        },
        {
          "titel": "3 Aktien, die schätzungsweise bis zu 47,8 % unter ihrem inneren Wert liegen",
          "einordnung": "Dies könnte auf eine attraktive Kaufgelegenheit für langfristig orientierte Aktionäre hindeuten, die an den fundamentalen Wert des Unternehmens glauben.",
          "url": "https://finance.yahoo.com/markets/stocks/articles/3-stocks-estimated-47-8-173800545.html",
          "quelle": "Simply Wall St.",
          "datum": "12.06.2026"
        },
        {
          "titel": "Der Haken, der sich in der Wachstumsgeschichte der Eli Lilly Aktie verbirgt",
          "einordnung": "Aktionäre sollten die Wachstumsgeschichten von Wettbewerbern wie Eli Lilly genau analysieren, um potenzielle Risiken und Chancen im Pharmasektor besser einschätzen zu können.",
          "url": "https://www.trefis.com/articles/602703/the-catch-hiding-in-eli-lilly-stocks-growth-story/2026-06-12",
          "quelle": "Trefis",
          "datum": "12.06.2026"
        },
        {
          "titel": "3 Aktien, die möglicherweise bis zu 39,8 % unter ihrem geschätzten inneren Wert liegen",
          "einordnung": "Dies signalisiert eine potenzielle Unterbewertung, die für Aktionäre eine Chance auf zukünftige Kursgewinne darstellen könnte.",
          "url": "https://finance.yahoo.com/markets/stocks/articles/3-stocks-might-39-8-113802585.html",
          "quelle": "Simply Wall St.",
          "datum": "12.06.2026"
        }
      ],
      "fehler": null
    },
    {
      "wkn": "A2ANT0",
      "name": "Ahold Delhaize",
      "ticker": "AD.AS",
      "currency": "EUR",
      "price": 36.37,
      "change_1d_pct": 0.47,
      "change_1w_pct": 1.45,
      "change_1m_pct": -0.38,
      "change_1y_pct": 4.73,
      "week52_high": 42.54,
      "week52_low": 32.13,
      "div_yield": null,
      "div_rate": 1.46,
      "market_cap": "32.0B",
      "pe_ratio": 14.43,
      "sparkline": [
        39.13,
        39.43,
        38.48,
        37.67,
        37.19,
        36.9,
        36.72,
        36.5,
        36.51,
        36.8,
        37.63,
        38.05,
        37.59,
        37.05,
        36.65,
        36.62,
        36.27,
        36.7,
        36.4,
        36.17,
        35.66,
        34.94,
        35.26,
        35.22,
        35.85,
        35.37,
        35.75,
        36.18,
        36.2,
        36.37
      ],
      "analyst_rating": "Halten",
      "analyst_target": 40.06,
      "analyst_count": 17,
      "news": [
        {
          "titel": "Ahold Delhaize USA zahlt 40 Millionen Dollar wegen überhöhter Arzneimittelpreise",
          "einordnung": "Diese Zahlung stellt eine Belastung für die Bilanz dar, aber Aktionäre sollten die langfristigen Auswirkungen auf den Ruf und die zukünftigen Geschäftspraktiken bewerten.",
          "url": "https://www.retail-insight-network.com/news/ahold-delhaize-usa-40m/",
          "quelle": "Retail Insight Network",
          "datum": "12.06.2026"
        },
        {
          "titel": "Was wird der nächste CEO von Ahold Delhaize priorisieren?",
          "einordnung": "Aktionäre sollten die strategischen Schwerpunkte des neuen CEOs genau beobachten, da diese maßgeblich die zukünftige Ausrichtung und Profitabilität des Unternehmens beeinflussen werden.",
          "url": "https://www.grocerydive.com/news/ahold-delhaize-ceo-Thierry-Garnier-Frans-Muller-executive-changes/822617/",
          "quelle": "Grocery Dive",
          "datum": "11.06.2026"
        },
        {
          "titel": "Der Leiter der Eigenmarken von Ahold Delhaize USA spricht über Strategie",
          "einordnung": "Die Strategie im Bereich Eigenmarken ist entscheidend für die Margen und die Kundenbindung, was für Aktionäre ein wichtiger Indikator für zukünftiges Wachstum ist.",
          "url": "https://www.grocerydive.com/news/ahold-delhaize-adusa-private-label-own-brands-abby-cook-executive/820852/",
          "quelle": "Grocery Dive",
          "datum": "21.05.2026"
        },
        {
          "titel": "Trumps Kürzungen bei Lebensmittelzuschüssen belasten US-Lebensmittelunternehmen",
          "einordnung": "Diese politischen Entscheidungen könnten die Profitabilität des US-Geschäfts von Ahold Delhaize beeinträchtigen und sollten von Aktionären genau beobachtet werden.",
          "url": "https://finance.yahoo.com/news/food-companies-hit-trump-administration-100006583.html",
          "quelle": "Financial Times",
          "datum": "13.05.2026"
        }
      ],
      "fehler": null
    },
    {
      "wkn": "840400",
      "name": "Allianz",
      "ticker": "ALV.DE",
      "currency": "EUR",
      "price": 386.4,
      "change_1d_pct": 0.81,
      "change_1w_pct": 3.65,
      "change_1m_pct": 1.6,
      "change_1y_pct": 17.8,
      "week52_high": 397.0,
      "week52_low": 333.2,
      "div_yield": null,
      "div_rate": 17.1,
      "market_cap": "146.6B",
      "pe_ratio": 12.48,
      "sparkline": [
        360.7015,
        366.0551,
        375.2328,
        371.6,
        369.1,
        371.7,
        368.2,
        372.3,
        380.3,
        374.5,
        381.4,
        382.6,
        385.7,
        385.9,
        385.6,
        391.0,
        388.9,
        389.4,
        380.9,
        381.6,
        374.9,
        376.7,
        368.6,
        371.3,
        372.8,
        374.1,
        377.9,
        381.5,
        383.3,
        386.4
      ],
      "analyst_rating": "Kaufen",
      "analyst_target": 403.9,
      "analyst_count": 18,
      "news": [
        {
          "titel": "3 europäische Dividendenaktien mit einer Rendite von bis zu 4,4 %",
          "einordnung": "Für dividendenorientierte Aktionäre könnte dies ein Hinweis sein, die Allianz als potenziellen Kandidaten für ein stabiles Einkommen zu prüfen.",
          "url": "https://finance.yahoo.com/markets/stocks/articles/3-european-dividend-stocks-yielding-103155015.html",
          "quelle": "Simply Wall St.",
          "datum": "12.06.2026"
        },
        {
          "titel": "Allianz in fortgeschrittenen Verhandlungen zur Übernahme der portugiesischen Caravela – Bericht",
          "einordnung": "Eine erfolgreiche Akquisition könnte die Marktposition der Allianz in Südeuropa stärken und neue Wachstumschancen eröffnen, was für Aktionäre positiv wäre.",
          "url": "https://www.lifeinsuranceinternational.com/news/allianz-acquire-portugal-caravela/",
          "quelle": "Life Insurance International",
          "datum": "08.06.2026"
        },
        {
          "titel": "PRU erweitert Präsenz im Altersvorsorgemarkt mit festverzinslicher Indexannuität",
          "einordnung": "Aktionäre sollten die Entwicklungen und Innovationen im Altersvorsorgemarkt, wie sie von Wettbewerbern wie PRU gezeigt werden, beobachten, da diese auch die Strategie der Allianz beeinflussen könnten.",
          "url": "https://finance.yahoo.com/markets/stocks/articles/pru-expands-retirement-market-presence-152400837.html",
          "quelle": "Zacks",
          "datum": "04.06.2026"
        },
        {
          "titel": "Europäische Dividendenaktien, die Sie für Ihr Portfolio in Betracht ziehen sollten",
          "einordnung": "Dies unterstreicht die Attraktivität europäischer Dividendenwerte und könnte die Allianz als stabilen Bestandteil eines diversifizierten Portfolios hervorheben.",
          "url": "https://finance.yahoo.com/markets/stocks/articles/european-dividend-stocks-consider-portfolio-104156977.html",
          "quelle": "Simply Wall St.",
          "datum": "04.06.2026"
        }
      ],
      "fehler": null
    },
    {
      "wkn": "850471",
      "name": "Boeing",
      "ticker": "BA",
      "currency": "EUR",
      "price": 189.43,
      "change_1d_pct": -1.06,
      "change_1w_pct": 1.77,
      "change_1m_pct": -8.87,
      "change_1y_pct": 7.62,
      "week52_high": 219.73,
      "week52_low": 152.71,
      "div_yield": null,
      "div_rate": null,
      "market_cap": "172.9B",
      "pe_ratio": 86.67,
      "sparkline": [
        196.4336,
        191.1811,
        193.8419,
        198.6365,
        199.5868,
        205.0553,
        205.7896,
        204.632,
        207.8543,
        198.0145,
        190.4813,
        190.585,
        185.7471,
        191.9586,
        189.7211,
        189.2114,
        189.1077,
        193.7728,
        197.643,
        199.6905,
        193.7728,
        188.071,
        181.9201,
        187.8291,
        186.1273,
        186.5333,
        185.3152,
        180.5551,
        191.4662,
        189.4274
      ],
      "analyst_rating": "Kaufen",
      "analyst_target": 233.25,
      "analyst_count": 25,
      "news": [
        {
          "titel": "Air India will Hunderte von Jet-Lieferungen verschieben, sagen Quellen",
          "einordnung": "Eine Verschiebung von Lieferungen könnte den Auftragsbestand und die Produktionspläne von Boeing belasten, was sich negativ auf den Umsatz und die Profitabilität auswirken könnte.",
          "url": "https://sg.finance.yahoo.com/news/air-india-seeks-defer-hundreds-165154419.html",
          "quelle": "Reuters",
          "datum": "12.06.2026"
        },
        {
          "titel": "Hexcel profitiert von starker Luft- und Raumfahrt-Nachfrage und Engagement im Verteidigungssektor",
          "einordnung": "Dies deutet auf eine robuste Nachfrage im Luft- und Raumfahrtsektor hin, von der auch Boeing als Hauptakteur profitieren sollte, was für Aktionäre positiv ist.",
          "url": "https://finance.yahoo.com/markets/stocks/articles/hexcel-gains-strong-aerospace-demand-134000456.html",
          "quelle": "Zacks",
          "datum": "12.06.2026"
        },
        {
          "titel": "Übernahmechancen: Wie diese 4 Kultaktien als Übernahmeziele abschneiden",
          "einordnung": "Aktionäre sollten die Konsolidierungstendenzen und Übernahmeaktivitäten in der Luft- und Raumfahrtbranche beobachten, da diese das Wettbewerbsumfeld für Boeing verändern könnten.",
          "url": "https://247wallst.com/investing/2026/06/12/acquisition-odds-how-these-4-cult-stocks-stack-up-as-buyout-targets/",
          "quelle": "24/7 Wall St.",
          "datum": "12.06.2026"
        },
        {
          "titel": "3 Aktien, die möglicherweise bis zu 39,8 % unter ihrem geschätzten inneren Wert liegen",
          "einordnung": "Eine potenzielle Unterbewertung könnte für Aktionäre eine attraktive Einstiegs- oder Nachkaufgelegenheit darstellen, falls Boeing zu diesen Aktien gehört.",
          "url": "https://finance.yahoo.com/markets/stocks/articles/3-stocks-might-39-8-113802585.html",
          "quelle": "Simply Wall St.",
          "datum": "12.06.2026"
        }
      ],
      "fehler": null
    },
    {
      "wkn": "850501",
      "name": "Bristol-Myers Squibb",
      "ticker": "BMY",
      "currency": "EUR",
      "price": 49.25,
      "change_1d_pct": 0.19,
      "change_1w_pct": -0.46,
      "change_1m_pct": 1.09,
      "change_1y_pct": 18.08,
      "week52_high": 54.33,
      "week52_low": 36.73,
      "div_yield": null,
      "div_rate": 2.18,
      "market_cap": "116.4B",
      "pe_ratio": 15.97,
      "sparkline": [
        50.2963,
        49.5706,
        49.1991,
        48.8881,
        48.5944,
        48.5166,
        48.0933,
        48.7672,
        48.7153,
        49.0436,
        49.2423,
        49.5101,
        50.374,
        50.5727,
        51.4452,
        51.3675,
        50.1321,
        49.6915,
        49.1645,
        49.3978,
        47.4713,
        47.048,
        47.2726,
        48.8967,
        49.4756,
        48.0069,
        48.7931,
        48.0328,
        49.1559,
        49.2466
      ],
      "analyst_rating": "Halten",
      "analyst_target": 54.49,
      "analyst_count": 25,
      "news": [
        {
          "titel": "Kann das Wachstumsportfolio von Bristol Myers den Rückgang älterer Medikamente ausgleichen?",
          "einordnung": "Aktionäre sollten genau beobachten, ob die neuen Produkte des Unternehmens ausreichen, um den Umsatzverlust durch Patentabläufe und Konkurrenz bei älteren Medikamenten zu kompensieren.",
          "url": "https://finance.yahoo.com/sectors/healthcare/articles/bristol-myers-growth-portfolio-offset-172000074.html",
          "quelle": "Zacks",
          "datum": "12.06.2026"
        },
        {
          "titel": "Die KI-Umstellung und Onkologie-Studien von Bristol Myers Squibb prägen die Wertentwicklung",
          "einordnung": "Investitionen in KI und erfolgreiche Onkologie-Studien sind entscheidend für die zukünftige Wettbewerbsfähigkeit und das Wachstum des Unternehmens, was für Aktionäre von großer Bedeutung ist.",
          "url": "https://finance.yahoo.com/sectors/healthcare/articles/bristol-myers-squibb-ai-overhaul-051111036.html",
          "quelle": "Simply Wall St.",
          "datum": "12.06.2026"
        },
        {
          "titel": "Warum Bristol Myers Squibb (BMY) heute den Aktienmarkt übertraf",
          "einordnung": "Eine Outperformance gegenüber dem Gesamtmarkt ist ein positives Signal, das Aktionäre dazu anregen sollte, die Gründe für diese Stärke zu analysieren.",
          "url": "https://finance.yahoo.com/markets/stocks/articles/why-bristol-myers-squibb-bmy-214503162.html",
          "quelle": "Zacks",
          "datum": "11.06.2026"
        },
        {
          "titel": "Takeda entwickelte eine Psoriasis-Pille mittels KI. Sie schlug Bristols Sotyktu in einem direkten Vergleichstest deutlich.",
          "einordnung": "Diese Nachricht ist negativ, da ein Konkurrenzprodukt von Takeda ein wichtiges Medikament von Bristol Myers Squibb übertrifft, was den zukünftigen Marktanteil und Umsatz beeinträchtigen könnte.",
          "url": "https://www.investors.com/news/technology/takeda-pharmaceutical-ai-designed-psoriasis-pill-bristol-myers-squibb-sotyktu/?src=A00220&yptr=yahoo",
          "quelle": "Investor's Business Daily",
          "datum": "11.06.2026"
        }
      ],
      "fehler": null
    },
    {
      "wkn": "916018",
      "name": "Brit. American Tobacco",
      "ticker": "BTI",
      "currency": "EUR",
      "price": 53.69,
      "change_1d_pct": 1.24,
      "change_1w_pct": 4.07,
      "change_1m_pct": -4.9,
      "change_1y_pct": 35.49,
      "week52_high": 58.14,
      "week52_low": 40.07,
      "div_yield": null,
      "div_rate": 2.89,
      "market_cap": "134.3B",
      "pe_ratio": 13.34,
      "sparkline": [
        50.7196,
        50.4086,
        51.3157,
        51.4539,
        50.1753,
        50.3481,
        52.2141,
        54.9786,
        56.4559,
        57.6221,
        56.2312,
        57.3198,
        57.0692,
        56.4127,
        56.7841,
        56.4645,
        56.1017,
        55.3242,
        54.3566,
        53.3804,
        52.6979,
        52.2314,
        50.6418,
        49.9766,
        51.5921,
        51.5662,
        51.7908,
        52.8016,
        53.0348,
        53.6914
      ],
      "analyst_rating": "Starker Kauf",
      "analyst_target": 58.35,
      "analyst_count": 5,
      "news": [
        {
          "titel": "Ist es zu spät, British American Tobacco (LSE:BATS) nach starken mehrjährigen Gewinnen noch in Betracht zu ziehen?",
          "einordnung": "Aktionäre sollten prüfen, ob das aktuelle Kursniveau noch attraktives Wachstumspotenzial bietet oder ob eine Korrektur wahrscheinlicher ist.",
          "url": "https://finance.yahoo.com/markets/stocks/articles/too-consider-british-american-tobacco-061217117.html",
          "quelle": "Simply Wall St.",
          "datum": "11.06.2026"
        },
        {
          "titel": "Wall-Street-Analysten halten British American Tobacco (BTI) für eine gute Investition: Ist sie das wirklich?",
          "einordnung": "Aktionäre sollten die Meinungen der Analysten kritisch hinterfragen und eigene Recherchen anstellen, um die Investitionsentscheidung zu validieren.",
          "url": "https://finance.yahoo.com/markets/stocks/articles/wall-street-analysts-think-british-133005020.html",
          "quelle": "Zacks",
          "datum": "10.06.2026"
        },
        {
          "titel": "Wie 350.000 US-Dollar in internationalen Dividendenaktien 19.000 US-Dollar pro Jahr generieren und das US-Konzentrationsrisiko reduzieren können.",
          "einordnung": "Dieser Artikel bietet Aktionären Einblicke in Strategien zur Diversifizierung ihres Portfolios und zur Generierung passiven Einkommens durch internationale Dividenden.",
          "url": "https://247wallst.com/personal-finance/2026/06/07/how-350000-in-dividend-paying-international-stocks-quietly-pays-19000-a-year-and-diversifies-away-from-u-s-concentration/",
          "quelle": "24/7 Wall St.",
          "datum": "07.06.2026"
        },
        {
          "titel": "Europäische Aktien, die in den USA als American Depositary Receipts gehandelt werden, fallen im Freitagshandel; steigen aber über die Woche.",
          "einordnung": "Aktionäre von ADRs sollten die kurzfristigen Schwankungen im Kontext der wöchentlichen Performance betrachten und nicht überreagieren.",
          "url": "https://finance.yahoo.com/markets/world-indices/articles/european-equities-traded-us-american-150640688.html",
          "quelle": "MT Newswires",
          "datum": "05.06.2026"
        }
      ],
      "fehler": null
    },
    {
      "wkn": "878841",
      "name": "Cisco Systems",
      "ticker": "CSCO",
      "currency": "EUR",
      "price": 104.46,
      "change_1d_pct": -0.75,
      "change_1w_pct": -0.59,
      "change_1m_pct": 18.7,
      "change_1y_pct": 90.02,
      "week52_high": 112.63,
      "week52_low": 55.23,
      "div_yield": null,
      "div_rate": 1.45,
      "market_cap": "476.6B",
      "pe_ratio": 40.3,
      "sparkline": [
        79.3492,
        80.0231,
        81.4658,
        79.1678,
        79.617,
        83.4268,
        85.2842,
        85.7766,
        88.0055,
        99.8064,
        102.1216,
        102.7004,
        99.6768,
        98.787,
        102.113,
        104.0222,
        102.2253,
        103.3829,
        102.4931,
        104.0308,
        104.817,
        110.5792,
        109.2833,
        112.307,
        105.0848,
        107.2532,
        103.979,
        102.6313,
        105.2489,
        104.4628
      ],
      "analyst_rating": "Kaufen",
      "analyst_target": 109.28,
      "analyst_count": 22,
      "news": [
        {
          "titel": "Was die Cisco-Aktie wirklich über KI aussagte.",
          "einordnung": "Aktionäre sollten analysieren, wie Cisco von der KI-Entwicklung profitiert oder betroffen ist, um die zukünftige Performance besser einschätzen zu können.",
          "url": "https://www.trefis.com/articles/602700/what-cisco-stock-was-really-saying-about-ai/2026-06-12",
          "quelle": "Trefis",
          "datum": "12.06.2026"
        },
        {
          "titel": "Warum ist Cisco (CSCO) seit dem letzten Gewinnbericht um 5,5 % gestiegen?",
          "einordnung": "Aktionäre sollten die Gründe für den Kursanstieg nach den Quartalszahlen verstehen, um die Nachhaltigkeit dieser Entwicklung beurteilen zu können.",
          "url": "https://finance.yahoo.com/markets/stocks/articles/why-cisco-csco-5-5-153003781.html",
          "quelle": "Zacks",
          "datum": "12.06.2026"
        },
        {
          "titel": "Cisco Systems (CSCO) hat kürzlich den 20-Tage-Durchschnitt überschritten.",
          "einordnung": "Dies könnte ein positives technisches Signal für Aktionäre sein, das auf eine kurzfristige Aufwärtsbewegung hindeutet.",
          "url": "https://finance.yahoo.com/markets/stocks/articles/cisco-systems-csco-recently-broke-133502558.html",
          "quelle": "Zacks",
          "datum": "12.06.2026"
        },
        {
          "titel": "Anleger suchen intensiv nach Cisco Systems, Inc. (CSCO): Das müssen Sie wissen.",
          "einordnung": "Aktionäre sollten die hier präsentierten Informationen nutzen, um ein umfassendes Bild von Cisco zu erhalten und fundierte Entscheidungen zu treffen.",
          "url": "https://finance.yahoo.com/markets/stocks/articles/investors-heavily-search-cisco-systems-130006486.html",
          "quelle": "Zacks",
          "datum": "12.06.2026"
        }
      ],
      "fehler": null
    },
    {
      "wkn": "A0MW32",
      "name": "CME Group",
      "ticker": "CME",
      "currency": "EUR",
      "price": 231.89,
      "change_1d_pct": 2.38,
      "change_1w_pct": 4.82,
      "change_1m_pct": -9.19,
      "change_1y_pct": 2.92,
      "week52_high": 284.36,
      "week52_low": 211.28,
      "div_yield": null,
      "div_rate": 4.49,
      "market_cap": "97.0B",
      "pe_ratio": 22.9,
      "sparkline": [
        248.8434,
        249.488,
        246.5057,
        247.812,
        246.5315,
        241.7186,
        242.8616,
        245.5861,
        255.3666,
        255.8564,
        256.8534,
        262.2335,
        259.87,
        249.3418,
        248.6285,
        250.2959,
        242.8273,
        239.8708,
        238.4269,
        235.0923,
        221.5303,
        215.3165,
        217.1299,
        220.0692,
        221.2209,
        216.6056,
        221.1066,
        227.8968,
        226.4973,
        231.888
      ],
      "analyst_rating": "Halten",
      "analyst_target": 264.3,
      "analyst_count": 15,
      "news": [
        {
          "titel": "CME Group fügt vier E-mini-Futures für breite Marktpräsenz hinzu.",
          "einordnung": "Dies erweitert die Handelsmöglichkeiten für institutionelle Anleger und könnte die Liquidität und Attraktivität der CME-Plattform steigern.",
          "url": "https://finance.yahoo.com/markets/options/articles/cme-group-adds-four-e-173800795.html",
          "quelle": "Zacks",
          "datum": "12.06.2026"
        },
        {
          "titel": "3 Large-Cap-Aktien, die wir nicht auf unserem Radar haben.",
          "einordnung": "Aktionäre sollten prüfen, ob ihre eigenen Bestände zu den genannten Aktien gehören und die Gründe für die negative Einschätzung nachvollziehen.",
          "url": "https://finance.yahoo.com/markets/stocks/articles/3-large-cap-stocks-keep-114920397.html",
          "quelle": "StockStory",
          "datum": "12.06.2026"
        },
        {
          "titel": "Die Wall Street nimmt Cardano auf – doch ADA liegt auf einem 5-Jahres-Tief.",
          "einordnung": "Aktionäre, die an Kryptowährungen interessiert sind, sollten die Diskrepanz zwischen institutionellem Interesse und dem aktuellen Kurs von Cardano genau analysieren.",
          "url": "https://beincrypto.com/cardano-ada-price-five-year-low-cme-futures/",
          "quelle": "BeInCrypto",
          "datum": "12.06.2026"
        },
        {
          "titel": "SpaceX initiiert, Intel hochgestuft: Die Top-Analystenempfehlungen der Wall Street.",
          "einordnung": "Aktionäre sollten diese Analystenempfehlungen als eine von vielen Informationsquellen betrachten und eigene Due Diligence betreiben.",
          "url": "https://finance.yahoo.com/markets/stocks/articles/intel-upgraded-reddit-initiated-wall-140337510.html",
          "quelle": "The Fly",
          "datum": "11.06.2026"
        }
      ],
      "fehler": null
    },
    {
      "wkn": "547030",
      "name": "CTS Eventim",
      "ticker": "EVD.DE",
      "currency": "EUR",
      "price": 50.45,
      "change_1d_pct": 1.59,
      "change_1w_pct": -7.09,
      "change_1m_pct": -7.43,
      "change_1y_pct": -51.5,
      "week52_high": 107.0,
      "week52_low": 48.68,
      "div_yield": null,
      "div_rate": 1.44,
      "market_cap": "4.8B",
      "pe_ratio": 16.43,
      "sparkline": [
        53.0341,
        52.7416,
        54.2039,
        54.7401,
        54.3989,
        53.9115,
        53.8627,
        52.4979,
        54.4964,
        54.1552,
        54.0577,
        54.7401,
        54.7401,
        54.4964,
        54.8376,
        55.8125,
        55.5688,
        55.91,
        56.15,
        62.15,
        61.15,
        57.8,
        55.15,
        55.8,
        54.3,
        51.4,
        50.9,
        50.0,
        49.66,
        50.45
      ],
      "analyst_rating": "Kaufen",
      "analyst_target": 88.62,
      "analyst_count": 12,
      "news": [
        {
          "titel": "Umsatz übertroffen: CTS Eventim AG & Co. KGaA übertraf die Analystenschätzungen um 14 %.",
          "einordnung": "Dies ist ein starkes positives Signal für Aktionäre, das auf eine robuste Geschäftsentwicklung und potenziellen Kursanstieg hindeutet.",
          "url": "https://finance.yahoo.com/markets/stocks/articles/revenue-beat-cts-eventim-ag-070015855.html",
          "quelle": "Simply Wall St.",
          "datum": "31.05.2026"
        },
        {
          "titel": "CTS Eventim-Aktien springen nach oben, da US-Tourneen und Winterspiele die Gewinne antreiben.",
          "einordnung": "Aktionäre können sich über die positiven Auswirkungen großer Events auf die Unternehmensgewinne freuen, was den Aktienkurs stützt.",
          "url": "https://www.wsj.com/business/cts-eventim-shares-jump-after-u-s-tours-winter-olympics-drive-earnings-5e4e932e?siteid=yhoof2&yptr=yahoo",
          "quelle": "The Wall Street Journal",
          "datum": "29.05.2026"
        },
        {
          "titel": "CTS Eventim AG & Co. KGaA (CEVMF) Q1 2026 Gewinn-Telefonkonferenz-Highlights: Starkes Umsatzwachstum ...",
          "einordnung": "Aktionäre sollten die vollständigen Highlights der Telefonkonferenz prüfen, um die Details des starken Umsatzwachstums und die Zukunftsaussichten zu verstehen.",
          "url": "https://finance.yahoo.com/markets/stocks/articles/cts-eventim-ag-co-kgaa-010021245.html",
          "quelle": "GuruFocus.com",
          "datum": "29.05.2026"
        },
        {
          "titel": "CTS Eventim AG & Co. KGaA Q1 Gewinn-Telefonkonferenz-Highlights.",
          "einordnung": "Aktionäre sollten diese Zusammenfassung nutzen, um schnell die wichtigsten Informationen zur Geschäftsentwicklung und den Zukunftsaussichten zu erfassen.",
          "url": "https://www.marketbeat.com/instant-alerts/cts-eventim-ag-co-kgaa-q1-earnings-call-highlights-2026-05-28/?utm_source=yahoofinance&utm_medium=yahoofinance",
          "quelle": "MarketBeat",
          "datum": "28.05.2026"
        }
      ],
      "fehler": null
    },
    {
      "wkn": "887891",
      "name": "Fastenal",
      "ticker": "FAST",
      "currency": "EUR",
      "price": 40.24,
      "change_1d_pct": 0.41,
      "change_1w_pct": -0.46,
      "change_1m_pct": 6.41,
      "change_1y_pct": 10.94,
      "week52_high": 43.74,
      "week52_low": 33.67,
      "div_yield": null,
      "div_rate": 0.79,
      "market_cap": "53.5B",
      "pe_ratio": 41.22,
      "sparkline": [
        38.7977,
        38.7718,
        38.2967,
        38.625,
        38.3226,
        38.1585,
        37.4069,
        37.4241,
        37.8129,
        37.9943,
        37.3723,
        38.0116,
        37.6401,
        37.7352,
        37.6056,
        37.9598,
        38.4004,
        38.72,
        38.6682,
        38.1844,
        38.003,
        38.6422,
        40.1368,
        40.7415,
        40.4219,
        39.7394,
        40.2405,
        39.7653,
        40.0763,
        40.2361
      ],
      "analyst_rating": "Halten",
      "analyst_target": 40.36,
      "analyst_count": 11,
      "news": [
        {
          "titel": "Mit EPS-Wachstum und mehr: Fastenal (NASDAQ:FAST) ist ein interessanter Fall.",
          "einordnung": "Aktionäre sollten die detaillierten Gründe für die positive Einschätzung, insbesondere das EPS-Wachstum, analysieren, um das Investitionspotenzial zu bewerten.",
          "url": "https://finance.yahoo.com/markets/stocks/articles/eps-growth-more-fastenal-nasdaq-120011587.html",
          "quelle": "Simply Wall St.",
          "datum": "11.06.2026"
        },
        {
          "titel": "1 Überflieger-Aktie auf unserer Beobachtungsliste und 2, die wir hinterfragen.",
          "einordnung": "Aktionäre sollten prüfen, ob Fastenal die 'Überflieger-Aktie' ist und die Gründe für die positive Einschätzung verstehen.",
          "url": "https://finance.yahoo.com/markets/stocks/articles/1-high-flying-stock-watchlist-122214347.html",
          "quelle": "StockStory",
          "datum": "09.06.2026"
        },
        {
          "titel": "Schneidet die Fastenal-Aktie schlechter ab als der Nasdaq?",
          "einordnung": "Aktionäre sollten die Performance von Fastenal im Vergleich zum Gesamtmarkt analysieren, um die relative Stärke oder Schwäche der Aktie zu beurteilen.",
          "url": "https://www.barchart.com/story/news/2375234/is-fastenal-stock-underperforming-the-nasdaq",
          "quelle": "Barchart",
          "datum": "09.06.2026"
        },
        {
          "titel": "3 Nasdaq 100 Aktien, die es wert sind, untersucht zu werden.",
          "einordnung": "Aktionäre sollten prüfen, ob Fastenal zu diesen drei Aktien gehört und die Argumente für eine nähere Betrachtung nachvollziehen.",
          "url": "https://finance.yahoo.com/markets/stocks/articles/3-nasdaq-100-stocks-worth-161350339.html",
          "quelle": "StockStory",
          "datum": "08.06.2026"
        }
      ],
      "fehler": null
    },
    {
      "wkn": "853260",
      "name": "Johnson & Johnson",
      "ticker": "JNJ",
      "currency": "EUR",
      "price": 207.41,
      "change_1d_pct": 0.73,
      "change_1w_pct": 3.14,
      "change_1m_pct": 4.79,
      "change_1y_pct": 57.08,
      "week52_high": 217.45,
      "week52_low": 128.76,
      "div_yield": null,
      "div_rate": 4.63,
      "market_cap": "577.9B",
      "pe_ratio": 27.82,
      "sparkline": [
        195.1471,
        192.5788,
        193.7384,
        192.9396,
        191.1272,
        190.105,
        190.1995,
        192.6304,
        197.9216,
        198.248,
        194.7348,
        196.6331,
        197.5608,
        196.9767,
        199.0468,
        201.2887,
        198.8525,
        199.8114,
        199.3881,
        194.6626,
        193.0903,
        192.5547,
        192.857,
        197.1161,
        201.09,
        200.563,
        204.7443,
        206.0315,
        205.8933,
        207.4051
      ],
      "analyst_rating": "Kaufen",
      "analyst_target": 218.45,
      "analyst_count": 23,
      "news": [
        {
          "titel": "JNJ hat die Messlatte höher gelegt: Warum stagniert die Aktie trotzdem?",
          "einordnung": "Dieser Titel deutet auf eine mögliche Diskrepanz zwischen positiven Unternehmensentwicklungen und der Aktienperformance hin, was eine genauere Analyse der Gründe erfordert.",
          "url": "https://www.trefis.com/articles/602698/jnj-raised-the-bar-so-why-is-the-stock-standing-still/2026-06-12",
          "quelle": "Trefis",
          "datum": "12.06.2026"
        },
        {
          "titel": "Johnson & Johnson hat gerade 1 Milliarde Dollar für eine Technologie bezahlt, die eines der „unbehandelbarsten“ Krebsziele knacken könnte. Warum das sehr gute Nachrichten für Investoren sind.",
          "einordnung": "Diese Akquisition könnte langfristig erhebliche Wachstumschancen und einen Wettbewerbsvorteil im Pharmasektor für J&J bedeuten.",
          "url": "https://www.fool.com/investing/2026/06/12/johnson-johnson-just-paid-1-billion-for-a-technolo/",
          "quelle": "Motley Fool",
          "datum": "12.06.2026"
        },
        {
          "titel": "Der Haken, der sich in der Wachstumsgeschichte der Eli Lilly Aktie verbirgt.",
          "einordnung": "Dieser Titel warnt davor, dass die scheinbar starke Wachstumsgeschichte von Eli Lilly möglicherweise versteckte Risiken oder Herausforderungen birgt, die Investoren beachten sollten.",
          "url": "https://www.trefis.com/articles/602703/the-catch-hiding-in-eli-lilly-stocks-growth-story/2026-06-12",
          "quelle": "Trefis",
          "datum": "12.06.2026"
        },
        {
          "titel": "Wie man 12.000 Dollar monatliches Dividendeneinkommen aufbaut (und warum die meisten Investoren die Kosten unterschätzen).",
          "einordnung": "Dieser Titel bietet eine Perspektive auf den Aufbau eines substanziellen Dividendeneinkommens, warnt aber gleichzeitig vor den oft übersehenen Kapitalkosten und dem Aufwand.",
          "url": "https://247wallst.com/personal-finance/2026/06/12/how-to-build-12000-a-month-in-dividend-income-and-why-most-investors-underestimate-the-cost/",
          "quelle": "24/7 Wall St.",
          "datum": "12.06.2026"
        }
      ],
      "fehler": null
    },
    {
      "wkn": "A0RLRP",
      "name": "Koei Tecmo",
      "ticker": "3635.T",
      "currency": "EUR",
      "price": 7.89,
      "change_1d_pct": -1.01,
      "change_1w_pct": -0.51,
      "change_1m_pct": -1.01,
      "change_1y_pct": -33.99,
      "week52_high": 13.0,
      "week52_low": 7.7,
      "div_yield": null,
      "div_rate": 0.26,
      "market_cap": "488.8B",
      "pe_ratio": 11.11,
      "sparkline": [
        8.6077,
        8.2895,
        8.1816,
        8.3461,
        8.2895,
        8.2625,
        8.3219,
        8.2625,
        7.9713,
        8.187,
        8.0495,
        8.3785,
        8.2787,
        8.2464,
        8.2571,
        8.0899,
        8.0873,
        8.2032,
        8.0765,
        7.9875,
        8.1735,
        8.2113,
        7.9551,
        7.823,
        7.9308,
        7.9875,
        7.9929,
        8.0198,
        7.9713,
        7.8904
      ],
      "analyst_rating": "Kaufen",
      "analyst_target": 10.86,
      "analyst_count": 9,
      "news": [
        {
          "titel": "Koei Tecmo (TSE:3635): Bewertung nach neuem Verkauf eigener Aktien und Details zur Kapitalerhöhung.",
          "einordnung": "Dieser Titel weist darauf hin, dass die jüngsten Kapitalmaßnahmen von Koei Tecmo eine Neubewertung der Aktie erforderlich machen, um die Auswirkungen auf den Shareholder Value zu verstehen.",
          "url": "https://finance.yahoo.com/news/koei-tecmo-tse-3635-assessing-112338756.html",
          "quelle": "Simply Wall St.",
          "datum": "15.09.2025"
        }
      ],
      "fehler": null
    },
    {
      "wkn": "856958",
      "name": "McDonald's",
      "ticker": "MCD",
      "currency": "EUR",
      "price": 246.13,
      "change_1d_pct": 0.05,
      "change_1w_pct": 1.81,
      "change_1m_pct": 4.04,
      "change_1y_pct": -3.74,
      "week52_high": 295.24,
      "week52_low": 234.85,
      "div_yield": null,
      "div_rate": 6.43,
      "market_cap": "202.4B",
      "pe_ratio": 23.49,
      "sparkline": [
        245.9602,
        243.7806,
        244.6988,
        243.7806,
        243.4374,
        236.6157,
        235.6289,
        235.8348,
        236.5728,
        235.9464,
        237.1649,
        242.382,
        240.949,
        240.4942,
        243.8493,
        242.2103,
        239.6275,
        241.052,
        238.5206,
        239.576,
        236.9245,
        238.7474,
        236.0952,
        235.6028,
        241.7538,
        239.9741,
        243.8358,
        244.069,
        246.0128,
        246.1251
      ],
      "analyst_rating": "Kaufen",
      "analyst_target": 286.2,
      "analyst_count": 31,
      "news": [
        {
          "titel": "McDonald's wird 2028 zu diesem Preis gehandelt werden.",
          "einordnung": "Dieser Titel präsentiert eine spekulative Preisprognose für die McDonald's-Aktie in der Zukunft, die Investoren als Diskussionsgrundlage für ihre eigenen Analysen nutzen können.",
          "url": "https://247wallst.com/investing/2026/06/12/mcdonalds-will-trade-at-this-price-in-2028/",
          "quelle": "24/7 Wall St.",
          "datum": "12.06.2026"
        },
        {
          "titel": "Die Dividendenwachstumsstrategie, die 50.000 Dollar pro Jahr in 125.000 Dollar verwandelt, ohne einen weiteren Dollar zu investieren.",
          "einordnung": "Dieser Titel beschreibt eine attraktive Dividendenstrategie, die auf dem Reinvestieren von Erträgen basiert, um das Einkommen ohne zusätzliche Kapitaleinlagen zu steigern.",
          "url": "https://247wallst.com/personal-finance/2026/06/12/the-dividend-growth-strategy-that-turns-50000-a-year-into-125000-without-investing-another-dollar/",
          "quelle": "24/7 Wall St.",
          "datum": "12.06.2026"
        },
        {
          "titel": "Pepsi macht einen mutigen Schritt, um Coca-Cola herauszufordern.",
          "einordnung": "Dieser Titel deutet auf eine verstärkte Wettbewerbsdynamik im Getränkesektor hin, die indirekt auch die Konsumgewohnheiten und damit die Geschäftsaussichten von McDonald's beeinflussen könnte.",
          "url": "https://www.thestreet.com/retail/pepsi-makes-a-bold-move-to-take-on-coca-cola-house-of-treats",
          "quelle": "TheStreet",
          "datum": "11.06.2026"
        },
        {
          "titel": "3 kinderleichte Dividendenwachstumsaktien, die man im Juni kaufen sollte.",
          "einordnung": "Dieser Titel schlägt konkrete Kaufempfehlungen für Dividendenwachstumsaktien vor, die als relativ sichere Investitionen für langfristige Erträge gelten könnten.",
          "url": "https://247wallst.com/investing/2026/06/11/3-no-brainer-dividend-growth-stocks-to-buy-in-june/",
          "quelle": "24/7 Wall St.",
          "datum": "11.06.2026"
        }
      ],
      "fehler": null
    },
    {
      "wkn": "710000",
      "name": "Mercedes-Benz",
      "ticker": "MBG.DE",
      "currency": "EUR",
      "price": 48.02,
      "change_1d_pct": 1.22,
      "change_1w_pct": 0.04,
      "change_1m_pct": -5.89,
      "change_1y_pct": -0.53,
      "week52_high": 62.34,
      "week52_low": 46.88,
      "div_yield": null,
      "div_rate": 3.5,
      "market_cap": "46.0B",
      "pe_ratio": 9.43,
      "sparkline": [
        47.925,
        48.19,
        50.18,
        50.32,
        50.13,
        50.26,
        50.22,
        50.76,
        51.02,
        50.35,
        49.97,
        49.54,
        50.01,
        49.76,
        50.12,
        50.76,
        50.92,
        52.51,
        52.71,
        52.19,
        51.44,
        51.67,
        49.955,
        49.075,
        47.995,
        48.355,
        47.705,
        47.11,
        47.435,
        48.015
      ],
      "analyst_rating": "Kaufen",
      "analyst_target": 60.78,
      "analyst_count": 23,
      "news": [
        {
          "titel": "Mercedes-Benz steigt mit Anti-Drohnen-Fahrzeug in den europäischen Rüstungsboom ein.",
          "einordnung": "Dieser Titel zeigt eine Diversifizierung der Geschäftsfelder von Mercedes-Benz in den Verteidigungssektor, was neue Wachstumschancen und Umsatzströme erschließen könnte.",
          "url": "https://app.moby.co/home/news/news-mercedes-benz-enters-european-rearmament-boom-with-anti-drone-vehicle?utm_source=yahoo_finance&utm_medium=rss",
          "quelle": "Moby",
          "datum": "11.06.2026"
        },
        {
          "titel": "Wirtschaftsprüfer einer kollabierten Schattenbank werden von der Finanzaufsicht untersucht.",
          "einordnung": "Dieser Titel ist nicht direkt auf Mercedes-Benz bezogen, sondern auf eine allgemeine Finanzmarktregulierung, die das Vertrauen in den Finanzsektor und damit indirekt auch die Investitionsbereitschaft beeinflussen kann.",
          "url": "https://uk.finance.yahoo.com/news/auditors-collapsed-shadow-bank-investigated-140702726.html",
          "quelle": "The Telegraph",
          "datum": "11.06.2026"
        },
        {
          "titel": "Vietnams Fahrzeugmarkt wächst im Mai um 7% – VAMA.",
          "einordnung": "Dieser Titel signalisiert ein Wachstum in einem wichtigen Schwellenlandmarkt, was für globale Automobilhersteller wie Mercedes-Benz positive Absatzchancen bedeuten kann.",
          "url": "https://www.just-auto.com/news/vietnam-vehicle-market-expands-by-7-in-may-vama/",
          "quelle": "Just Auto",
          "datum": "10.06.2026"
        },
        {
          "titel": "Preist die Mercedes-Benz Group (XTRA:MBG) nach den jüngsten Kursrückgängen jetzt zu viel Risiko ein?",
          "einordnung": "Dieser Titel regt zur Überlegung an, ob die aktuelle Bewertung der Mercedes-Benz Aktie nach Kursverlusten eine attraktive Einstiegsgelegenheit darstellen könnte, da das Risiko möglicherweise überbewertet wird.",
          "url": "https://finance.yahoo.com/markets/stocks/articles/mercedes-benz-group-xtra-mbg-190926789.html",
          "quelle": "Simply Wall St.",
          "datum": "09.06.2026"
        }
      ],
      "fehler": null
    },
    {
      "wkn": "851995",
      "name": "PepsiCo",
      "ticker": "PEP",
      "currency": "EUR",
      "price": 124.57,
      "change_1d_pct": 0.33,
      "change_1w_pct": 1.61,
      "change_1m_pct": -2.38,
      "change_1y_pct": 13.31,
      "week52_high": 148.14,
      "week52_low": 110.23,
      "div_yield": null,
      "div_rate": 5.11,
      "market_cap": "197.1B",
      "pe_ratio": 22.64,
      "sparkline": [
        134.5707,
        132.1598,
        132.5445,
        133.3311,
        133.6132,
        132.1855,
        127.7314,
        129.8174,
        127.6117,
        127.0988,
        127.4835,
        127.4322,
        128.5521,
        127.6288,
        127.2527,
        128.7231,
        124.5426,
        126.3037,
        125.0641,
        123.2688,
        120.9862,
        121.3966,
        121.8582,
        121.5248,
        122.6047,
        121.5334,
        123.3476,
        124.6781,
        124.1683,
        124.5744
      ],
      "analyst_rating": "Halten",
      "analyst_target": 147.23,
      "analyst_count": 21,
      "news": [
        {
          "titel": "Getränke-, Alkohol- und Tabakaktien im Q1-Rückblick: PepsiCo (NASDAQ:PEP) im Vergleich zu Wettbewerbern.",
          "einordnung": "Dieser Titel bietet eine vergleichende Analyse der Quartalsergebnisse von PepsiCo im Kontext seiner Branche, was für Investoren zur Bewertung der relativen Stärke nützlich ist.",
          "url": "https://finance.yahoo.com/markets/stocks/articles/beverages-alcohol-tobacco-stocks-q1-174920672.html",
          "quelle": "StockStory",
          "datum": "12.06.2026"
        },
        {
          "titel": "Ist Keurig Dr Pepper Inc. (KDP) jetzt eine gute Aktie zum Kauf?",
          "einordnung": "Dieser Titel stellt eine Kaufempfehlung für Keurig Dr Pepper in den Raum, was für Investoren im Getränkesektor eine interessante Alternative oder Ergänzung zu PepsiCo darstellen könnte.",
          "url": "https://finance.yahoo.com/markets/stocks/articles/keurig-dr-pepper-inc-kdp-161652500.html",
          "quelle": "Insider Monkey",
          "datum": "12.06.2026"
        },
        {
          "titel": "AMD hochgestuft, Adobe herabgestuft: Die Top-Analystenempfehlungen der Wall Street.",
          "einordnung": "Dieser Titel fasst wichtige Analystenbewertungen zusammen, die zwar nicht direkt PepsiCo betreffen, aber die allgemeine Marktstimmung und Sektorrotation widerspiegeln können.",
          "url": "https://finance.yahoo.com/markets/stocks/articles/amd-upgraded-adobe-downgraded-wall-133850577.html",
          "quelle": "The Fly",
          "datum": "12.06.2026"
        },
        {
          "titel": "Die Dividendenwachstumsstrategie, die 50.000 Dollar pro Jahr in 125.000 Dollar verwandelt, ohne einen weiteren Dollar zu investieren.",
          "einordnung": "Dieser Titel beschreibt eine attraktive Dividendenstrategie, die auf dem Reinvestieren von Erträgen basiert, um das Einkommen ohne zusätzliche Kapitaleinlagen zu steigern.",
          "url": "https://247wallst.com/personal-finance/2026/06/12/the-dividend-growth-strategy-that-turns-50000-a-year-into-125000-without-investing-another-dollar/",
          "quelle": "24/7 Wall St.",
          "datum": "12.06.2026"
        }
      ],
      "fehler": null
    },
    {
      "wkn": "899744",
      "name": "Realty Income",
      "ticker": "O",
      "currency": "EUR",
      "price": 54.14,
      "change_1d_pct": 1.23,
      "change_1w_pct": 3.01,
      "change_1m_pct": 2.32,
      "change_1y_pct": 14.16,
      "week52_high": 58.69,
      "week52_low": 48.26,
      "div_yield": null,
      "div_rate": 2.81,
      "market_cap": "58.4B",
      "pe_ratio": 51.37,
      "sparkline": [
        54.8833,
        54.5737,
        54.6769,
        55.0553,
        53.1459,
        53.2577,
        53.6361,
        53.7824,
        52.9137,
        53.2921,
        52.5696,
        53.0771,
        53.4039,
        53.5329,
        53.5243,
        53.3437,
        53.7136,
        53.4899,
        53.0599,
        52.9398,
        51.4452,
        51.7562,
        51.5921,
        51.618,
        52.5597,
        51.8426,
        52.9139,
        53.6568,
        53.484,
        54.1406
      ],
      "analyst_rating": "Kaufen",
      "analyst_target": 58.87,
      "analyst_count": 20,
      "news": [
        {
          "titel": "Wie man 12.000 Dollar monatliches Dividendeneinkommen aufbaut (und warum die meisten Investoren die Kosten unterschätzen).",
          "einordnung": "Dieser Titel bietet eine Perspektive auf den Aufbau eines substanziellen Dividendeneinkommens, warnt aber gleichzeitig vor den oft übersehenen Kapitalkosten und dem Aufwand.",
          "url": "https://247wallst.com/personal-finance/2026/06/12/how-to-build-12000-a-month-in-dividend-income-and-why-most-investors-underestimate-the-cost/",
          "quelle": "24/7 Wall St.",
          "datum": "12.06.2026"
        },
        {
          "titel": "Die 5,3% Rendite von Realty Income ist ein Schnäppchen: Warum ein sich änderndes Zinsumfeld diese monatliche Dividendenmaschine zu einem Top-Kauf für Rentner macht.",
          "einordnung": "Dieser Titel hebt die Attraktivität der hohen Dividendenrendite von Realty Income hervor, insbesondere im aktuellen Zinsumfeld, was es zu einer potenziellen Kerninvestition für Einkommenssuchende macht.",
          "url": "https://247wallst.com/investing/2026/06/12/realty-incomes-5-3-yield-is-a-steal-why-a-shifting-interest-rate-environment-makes-this-monthly-dividend-machine-a-top-buy-for-retirees/",
          "quelle": "24/7 Wall St.",
          "datum": "12.06.2026"
        },
        {
          "titel": "W.P. Carey kündigt Dividendenerhöhung an: Ist die Erhöhung nachhaltig?",
          "einordnung": "Dieser Titel informiert über eine Dividendenerhöhung bei einem Konkurrenten von Realty Income und wirft die wichtige Frage nach der Nachhaltigkeit solcher Ausschüttungen auf, die für Dividendeninvestoren entscheidend ist.",
          "url": "https://finance.yahoo.com/markets/stocks/articles/w-p-carey-announces-dividend-130600366.html",
          "quelle": "Zacks",
          "datum": "12.06.2026"
        },
        {
          "titel": "Realty Income Corporation (O) ist eine Trendaktie: Fakten, die man vor einer Investition kennen sollte.",
          "einordnung": "Eine Trendaktie kann kurzfristige Chancen bieten, erfordert aber eine gründliche Analyse der Fundamentaldaten, um langfristige Risiken zu vermeiden.",
          "url": "https://finance.yahoo.com/markets/stocks/articles/realty-income-corporation-o-trending-130004914.html",
          "quelle": "Zacks",
          "datum": "12.06.2026"
        }
      ],
      "fehler": null
    },
    {
      "wkn": "852147",
      "name": "Rio Tinto",
      "ticker": "RIO",
      "currency": "EUR",
      "price": 90.74,
      "change_1d_pct": 1.35,
      "change_1w_pct": 4.32,
      "change_1m_pct": -6.25,
      "change_1y_pct": 88.47,
      "week52_high": 97.26,
      "week52_low": 48.07,
      "div_yield": null,
      "div_rate": 3.47,
      "market_cap": "170.8B",
      "pe_ratio": 17.28,
      "sparkline": [
        86.8911,
        85.2065,
        86.822,
        91.1501,
        89.0767,
        91.0378,
        93.2148,
        94.597,
        96.7914,
        94.6748,
        89.5778,
        89.2668,
        87.1848,
        89.2495,
        90.5022,
        90.0443,
        92.3855,
        92.1004,
        91.9794,
        91.9103,
        94.1305,
        96.4717,
        93.1803,
        91.0551,
        86.9861,
        87.1934,
        87.6167,
        85.5779,
        89.5346,
        90.7441
      ],
      "analyst_rating": "Kaufen",
      "analyst_target": 88.87,
      "analyst_count": 7,
      "news": [
        {
          "titel": "Rechtfertigt Albemarles Premium-Bewertung den Kauf der Aktie jetzt?",
          "einordnung": "Eine hohe Bewertung kann auf starkes Wachstumspotenzial hindeuten, birgt aber auch das Risiko einer Korrektur, falls die Erwartungen nicht erfüllt werden.",
          "url": "https://finance.yahoo.com/markets/stocks/articles/does-albemarles-premium-valuation-justify-114400624.html",
          "quelle": "Zacks",
          "datum": "12.06.2026"
        },
        {
          "titel": "Sandvik (SAND) kooperiert mit Rio Tinto (RIO) zur Integration autonomer Bohrsysteme.",
          "einordnung": "Diese Partnerschaft könnte die Effizienz und Sicherheit der Bergbauoperationen von Rio Tinto verbessern und somit langfristig die Profitabilität steigern.",
          "url": "https://finance.yahoo.com/markets/stocks/articles/sandvik-sand-collaborates-rio-tinto-195558723.html",
          "quelle": "Insider Monkey",
          "datum": "11.06.2026"
        },
        {
          "titel": "Kupferpreis-Rallye verblasst, da Trumps Zollwetten an Schwung verlieren; Bergbauaktien schwanken.",
          "einordnung": "Ein nachlassender Kupferpreis und politische Unsicherheiten können kurzfristig Druck auf Bergbauaktien ausüben, was eine genaue Beobachtung der Rohstoffmärkte erfordert.",
          "url": "https://www.investors.com/news/copper-price-trump-tariffs-loom-bhp-rio-fcx-mining-stocks-buy-points/?src=A00220&yptr=yahoo",
          "quelle": "Investor's Business Daily",
          "datum": "09.06.2026"
        },
        {
          "titel": "3 Multi-Metall-Aktien für Einkommen und langfristiges Wachstum.",
          "einordnung": "Multi-Metall-Aktien bieten oft eine Diversifikation innerhalb des Rohstoffsektors und können sowohl stabile Dividenden als auch Wachstumspotenzial bieten.",
          "url": "https://www.marketbeat.com/articles/3-multi-metal-stocks-for-income-and-long-term-growth/?utm_source=yahoofinance&utm_medium=yahoofinance",
          "quelle": "MarketBeat",
          "datum": "08.06.2026"
        }
      ],
      "fehler": null
    },
    {
      "wkn": "A3C99G",
      "name": "Shell",
      "ticker": "SHELL.AS",
      "currency": "EUR",
      "price": 37.31,
      "change_1d_pct": -1.61,
      "change_1w_pct": -0.23,
      "change_1m_pct": 3.75,
      "change_1y_pct": 26.31,
      "week52_high": 41.33,
      "week52_low": 29.55,
      "div_yield": null,
      "div_rate": 1.34,
      "market_cap": "207.0B",
      "pe_ratio": 13.42,
      "sparkline": [
        38.0754,
        37.9863,
        36.7641,
        35.7151,
        35.5172,
        35.8537,
        36.0318,
        35.9378,
        35.9625,
        36.2248,
        37.4519,
        37.536,
        37.2144,
        37.455,
        37.11,
        36.69,
        36.94,
        36.035,
        36.215,
        35.975,
        36.955,
        37.215,
        37.825,
        37.315,
        37.395,
        37.45,
        36.84,
        37.54,
        37.92,
        37.31
      ],
      "analyst_rating": "Kaufen",
      "analyst_target": 42.79,
      "analyst_count": 7,
      "news": [
        {
          "titel": "Shell (SHEL) setzt verstärkt auf fossile Brennstoffe – Berichten zufolge plant man den Verkauf von Offshore-Windparks im Wert von 1 Mrd. US-Dollar.",
          "einordnung": "Diese strategische Neuausrichtung könnte kurzfristig die Profitabilität aus dem Kerngeschäft stärken, wirft aber Fragen zur langfristigen Dekarbonisierungsstrategie des Unternehmens auf.",
          "url": "https://stocktwits.com/news-articles/markets/equity/shell-eyes-1-billion-offshore-wind-sale-leans-into-fossil-fuels/cZKdcyLR755",
          "quelle": "Stocktwits",
          "datum": "12.06.2026"
        },
        {
          "titel": "Shells Rückkehr nach Venezuela gewinnt mit dem Loran-Gas-Deal an Schwung.",
          "einordnung": "Die Wiederaufnahme von Aktivitäten in Venezuela könnte Shell neue Gasreserven erschließen, birgt jedoch auch politische und operative Risiken.",
          "url": "https://finance.yahoo.com/sectors/energy/articles/shells-venezuela-return-gains-momentum-125400325.html",
          "quelle": "Zacks",
          "datum": "12.06.2026"
        },
        {
          "titel": "Shell positioniert sich frühzeitig für Venezuelas Comeback.",
          "einordnung": "Ein frühes Engagement in Venezuela könnte Shell einen Wettbewerbsvorteil verschaffen, erfordert aber eine sorgfältige Abwägung der geopolitischen und wirtschaftlichen Unsicherheiten.",
          "url": "https://finance.yahoo.com/sectors/energy/articles/shell-moves-early-venezuelas-comeback-121220041.html",
          "quelle": "GuruFocus.com",
          "datum": "12.06.2026"
        },
        {
          "titel": "Shells CEO warnt, dass die Ölpreise auch lange nach Kriegsende weiter steigen werden. Das bedeutet es für Ölaktien.",
          "einordnung": "Die Prognose des CEOs deutet auf anhaltend hohe Gewinne für Ölkonzerne hin, was die Attraktivität von Ölaktien als Inflationsschutz und für Dividenden steigern könnte.",
          "url": "https://www.fool.com/investing/2026/06/11/shells-ceo-warns-that-oil-prices-will-continue-rising-long-after-the-war-ends-heres-what-that-means-for-oil-stocks/",
          "quelle": "Motley Fool",
          "datum": "11.06.2026"
        }
      ],
      "fehler": null
    },
    {
      "wkn": "723133",
      "name": "Sixt",
      "ticker": "SIX2.DE",
      "currency": "EUR",
      "price": 74.55,
      "change_1d_pct": 2.97,
      "change_1w_pct": 4.93,
      "change_1m_pct": 3.33,
      "change_1y_pct": -3.43,
      "week52_high": 98.7,
      "week52_low": 57.7,
      "div_yield": null,
      "div_rate": 3.2,
      "market_cap": "3.5B",
      "pe_ratio": 11.68,
      "sparkline": [
        68.5,
        67.65,
        69.5,
        69.7,
        70.15,
        69.75,
        69.0,
        71.3,
        72.15,
        71.05,
        70.8,
        70.8,
        71.8,
        71.2,
        72.25,
        73.35,
        73.85,
        74.0,
        74.5,
        76.5,
        73.8,
        73.1,
        73.25,
        72.7,
        71.05,
        73.25,
        71.95,
        73.15,
        72.4,
        74.55
      ],
      "analyst_rating": "none",
      "analyst_target": 95.43,
      "analyst_count": 7,
      "news": [
        {
          "titel": "Ecos (India) Mobility & Hospitality Ltd (NSE:ECOSMOBLTY) Q4 2026 Gewinnmitteilung-Highlights: ...",
          "einordnung": "Gewinnmitteilungen geben wichtige Einblicke in die finanzielle Performance und Zukunftsaussichten eines Unternehmens, die für Investitionsentscheidungen entscheidend sind.",
          "url": "https://finance.yahoo.com/markets/stocks/articles/ecos-india-mobility-hospitality-ltd-010150184.html",
          "quelle": "GuruFocus.com",
          "datum": "30.05.2026"
        },
        {
          "titel": "Sixt SE (ETR:SIX2) hat gerade die Ergebnisse des ersten Quartals veröffentlicht: Haben Analysten ihre Meinung zur Aktie geändert?",
          "einordnung": "Aktuelle Quartalsergebnisse und die Reaktion der Analysten sind entscheidend, um die kurz- und mittelfristige Kursentwicklung der Sixt-Aktie einzuschätzen.",
          "url": "https://finance.yahoo.com/markets/stocks/articles/sixt-se-etr-six2-just-060916116.html",
          "quelle": "Simply Wall St.",
          "datum": "16.05.2026"
        },
        {
          "titel": "Eine Betrachtung der Sixt (XTRA:SIX2) Bewertung nach der jüngsten Aktienkursvolatilität.",
          "einordnung": "Nach Kursvolatilität ist eine Neubewertung der Aktie wichtig, um festzustellen, ob der aktuelle Preis eine Kaufgelegenheit oder ein erhöhtes Risiko darstellt.",
          "url": "https://finance.yahoo.com/markets/stocks/articles/look-sixt-xtra-six2-valuation-090954777.html",
          "quelle": "Simply Wall St.",
          "datum": "05.05.2026"
        },
        {
          "titel": "Weitere Schwäche, da Sixt (ETR:SIX2) diese Woche um 3,8% fällt und die Dreijahresverluste auf 38% ansteigen.",
          "einordnung": "Anhaltende Kursverluste signalisieren möglicherweise fundamentale Probleme oder eine negative Marktstimmung, die eine genaue Analyse der Unternehmensstrategie und des Wettbewerbsumfelds erfordert.",
          "url": "https://finance.yahoo.com/news/further-weakness-sixt-etr-six2-065522060.html",
          "quelle": "Simply Wall St.",
          "datum": "16.02.2026"
        }
      ],
      "fehler": null
    },
    {
      "wkn": "852654",
      "name": "Texas Instruments",
      "ticker": "TXN",
      "currency": "EUR",
      "price": 259.58,
      "change_1d_pct": 1.13,
      "change_1w_pct": 5.41,
      "change_1m_pct": -1.92,
      "change_1y_pct": 54.71,
      "week52_high": 286.39,
      "week52_low": 131.94,
      "div_yield": null,
      "div_rate": 4.91,
      "market_cap": "273.5B",
      "pe_ratio": 51.36,
      "sparkline": [
        241.5459,
        241.4341,
        242.7559,
        250.0472,
        246.4188,
        248.6304,
        257.2349,
        254.9974,
        264.6471,
        266.2281,
        261.5285,
        259.6883,
        261.1656,
        263.3858,
        257.7791,
        267.1265,
        280.6725,
        274.2451,
        272.9492,
        264.0769,
        253.2955,
        266.1849,
        266.5909,
        263.8091,
        246.2633,
        251.3085,
        249.3475,
        243.6284,
        256.6647,
        259.576
      ],
      "analyst_rating": "Kaufen",
      "analyst_target": 251.87,
      "analyst_count": 33,
      "news": [
        {
          "titel": "Was ein geduldiger Investor wirklich für die Broadcom-Aktie zahlt.",
          "einordnung": "Langfristige Investitionen in Qualitätsunternehmen können sich trotz kurzfristiger Schwankungen auszahlen, erfordern jedoch Geduld und Vertrauen in das Geschäftsmodell.",
          "url": "https://www.trefis.com/articles/602708/what-a-patient-investor-really-pays-for-broadcom-stock/2026-06-12",
          "quelle": "Trefis",
          "datum": "12.06.2026"
        },
        {
          "titel": "Die besten Halbleiter-ETFs: Wie Sie den KI-Goldrausch nutzen können.",
          "einordnung": "Halbleiter-ETFs bieten eine diversifizierte Möglichkeit, am Wachstum des KI-Sektors zu partizipieren, ohne das Risiko einzelner Aktien tragen zu müssen.",
          "url": "https://www.kiplinger.com/investing/etfs/best-semiconductor-etfs",
          "quelle": "Kiplinger",
          "datum": "12.06.2026"
        },
        {
          "titel": "Diese 3 Halbleiteraktien erhielten gerade ein bullisches Signal von Citi. Kaufen Sie den Rücksetzer.",
          "einordnung": "Eine positive Analystenbewertung kann ein Kaufsignal sein, doch sollten Anleger die Empfehlung im Kontext eigener Recherchen und Risikobereitschaft prüfen.",
          "url": "https://www.barchart.com/story/news/2438312/these-3-semiconductor-stocks-just-got-a-bullish-nod-from-citi-buy-the-dip",
          "quelle": "Barchart",
          "datum": "12.06.2026"
        },
        {
          "titel": "Lattice Semiconductor und Texas Instruments Aktien schießen in die Höhe, was Sie wissen müssen.",
          "einordnung": "Ein starker Kursanstieg kann auf positive Nachrichten oder eine erhöhte Nachfrage hindeuten, erfordert jedoch eine Analyse der Gründe, um die Nachhaltigkeit des Wachstums zu beurteilen.",
          "url": "https://finance.yahoo.com/markets/stocks/articles/lattice-semiconductor-texas-instruments-shares-234537463.html",
          "quelle": "StockStory",
          "datum": "11.06.2026"
        }
      ],
      "fehler": null
    },
    {
      "wkn": "869561",
      "name": "UnitedHealth",
      "ticker": "UNH",
      "currency": "EUR",
      "price": 352.81,
      "change_1d_pct": 0.7,
      "change_1w_pct": 2.23,
      "change_1m_pct": 1.8,
      "change_1y_pct": 31.84,
      "week52_high": 359.37,
      "week52_low": 202.67,
      "div_yield": null,
      "div_rate": 8.02,
      "market_cap": "370.9B",
      "pe_ratio": 30.8,
      "sparkline": [
        318.589,
        320.2909,
        314.3473,
        317.2932,
        319.4184,
        328.2647,
        332.1177,
        342.4413,
        346.5621,
        344.7738,
        340.247,
        337.8972,
        336.2644,
        331.1329,
        330.4245,
        335.5992,
        325.5693,
        331.7462,
        330.4677,
        328.5498,
        328.161,
        326.4851,
        325.6903,
        342.5104,
        345.1021,
        351.2358,
        356.7907,
        352.0047,
        350.3546,
        352.8081
      ],
      "analyst_rating": "Kaufen",
      "analyst_target": 351.94,
      "analyst_count": 26,
      "news": [
        {
          "titel": "Patienten wird die Versorgung verweigert, dann später genehmigt? Bundesaufsichtsbehörde äußert Bedenken bezüglich Medicare Advantage.",
          "einordnung": "Bedenken der Aufsichtsbehörden bezüglich Medicare Advantage könnten zu strengeren Vorschriften führen und potenziell die Profitabilität von UnitedHealth in diesem wichtigen Segment beeinträchtigen.",
          "url": "https://www.yahoo.com/news/politics/articles/patients-denied-care-then-approved-123107936.html",
          "quelle": "Benzinga",
          "datum": "12.06.2026"
        },
        {
          "titel": "Haben Dividendenerhöhung und abgelehnter unabhängiger Vorsitzender die Investment-Erzählung der UnitedHealth Group (UNH) verändert?",
          "einordnung": "Eine Dividendenerhöhung ist positiv, aber die Ablehnung eines unabhängigen Vorsitzenden könnte Governance-Bedenken aufwerfen und die langfristige Anlegerwahrnehmung beeinflussen.",
          "url": "https://finance.yahoo.com/markets/stocks/articles/did-dividend-hike-rejected-independent-081625742.html",
          "quelle": "Simply Wall St.",
          "datum": "12.06.2026"
        },
        {
          "titel": "UnitedHealth Group hat gerade ein 52-Wochen-Hoch erreicht. Ist es zu spät, diese stark steigende Aktie zu kaufen?",
          "einordnung": "Ein 52-Wochen-Hoch signalisiert starke Performance, doch Anleger sollten vor einem Kauf prüfen, ob die Bewertung noch attraktiv ist und weiteres Wachstumspotenzial besteht.",
          "url": "https://www.fool.com/investing/2026/06/11/unitedhealth-group-hit-52-week-high-buy-stock/",
          "quelle": "Motley Fool",
          "datum": "11.06.2026"
        },
        {
          "titel": "Reicht HealthEquitys verbesserte Profitabilität aus, um die Schlüsselrisiken zu kompensieren?",
          "einordnung": "Aktionäre sollten prüfen, ob die positive Gewinnentwicklung von HealthEquity die bestehenden Risiken ausreichend kompensiert, um die Investition zu rechtfertigen.",
          "url": "https://finance.yahoo.com/sectors/healthcare/articles/healthequitys-improving-profitability-enough-offset-171000663.html",
          "quelle": "Zacks",
          "datum": "11.06.2026"
        }
      ],
      "fehler": null
    }
  ]
}