{
  "aktualisiert": "2026-07-20T19:26:10.319330+00:00",
  "aktien": [
    {
      "wkn": "A1J84E",
      "name": "AbbVie",
      "ticker": "ABBV",
      "currency": "EUR",
      "price": 221.47,
      "change_1d_pct": -0.63,
      "change_1w_pct": 2.69,
      "change_1m_pct": 15.12,
      "change_1y_pct": 41.05,
      "week52_high": 229.14,
      "week52_low": 161.7,
      "div_yield": null,
      "div_rate": 6.06,
      "market_cap": "446.8B",
      "pe_ratio": 123.96,
      "sparkline": [
        197.6015,
        193.984,
        196.0275,
        195.6188,
        195.4623,
        198.0363,
        192.6969,
        193.4622,
        192.3839,
        188.2619,
        200.019,
        204.1497,
        204.2628,
        211.437,
        220.3158,
        221.1506,
        218.8287,
        218.3243,
        227.0292,
        221.5419,
        221.4462,
        219.7853,
        217.3243,
        215.7329,
        215.6633,
        212.8632,
        213.7915,
        222.7948,
        222.8823,
        221.4741
      ],
      "analyst_rating": "Kaufen",
      "analyst_target": 233.46,
      "analyst_count": 28,
      "news": [
        {
          "titel": "JNJ-Aktie: Zwischen den Zeilen des jüngsten Earnings Call lesen",
          "einordnung": "Dieser Titel deutet auf mögliche Auswirkungen der Geschäftsentwicklung eines Konkurrenten auf AbbVies eigene Marktposition und zukünftige Strategie hin.",
          "url": "https://www.trefis.com/articles/607982/reading-between-the-lines-of-jnj-stocks-latest-call/2026-07-20",
          "quelle": "Trefis",
          "datum": "20.07.2026"
        },
        {
          "titel": "Eli Lilly-Aktie und der Preis des Vertrauens",
          "einordnung": "Die Bewertung eines Konkurrenten wie Eli Lilly kann Aufschluss über die allgemeine Marktstimmung und die Investorenerwartungen in der Pharmabranche geben, was auch AbbVie beeinflussen könnte.",
          "url": "https://www.trefis.com/articles/607976/eli-lilly-stock-and-the-price-of-confidence/2026-07-20",
          "quelle": "Trefis",
          "datum": "20.07.2026"
        },
        {
          "titel": "Wie wird AbbVies 10,9 Milliarden Dollar schwere Übernahme von Apogee die Dividende beeinflussen?",
          "einordnung": "Aktionäre sollten prüfen, ob diese Akquisition die finanzielle Stabilität und die Fähigkeit von AbbVie zur Aufrechterhaltung oder Erhöhung der Dividende beeinträchtigt.",
          "url": "https://www.fool.com/investing/2026/07/19/how-will-abbvies-109-billion-acquisition-of-apogee/",
          "quelle": "Motley Fool",
          "datum": "20.07.2026"
        },
        {
          "titel": "Meine 2 bevorzugten Dividendenkönige, die man jetzt kaufen sollte",
          "einordnung": "Wenn AbbVie als Dividendenkönig genannt wird, bestätigt dies seine Attraktivität für langfristig orientierte Anleger, die auf stabile und wachsende Dividendenzahlungen Wert legen.",
          "url": "https://www.fool.com/investing/2026/07/19/my-2-favorite-dividend-kings-to-buy-right-now/",
          "quelle": "Motley Fool",
          "datum": "19.07.2026"
        }
      ],
      "fehler": null
    },
    {
      "wkn": "A2ANT0",
      "name": "Ahold Delhaize",
      "ticker": "AD.AS",
      "currency": "EUR",
      "price": 35.98,
      "change_1d_pct": -0.88,
      "change_1w_pct": 1.07,
      "change_1m_pct": 3.96,
      "change_1y_pct": 6.0,
      "week52_high": 42.54,
      "week52_low": 32.13,
      "div_yield": null,
      "div_rate": 1.46,
      "market_cap": "31.7B",
      "pe_ratio": 14.28,
      "sparkline": [
        35.75,
        36.18,
        36.2,
        36.37,
        36.01,
        36.21,
        35.39,
        34.52,
        34.61,
        34.23,
        34.85,
        35.26,
        35.13,
        35.43,
        35.33,
        35.22,
        35.16,
        36.16,
        35.92,
        35.44,
        36.33,
        36.06,
        35.76,
        35.91,
        35.6,
        36.12,
        35.88,
        35.92,
        36.3,
        35.98
      ],
      "analyst_rating": "Halten",
      "analyst_target": 39.31,
      "analyst_count": 18,
      "news": [
        {
          "titel": "Ahold Delhaizes erstes Jahrzehnt: Wichtige Meilensteine in den USA",
          "einordnung": "Dieser Rückblick beleuchtet die strategische Entwicklung und das Wachstum von Ahold Delhaize auf dem wichtigen US-Markt, was für zukünftige Ertragsprognosen relevant ist.",
          "url": "https://www.grocerydive.com/news/ahold-delhaize-usa-adusa-timeline-10-year-merger-anniversary/825596/",
          "quelle": "Grocery Dive",
          "datum": "20.07.2026"
        },
        {
          "titel": "Weißes Haus setzt führende US-Lebensmittelhändler wegen Rindfleischpreisen unter Druck",
          "einordnung": "Politische Interventionen bei den Preisen könnten die Gewinnmargen von Ahold Delhaize in den USA beeinflussen und erfordern eine genaue Beobachtung.",
          "url": "https://www.wsj.com/business/retail/white-house-pressures-top-u-s-grocers-on-beef-prices-ae7f4822?siteid=yhoof2&yptr=yahoo",
          "quelle": "The Wall Street Journal",
          "datum": "07.07.2026"
        },
        {
          "titel": "Krogers 1,65 Milliarden Dollar Supermarkt-Deal verdoppelt Präsenz im Osten",
          "einordnung": "Eine Konsolidierung oder Expansion eines Konkurrenten wie Kroger im US-Osten könnte den Wettbewerbsdruck für Ahold Delhaize in dieser Region erhöhen.",
          "url": "https://www.wsj.com/livecoverage/stock-market-today-dow-sp-500-nasdaq-07-01-2026/card/kroger-s-1-65-billion-supermarket-deal-doubles-down-on-the-east-pkbHI0BxZqndphU4gnSH?siteid=yhoof2&yptr=yahoo",
          "quelle": "The Wall Street Journal",
          "datum": "01.07.2026"
        },
        {
          "titel": "Ahold Delhaize nominiert ehemaligen Amazon-Manager als US-CEO",
          "einordnung": "Die Ernennung eines erfahrenen Managers von Amazon könnte auf eine stärkere Fokussierung auf digitale Strategien und Effizienz im US-Geschäft hindeuten.",
          "url": "https://www.grocerydive.com/news/ahold-delhaize-usa-ceo-nominee-former-amazon-fresh-veteran-claire-peters/823251/",
          "quelle": "Grocery Dive",
          "datum": "18.06.2026"
        }
      ],
      "fehler": null
    },
    {
      "wkn": "840400",
      "name": "Allianz",
      "ticker": "ALV.DE",
      "currency": "EUR",
      "price": 422.8,
      "change_1d_pct": -0.02,
      "change_1w_pct": 0.43,
      "change_1m_pct": 5.59,
      "change_1y_pct": 28.71,
      "week52_high": 425.5,
      "week52_low": 334.1,
      "div_yield": null,
      "div_rate": 17.1,
      "market_cap": "160.4B",
      "pe_ratio": 13.66,
      "sparkline": [
        377.9,
        381.5,
        383.3,
        386.4,
        394.7,
        399.0,
        400.2,
        400.0,
        400.4,
        406.6,
        405.2,
        404.5,
        407.1,
        407.9,
        408.8,
        414.1,
        414.1,
        418.4,
        419.8,
        420.2,
        422.8,
        418.5,
        422.7,
        421.6,
        421.0,
        421.0,
        416.4,
        419.6,
        422.9,
        422.8
      ],
      "analyst_rating": "Kaufen",
      "analyst_target": 415.01,
      "analyst_count": 17,
      "news": [
        {
          "titel": "Wharton-Ökonom: „Das Schlimmste der Inflation liegt hinter uns“, aber KI könnte in 3-4 Jahren überbaut sein",
          "einordnung": "Eine Entspannung der Inflation ist positiv für Versicherer wie Allianz, während eine mögliche Überhitzung im KI-Sektor zukünftige Investitionen und Risikobewertungen beeinflussen könnte.",
          "url": "https://247wallst.com/investing/2026/07/20/wharton-economist-the-worst-of-the-inflation-is-behind-us-but-ai-could-face-an-overbuild-in-3-4-years/",
          "quelle": "24/7 Wall St.",
          "datum": "20.07.2026"
        },
        {
          "titel": "KI-Automatisierung trifft Versicherungsjobs, da Allianz Kürzungen plant",
          "einordnung": "Diese Nachricht deutet auf Effizienzsteigerungen durch KI hin, die langfristig die Profitabilität der Allianz verbessern, kurzfristig aber auch Restrukturierungskosten verursachen könnten.",
          "url": "https://www.lifeinsuranceinternational.com/analyst-comment/ai-automation-hits-insurance-jobs-allianz-plans-cuts/",
          "quelle": "Life Insurance International",
          "datum": "20.07.2026"
        },
        {
          "titel": "Warum steigen die Aktien von BATL, TPET, XOM, CVX, USO, UCO über Nacht?",
          "einordnung": "Dieser Titel ist nicht direkt auf Allianz bezogen, könnte aber auf allgemeine Markttrends oder Sektorverschiebungen hinweisen, die indirekt auch das Anlageportfolio der Allianz beeinflussen.",
          "url": "https://stocktwits.com/news-articles/markets/equity/why-are-batl-tpet-xom-cvx-uso-uco-stocks-rising-overnight/cZZLqW1R7Mp",
          "quelle": "Stocktwits",
          "datum": "20.07.2026"
        },
        {
          "titel": "Allianz (XTRA:ALV) Aktie erscheint aufgrund ihrer Ertragsstärke fair bewertet",
          "einordnung": "Diese Einschätzung bestätigt die solide finanzielle Leistung der Allianz und deutet auf eine angemessene Bewertung im Verhältnis zu ihren Gewinnen hin.",
          "url": "https://finance.yahoo.com/markets/stocks/articles/allianz-xtra-alv-stock-looks-100856806.html",
          "quelle": "Simply Wall St.",
          "datum": "17.07.2026"
        }
      ],
      "fehler": null
    },
    {
      "wkn": "850471",
      "name": "Boeing",
      "ticker": "BA",
      "currency": "EUR",
      "price": 183.73,
      "change_1d_pct": -1.99,
      "change_1w_pct": -2.66,
      "change_1m_pct": -7.02,
      "change_1y_pct": -8.52,
      "week52_high": 222.76,
      "week52_low": 154.82,
      "div_yield": null,
      "div_rate": null,
      "market_cap": "165.4B",
      "pe_ratio": 82.92,
      "sparkline": [
        188.6911,
        189.1027,
        187.8679,
        183.0422,
        194.1036,
        191.844,
        200.5144,
        199.2357,
        197.6068,
        195.0582,
        193.4029,
        189.7946,
        192.8949,
        191.0295,
        190.2675,
        188.0255,
        189.5844,
        191.4324,
        198.3599,
        205.4101,
        202.9053,
        197.0112,
        195.3997,
        194.6728,
        188.7437,
        190.1449,
        191.0295,
        187.719,
        187.4475,
        183.7297
      ],
      "analyst_rating": "Kaufen",
      "analyst_target": 236.53,
      "analyst_count": 26,
      "news": [
        {
          "titel": "Boeing verschiebt Jet der nächsten Generation auf Ende der 2030er Jahre",
          "einordnung": "Die Verzögerung bei der Entwicklung neuer Flugzeugmodelle könnte Boeings zukünftige Wettbewerbsfähigkeit und Marktanteile beeinflussen.",
          "url": "https://finance.yahoo.com/markets/stocks/articles/boeing-pushes-next-generation-jet-174135441.html",
          "quelle": "GuruFocus.com",
          "datum": "20.07.2026"
        },
        {
          "titel": "Boeing erhält auf der Farnborough Airshow einen Auftrag über 100 Jets von SMBC",
          "einordnung": "Ein Großauftrag wie dieser stärkt Boeings Auftragsbestand und signalisiert Vertrauen in seine Produkte und zukünftige Produktionskapazitäten.",
          "url": "https://finance.yahoo.com/markets/stocks/articles/boeing-lands-100-jet-smbc-174005549.html",
          "quelle": "GuruFocus.com",
          "datum": "20.07.2026"
        },
        {
          "titel": "Boeing erhält Auftrag über bis zu 20 Dreamliner von Philippine Airlines",
          "einordnung": "Dieser Auftrag trägt zur Stabilisierung des Auftragsbuchs bei und unterstreicht die anhaltende Nachfrage nach Boeings Langstreckenflugzeugen.",
          "url": "https://finance.yahoo.com/markets/stocks/articles/boeing-lands-20-dreamliner-order-172843110.html",
          "quelle": "GuruFocus.com",
          "datum": "20.07.2026"
        },
        {
          "titel": "GE Aerospace CEO: 210 Mrd. Dollar Auftragsbestand und historischer Transatlantikflug beweisen, dass Hybrid-Elektro-Luftfahrt kommt",
          "einordnung": "Die Entwicklung der Hybrid-Elektro-Luftfahrt durch Partner wie GE Aerospace ist ein wichtiger Trend, der zukünftige Flugzeugdesigns und damit auch Boeings Produktstrategie beeinflussen wird.",
          "url": "https://247wallst.com/investing/2026/07/20/ge-aerospace-ceo-210b-backlog-and-historic-transatlantic-flight-proves-hybrid-electric-aviation-is-coming/",
          "quelle": "24/7 Wall St.",
          "datum": "20.07.2026"
        }
      ],
      "fehler": null
    },
    {
      "wkn": "850501",
      "name": "Bristol-Myers Squibb",
      "ticker": "BMY",
      "currency": "EUR",
      "price": 52.71,
      "change_1d_pct": -0.92,
      "change_1w_pct": 1.42,
      "change_1m_pct": 10.09,
      "change_1y_pct": 35.08,
      "week52_high": 55.08,
      "week52_low": 37.24,
      "div_yield": null,
      "div_rate": 2.21,
      "market_cap": "122.9B",
      "pe_ratio": 16.86,
      "sparkline": [
        49.5972,
        48.125,
        48.913,
        48.1509,
        49.2768,
        49.476,
        48.7052,
        48.4281,
        47.8738,
        46.7653,
        47.3715,
        48.0903,
        47.6313,
        47.9691,
        49.8137,
        50.7144,
        49.9003,
        48.8784,
        50.9103,
        49.6579,
        50.7701,
        50.3935,
        50.7439,
        50.4286,
        51.97,
        49.8768,
        51.427,
        52.9947,
        53.1961,
        52.7056
      ],
      "analyst_rating": "Kaufen",
      "analyst_target": 55.14,
      "analyst_count": 24,
      "news": [
        {
          "titel": "Bristol Myers Squibb erweitert NVIDIA KI-Supercomputer für die Medikamentenentwicklung",
          "einordnung": "Die Investition in KI-Technologie zur Medikamentenentwicklung kann die Effizienz und Geschwindigkeit der Forschung erhöhen und somit zukünftige Umsätze und Gewinne steigern.",
          "url": "https://qz.com/bristol-myers-squibb-nvidia-ai-supercomputer-drug-discovery-072026",
          "quelle": "Quartz",
          "datum": "20.07.2026"
        },
        {
          "titel": "Mercks Keytruda steht vor einem Patentablauf. Diese neuen Krebsmedikamente könnten übernehmen.",
          "einordnung": "Der Patentablauf eines Konkurrenzprodukts schafft Marktchancen für Bristol Myers Squibb, wenn es eigene innovative Krebsmedikamente in der Pipeline hat.",
          "url": "https://www.barrons.com/articles/merck-keytruda-new-cancer-drugs-treatments-ec397d85?siteid=yhoof2&yptr=yahoo",
          "quelle": "Barrons.com",
          "datum": "20.07.2026"
        },
        {
          "titel": "Top-Mittagsnachrichten: Brookfield, CPP Investments übernehmen LXP; Google arbeitet an neuem Server-Chip",
          "einordnung": "Dieser Titel ist nicht direkt auf Bristol Myers Squibb bezogen, bietet aber einen allgemeinen Überblick über wichtige Wirtschaftsereignisse, die das breitere Marktumfeld beeinflussen könnten.",
          "url": "https://finance.yahoo.com/markets/stocks/articles/top-midday-stories-brookfield-cpp-153836000.html",
          "quelle": "MT Newswires",
          "datum": "20.07.2026"
        },
        {
          "titel": "Bristol Myers Squibb erweitert Nvidia KI-Infrastruktur für die Medikamentenentwicklung",
          "einordnung": "Diese Investition unterstreicht das Engagement des Unternehmens, durch den Einsatz modernster KI-Technologie die Effizienz und Erfolgsquote in der Forschung und Entwicklung zu verbessern.",
          "url": "https://investorshub.advfn.com/market-news/article/32196/bristol-myers-squibb-expands-nvidia-ai-infrastructure-for-drug-discovery",
          "quelle": "InvestorsHub",
          "datum": "20.07.2026"
        }
      ],
      "fehler": null
    },
    {
      "wkn": "916018",
      "name": "Brit. American Tobacco",
      "ticker": "BTI",
      "currency": "EUR",
      "price": 54.71,
      "change_1d_pct": -0.59,
      "change_1w_pct": 5.96,
      "change_1m_pct": 6.46,
      "change_1y_pct": 27.52,
      "week52_high": 58.94,
      "week52_low": 43.68,
      "div_yield": null,
      "div_rate": 2.93,
      "market_cap": "134.8B",
      "pe_ratio": 13.55,
      "sparkline": [
        51.5853,
        51.5594,
        51.784,
        52.7946,
        53.0278,
        53.8311,
        52.7428,
        53.0192,
        51.3866,
        50.8856,
        50.877,
        52.4664,
        53.0278,
        53.9693,
        54.2112,
        54.1939,
        53.3474,
        52.3109,
        53.3561,
        53.0883,
        53.382,
        53.0278,
        52.5787,
        52.5655,
        51.6284,
        50.9716,
        51.4357,
        55.3155,
        55.0353,
        54.7068
      ],
      "analyst_rating": "Starker Kauf",
      "analyst_target": 59.94,
      "analyst_count": 5,
      "news": [
        {
          "titel": "Wall Street stürzt im KI-„Blutbad“ ab",
          "einordnung": "Dieser Titel deutet auf eine breitere Marktkorrektur hin, die auch BAT-Aktien beeinflussen könnte, unabhängig von unternehmensspezifischen Nachrichten.",
          "url": "https://uk.finance.yahoo.com/news/global-stocks-plunge-ai-bloodbath-093710394.html",
          "quelle": "The Telegraph",
          "datum": "17.07.2026"
        },
        {
          "titel": "5 solide Dividendenaktien, die man im Juli kaufen sollte",
          "einordnung": "Wenn BAT in dieser Liste enthalten ist, könnte dies ein positives Signal für Anleger sein, die auf stabile Dividendenzahlungen Wert legen.",
          "url": "https://247wallst.com/investing/2026/07/10/5-solid-dividend-stocks-to-buy-in-july/",
          "quelle": "24/7 Wall St.",
          "datum": "10.07.2026"
        },
        {
          "titel": "Tabakaktien kommen aus der Kälte",
          "einordnung": "Dies deutet auf eine mögliche Neubewertung und steigendes Interesse an Tabakaktien hin, was positiv für BAT wäre.",
          "url": "https://www.wsj.com/finance/stocks/tobacco-stocks-are-coming-in-from-the-cold-4b45d4cd?siteid=yhoof2&yptr=yahoo",
          "quelle": "The Wall Street Journal",
          "datum": "09.07.2026"
        },
        {
          "titel": "British American Tobacco streicht 5.500 Stellen. So nutzen Sie die Hochdividendenaktie hier.",
          "einordnung": "Der Stellenabbau könnte auf Kostensenkungen und Effizienzsteigerungen hindeuten, die langfristig die Profitabilität und damit die Dividendenfähigkeit von BAT stützen könnten.",
          "url": "https://www.barchart.com/story/news/3132490/british-american-tobacco-is-cutting-5-500-jobs-how-to-play-the-high-yield-dividend-stock-here",
          "quelle": "Barchart",
          "datum": "05.07.2026"
        }
      ],
      "fehler": null
    },
    {
      "wkn": "878841",
      "name": "Cisco Systems",
      "ticker": "CSCO",
      "currency": "EUR",
      "price": 97.42,
      "change_1d_pct": -0.63,
      "change_1w_pct": -6.72,
      "change_1m_pct": -4.84,
      "change_1y_pct": 66.15,
      "week52_high": 114.18,
      "week52_low": 57.58,
      "div_yield": null,
      "div_rate": 1.47,
      "market_cap": "438.4B",
      "pe_ratio": 37.08,
      "sparkline": [
        106.1353,
        108.3253,
        105.0184,
        103.6573,
        106.301,
        105.6641,
        104.8526,
        104.3291,
        102.3746,
        104.3029,
        106.0393,
        105.7077,
        104.4687,
        103.8056,
        99.2684,
        102.6975,
        102.4881,
        102.0954,
        98.3261,
        99.8237,
        97.9057,
        99.6836,
        103.6159,
        106.2433,
        104.4391,
        102.5474,
        97.8882,
        96.0402,
        98.0371,
        97.4241
      ],
      "analyst_rating": "Kaufen",
      "analyst_target": 114.05,
      "analyst_count": 22,
      "news": [
        {
          "titel": "Cisco (CSCO) testet Quanten-Networking, während Webex einen KI-Kontaktcenter-Partner hinzufügt",
          "einordnung": "Diese Nachricht zeigt Ciscos Engagement in zukunftsweisenden Technologien wie Quanten-Networking und KI, was langfristig Wachstumschancen eröffnen könnte.",
          "url": "https://finance.yahoo.com/technology/ai/articles/cisco-csco-tests-quantum-networking-160903232.html",
          "quelle": "Simply Wall St.",
          "datum": "20.07.2026"
        },
        {
          "titel": "Kursprognose: Cisco-Aktie wird sich an diesem Datum verdoppeln",
          "einordnung": "Solche aggressiven Kursprognosen sind mit Vorsicht zu genießen und sollten durch eigene Recherche und fundamentale Analyse überprüft werden.",
          "url": "https://247wallst.com/investing/2026/07/20/price-prediction-cisco-stock-will-double-on-this-date/",
          "quelle": "24/7 Wall St.",
          "datum": "20.07.2026"
        },
        {
          "titel": "Übertrifft die Aktie von Aehr Test Systems (AEHR) in diesem Jahr ihre Konkurrenten im Computer- und Technologiesektor?",
          "einordnung": "Dieser Titel vergleicht eine andere Firma mit Technologie-Peers und ist für Cisco-Aktionäre nur indirekt relevant, indem er das allgemeine Marktumfeld beleuchtet.",
          "url": "https://finance.yahoo.com/markets/stocks/articles/aehr-test-systems-aehr-stock-134003381.html",
          "quelle": "Zacks",
          "datum": "20.07.2026"
        },
        {
          "titel": "Wall-Street-Analysten halten Cisco (CSCO) für eine gute Investition: Ist sie es?",
          "einordnung": "Die positive Einschätzung von Analysten kann ein Indikator für Vertrauen in das Unternehmen sein, sollte aber immer kritisch hinterfragt werden.",
          "url": "https://finance.yahoo.com/markets/stocks/articles/wall-street-analysts-think-cisco-133004041.html",
          "quelle": "Zacks",
          "datum": "20.07.2026"
        }
      ],
      "fehler": null
    },
    {
      "wkn": "A0MW32",
      "name": "CME Group",
      "ticker": "CME",
      "currency": "EUR",
      "price": 215.47,
      "change_1d_pct": 0.4,
      "change_1w_pct": 0.38,
      "change_1m_pct": -2.58,
      "change_1y_pct": -7.05,
      "week52_high": 288.28,
      "week52_low": 191.2,
      "div_yield": null,
      "div_rate": 4.55,
      "market_cap": "88.9B",
      "pe_ratio": 21.01,
      "sparkline": [
        224.2681,
        219.5893,
        224.1523,
        231.036,
        229.6172,
        236.0544,
        233.0329,
        229.1093,
        221.1745,
        215.7796,
        214.7462,
        212.1713,
        202.9053,
        197.055,
        193.5518,
        191.4324,
        193.4029,
        202.3098,
        207.2143,
        205.6028,
        210.8488,
        212.8807,
        209.938,
        210.4285,
        214.6586,
        213.3536,
        214.7286,
        215.6833,
        214.6148,
        215.4731
      ],
      "analyst_rating": "Kaufen",
      "analyst_target": 246.51,
      "analyst_count": 15,
      "news": [
        {
          "titel": "Quartalsergebnisse von Airlines, Alphabet, Tesla: Was diese Woche zu beachten ist",
          "einordnung": "Dieser Titel ist eine allgemeine Marktübersicht und für CME-Aktionäre nur relevant, um das breitere Marktumfeld vor den eigenen Quartalszahlen zu verstehen.",
          "url": "https://www.wsj.com/livecoverage/stock-market-today-dow-sp-500-nasdaq-07-20-2026/card/airlines-telecom-tesla-earnings-what-to-watch-this-week-dgEGlUZXltuGWNCCLUmT?siteid=yhoof2&yptr=yahoo",
          "quelle": "The Wall Street Journal",
          "datum": "20.07.2026"
        },
        {
          "titel": "CME (CME) Q2 Gewinnvorschau: Was Sie über die Schlagzeilenschätzungen hinaus wissen sollten",
          "einordnung": "Diese Vorschau ist wichtig, um sich auf die bevorstehenden Quartalsergebnisse vorzubereiten und die Erwartungen des Marktes zu verstehen.",
          "url": "https://finance.yahoo.com/markets/stocks/articles/cme-cme-q2-earnings-preview-131508591.html",
          "quelle": "Zacks",
          "datum": "20.07.2026"
        },
        {
          "titel": "Q1 Gewinn-Highlights: CME Group (NASDAQ:CME) im Vergleich zu den anderen Finanzbörsen- und Datenaktien",
          "einordnung": "Der Vergleich mit Wettbewerbern ist entscheidend, um die relative Performance der CME Group im Sektor zu beurteilen.",
          "url": "https://finance.yahoo.com/markets/stocks/articles/q1-earnings-highlights-cme-group-182546762.html",
          "quelle": "StockStory",
          "datum": "17.07.2026"
        },
        {
          "titel": "Was steht für die CME Group in dieser Berichtssaison an?",
          "einordnung": "Dieser Titel bereitet auf die bevorstehende Berichtssaison vor und regt zur Analyse der Erwartungen und potenziellen Überraschungen an.",
          "url": "https://finance.yahoo.com/markets/stocks/articles/whats-cards-cme-group-earnings-153800354.html",
          "quelle": "Zacks",
          "datum": "17.07.2026"
        }
      ],
      "fehler": null
    },
    {
      "wkn": "547030",
      "name": "CTS Eventim",
      "ticker": "EVD.DE",
      "currency": "EUR",
      "price": 57.9,
      "change_1d_pct": 1.49,
      "change_1w_pct": 2.48,
      "change_1m_pct": 11.13,
      "change_1y_pct": -42.06,
      "week52_high": 104.9,
      "week52_low": 48.68,
      "div_yield": null,
      "div_rate": 1.44,
      "market_cap": "5.6B",
      "pe_ratio": 18.86,
      "sparkline": [
        50.9,
        50.0,
        49.66,
        50.45,
        53.0,
        54.7,
        53.55,
        52.8,
        52.1,
        51.15,
        50.4,
        50.35,
        49.8,
        49.56,
        50.4,
        51.05,
        53.3,
        57.55,
        57.4,
        57.25,
        56.9,
        54.1,
        53.6,
        56.5,
        56.5,
        55.85,
        57.2,
        56.75,
        57.05,
        57.9
      ],
      "analyst_rating": "Starker Kauf",
      "analyst_target": 87.96,
      "analyst_count": 12,
      "news": [
        {
          "titel": "Umsatzüberraschung: CTS Eventim AG & Co. KGaA übertraf Analystenschätzungen um 14%",
          "einordnung": "Ein deutliches Übertreffen der Umsatzschätzungen ist ein starkes positives Signal für die operative Leistung und das Wachstum des Unternehmens.",
          "url": "https://finance.yahoo.com/markets/stocks/articles/revenue-beat-cts-eventim-ag-070015855.html",
          "quelle": "Simply Wall St.",
          "datum": "31.05.2026"
        },
        {
          "titel": "CTS Eventim-Aktien springen nach US-Tourneen und Olympischen Winterspielen, die die Gewinne antreiben",
          "einordnung": "Die positiven Auswirkungen großer Events auf die Gewinne zeigen die Stärke des Geschäftsmodells und das Potenzial für zukünftiges Wachstum.",
          "url": "https://www.wsj.com/business/cts-eventim-shares-jump-after-u-s-tours-winter-olympics-drive-earnings-5e4e932e?siteid=yhoof2&yptr=yahoo",
          "quelle": "The Wall Street Journal",
          "datum": "29.05.2026"
        },
        {
          "titel": "CTS Eventim AG & Co. KGaA (CEVMF) Q1 2026 Earnings Call Highlights: Starkes Umsatzwachstum ...",
          "einordnung": "Starkes Umsatzwachstum ist ein positives Zeichen für die Expansion und die Marktposition des Unternehmens.",
          "url": "https://finance.yahoo.com/markets/stocks/articles/cts-eventim-ag-co-kgaa-010021245.html",
          "quelle": "GuruFocus.com",
          "datum": "29.05.2026"
        },
        {
          "titel": "CTS Eventim AG & Co. KGaA Q1 Earnings Call Highlights",
          "einordnung": "Die Highlights des Earnings Calls bieten wichtige Einblicke in die finanzielle Gesundheit und die strategische Ausrichtung des Unternehmens.",
          "url": "https://www.marketbeat.com/instant-alerts/cts-eventim-ag-co-kgaa-q1-earnings-call-highlights-2026-05-28/?utm_source=yahoofinance&utm_medium=yahoofinance",
          "quelle": "MarketBeat",
          "datum": "28.05.2026"
        }
      ],
      "fehler": null
    },
    {
      "wkn": "887891",
      "name": "Fastenal",
      "ticker": "FAST",
      "currency": "EUR",
      "price": 39.17,
      "change_1d_pct": -1.67,
      "change_1w_pct": -4.92,
      "change_1m_pct": -0.32,
      "change_1y_pct": -0.76,
      "week52_high": 44.34,
      "week52_low": 34.13,
      "div_yield": null,
      "div_rate": 0.84,
      "market_cap": "51.3B",
      "pe_ratio": 38.24,
      "sparkline": [
        40.9787,
        40.2868,
        40.7948,
        40.3131,
        40.6284,
        40.786,
        40.3744,
        40.3306,
        39.3059,
        40.1905,
        40.3919,
        39.9365,
        40.5145,
        41.0925,
        41.2502,
        41.5129,
        42.0647,
        41.8195,
        42.5639,
        42.3099,
        41.2589,
        40.7335,
        40.5933,
        40.7159,
        41.2064,
        40.0591,
        39.7263,
        40.8736,
        39.8401,
        39.1789
      ],
      "analyst_rating": "Halten",
      "analyst_target": 41.9,
      "analyst_count": 13,
      "news": [
        {
          "titel": "3 Dividendenaktien, die Buffets Test bestehen: Kaufen, Verkaufen oder Halten?",
          "einordnung": "Wenn Fastenal in dieser Liste ist, deutet dies auf eine hohe Qualität und Stabilität hin, die von einem renommierten Investor geschätzt wird.",
          "url": "https://247wallst.com/investing/2026/07/20/3-dividend-stocks-that-pass-buffetts-test-buy-sell-or-hold/",
          "quelle": "24/7 Wall St.",
          "datum": "20.07.2026"
        },
        {
          "titel": "Übersehen Sie nicht die internationalen Umsatztrends von Fastenal (FAST) bei der Bewertung der Aktie",
          "einordnung": "Die Analyse internationaler Umsatztrends ist entscheidend, um das globale Wachstumspotenzial und die Diversifizierung des Unternehmens zu verstehen.",
          "url": "https://finance.yahoo.com/markets/stocks/articles/dont-overlook-fastenal-fast-international-131502641.html",
          "quelle": "Zacks",
          "datum": "20.07.2026"
        },
        {
          "titel": "MarketBeat Wochenrückblick – 13.07.-17.07.",
          "einordnung": "Ein allgemeiner Wochenrückblick bietet Kontext zu den breiteren Marktbewegungen, die auch Fastenal beeinflussen könnten.",
          "url": "https://www.marketbeat.com/articles/marketbeat-week-in-review-07-13-07-17/?utm_source=yahoofinance&utm_medium=yahoofinance",
          "quelle": "MarketBeat",
          "datum": "18.07.2026"
        },
        {
          "titel": "Bleibt die Volatilität niedrig, passiert Folgendes mit DIVOs monatlichem Einkommen",
          "einordnung": "Dieser Titel bezieht sich auf einen spezifischen ETF (DIVO) und ist für Fastenal-Aktionäre nur indirekt relevant, um das allgemeine Marktumfeld zu verstehen.",
          "url": "https://247wallst.com/investing/etf/2026/07/17/if-volatility-stays-low-heres-what-happens-to-divos-monthly-income/",
          "quelle": "24/7 Wall St.",
          "datum": "18.07.2026"
        }
      ],
      "fehler": null
    },
    {
      "wkn": "853260",
      "name": "Johnson & Johnson",
      "ticker": "JNJ",
      "currency": "EUR",
      "price": 218.49,
      "change_1d_pct": -1.41,
      "change_1w_pct": -3.22,
      "change_1m_pct": 6.52,
      "change_1y_pct": 55.57,
      "week52_high": 235.97,
      "week52_low": 142.56,
      "div_yield": null,
      "div_rate": 4.69,
      "market_cap": "600.5B",
      "pe_ratio": 28.91,
      "sparkline": [
        203.86,
        203.3257,
        207.5646,
        208.8695,
        208.7294,
        210.9539,
        206.391,
        205.9706,
        205.1124,
        200.024,
        202.5638,
        209.3863,
        211.0678,
        214.4659,
        223.0312,
        226.4031,
        222.4269,
        222.4357,
        230.3704,
        227.1212,
        234.0488,
        230.6857,
        226.9198,
        225.0631,
        225.755,
        222.3218,
        216.3401,
        218.9237,
        221.6124,
        218.4814
      ],
      "analyst_rating": "Kaufen",
      "analyst_target": 236.43,
      "analyst_count": 22,
      "news": [
        {
          "titel": "Johnson & Johnson: Zwischen den Zeilen des jüngsten Analysten-Calls der JNJ-Aktie lesen",
          "einordnung": "Aktionäre sollten die Details des jüngsten Analysten-Calls genau prüfen, um zukünftige Strategien und potenzielle Auswirkungen auf den Aktienkurs zu verstehen.",
          "url": "https://www.trefis.com/articles/607982/reading-between-the-lines-of-jnj-stocks-latest-call/2026-07-20",
          "quelle": "Trefis",
          "datum": "20.07.2026"
        },
        {
          "titel": "Mercks Keytruda steht vor dem Patentablauf. Diese neuen Krebsmedikamente könnten übernehmen.",
          "einordnung": "Für JNJ-Aktionäre ist dies relevant, da neue Krebsmedikamente von Wettbewerbern oder JNJ selbst das Marktgefüge und zukünftige Einnahmequellen beeinflussen könnten.",
          "url": "https://www.barrons.com/articles/merck-keytruda-new-cancer-drugs-treatments-ec397d85?siteid=yhoof2&yptr=yahoo",
          "quelle": "Barrons.com",
          "datum": "20.07.2026"
        },
        {
          "titel": "Was ist wichtiger für Intuitive Surgical: Die heutigen Roboter oder das Wachstum von morgen?",
          "einordnung": "Für JNJ-Aktionäre ist die Abwägung zwischen aktuellen Produktstärken und zukünftigem Wachstumspotenzial im Medizintechnikbereich, in dem JNJ ebenfalls aktiv ist, von Bedeutung.",
          "url": "https://www.trefis.com/articles/607980/whats-more-important-for-intuitive-surgical-todays-robots-or-tomorrows-growth/2026-07-20",
          "quelle": "Trefis",
          "datum": "20.07.2026"
        },
        {
          "titel": "Jim Cramer: Alibaba ist „immer noch der beste Weg, um auf China zu setzen“, obwohl die Aktie seit Jahresbeginn um 18 % gefallen ist.",
          "einordnung": "Obwohl der Titel Alibaba betrifft, sollten JNJ-Aktionäre die allgemeine Einschätzung des chinesischen Marktes beachten, da dieser ein wichtiger Wachstumsmarkt für JNJ ist.",
          "url": "https://247wallst.com/investing/2026/07/20/jim-cramer-alibaba-is-still-the-best-way-to-play-china-despite-being-down-18-ytd/",
          "quelle": "24/7 Wall St.",
          "datum": "20.07.2026"
        }
      ],
      "fehler": null
    },
    {
      "wkn": "A0RLRP",
      "name": "Koei Tecmo",
      "ticker": "3635.T",
      "currency": "EUR",
      "price": 8.49,
      "change_1d_pct": 2.01,
      "change_1w_pct": -1.22,
      "change_1m_pct": 9.88,
      "change_1y_pct": -21.86,
      "week52_high": 11.73,
      "week52_low": 7.64,
      "div_yield": null,
      "div_rate": 0.26,
      "market_cap": "525.9B",
      "pe_ratio": 11.95,
      "sparkline": [
        7.9839,
        7.9893,
        8.0163,
        7.9677,
        7.8869,
        7.8033,
        7.895,
        7.8923,
        7.7225,
        7.8006,
        8.143,
        8.0971,
        7.9731,
        8.1052,
        8.1268,
        8.3182,
        8.1645,
        8.2562,
        8.4017,
        8.4341,
        8.5473,
        8.6012,
        8.6901,
        8.6281,
        8.5904,
        8.6254,
        8.5338,
        8.3667,
        8.3182,
        8.4853
      ],
      "analyst_rating": "Kaufen",
      "analyst_target": 10.77,
      "analyst_count": 9,
      "news": [
        {
          "titel": "Koei Tecmo (TSE:3635): Bewertung nach neuem Verkauf eigener Aktien und Details zum Aktienangebot",
          "einordnung": "Aktionäre sollten die Auswirkungen des Verkaufs eigener Aktien und des neuen Aktienangebots auf die Bewertung und den zukünftigen Aktienkurs genau prüfen.",
          "url": "https://finance.yahoo.com/news/koei-tecmo-tse-3635-assessing-112338756.html",
          "quelle": "Simply Wall St.",
          "datum": "15.09.2025"
        }
      ],
      "fehler": null
    },
    {
      "wkn": "856958",
      "name": "McDonald's",
      "ticker": "MCD",
      "currency": "EUR",
      "price": 234.0,
      "change_1d_pct": -0.2,
      "change_1w_pct": -1.99,
      "change_1m_pct": -5.86,
      "change_1y_pct": -7.47,
      "week52_high": 299.3,
      "week52_low": 231.29,
      "div_yield": null,
      "div_rate": 6.52,
      "market_cap": "189.8B",
      "pe_ratio": 22.03,
      "sparkline": [
        245.0839,
        243.2797,
        247.1945,
        247.431,
        249.4016,
        249.4366,
        250.5839,
        252.1691,
        248.5696,
        244.0066,
        236.5536,
        237.9198,
        239.8641,
        231.6841,
        236.2558,
        233.9962,
        236.7375,
        235.9668,
        245.7758,
        244.7861,
        247.1595,
        243.6913,
        242.1499,
        240.4947,
        238.7518,
        235.5377,
        232.0432,
        239.4963,
        234.4604,
        233.9959
      ],
      "analyst_rating": "Kaufen",
      "analyst_target": 286.08,
      "analyst_count": 31,
      "news": [
        {
          "titel": "Chinas Luckin Coffee kommt nach New York, und Starbucks sollte sich Sorgen machen.",
          "einordnung": "Für McDonald's-Aktionäre ist dies relevant, da es die Wettbewerbslandschaft im Fast-Food- und Getränkesektor in den USA verschärft, wo McDonald's ebenfalls aktiv ist.",
          "url": "https://247wallst.com/investing/2026/07/20/chinas-luckin-coffee-comes-to-new-york-and-starbucks-should-worry/",
          "quelle": "24/7 Wall St.",
          "datum": "20.07.2026"
        },
        {
          "titel": "Ist McDonald's (MCD) ein Kauf, da Wall Street-Analysten optimistisch erscheinen?",
          "einordnung": "Aktionäre sollten die Gründe für den Optimismus der Analysten prüfen, um fundierte Entscheidungen über Halten oder Kaufen der Aktie zu treffen.",
          "url": "https://finance.yahoo.com/markets/stocks/articles/mcdonalds-mcd-buy-wall-street-133004560.html",
          "quelle": "Zacks",
          "datum": "20.07.2026"
        },
        {
          "titel": "Ein schwacher Yen machte Tokio zum Schnäppchen. Ein starker Schekel machte Tel Aviv zur teuersten Stadt der Welt, um McDonald's zu kaufen.",
          "einordnung": "Dieser Titel zeigt, wie Wechselkurse und lokale Wirtschaftsfaktoren die Preisgestaltung und damit die Profitabilität von McDonald's in verschiedenen Märkten beeinflussen.",
          "url": "https://finance.yahoo.com/markets/currencies/articles/weak-yen-turned-tokyo-steal-100000076.html",
          "quelle": "Fortune",
          "datum": "19.07.2026"
        },
        {
          "titel": "FDA findet ausbruchsverursachenden Parasiten in Salatprobe von Taylor Farms.",
          "einordnung": "McDonald's-Aktionäre sollten die Auswirkungen auf die Lieferkette und das Markenimage beobachten, da Lebensmittelsicherheit für das Unternehmen von höchster Bedeutung ist.",
          "url": "https://www.yahoo.com/news/science/articles/fda-finds-outbreak-linked-parasite-063005891.html",
          "quelle": "Investing.com",
          "datum": "19.07.2026"
        }
      ],
      "fehler": null
    },
    {
      "wkn": "710000",
      "name": "Mercedes-Benz",
      "ticker": "MBG.DE",
      "currency": "EUR",
      "price": 45.13,
      "change_1d_pct": -0.83,
      "change_1w_pct": 1.91,
      "change_1m_pct": -0.31,
      "change_1y_pct": -6.28,
      "week52_high": 62.34,
      "week52_low": 42.62,
      "div_yield": null,
      "div_rate": 3.5,
      "market_cap": "43.2B",
      "pe_ratio": 8.87,
      "sparkline": [
        47.705,
        47.11,
        47.435,
        48.015,
        49.375,
        48.88,
        46.75,
        44.6,
        45.275,
        45.53,
        45.24,
        44.405,
        44.635,
        43.335,
        43.08,
        43.92,
        43.79,
        44.825,
        45.24,
        45.405,
        45.97,
        44.125,
        43.9,
        43.99,
        44.29,
        45.11,
        46.285,
        45.86,
        45.51,
        45.135
      ],
      "analyst_rating": "Kaufen",
      "analyst_target": 58.3,
      "analyst_count": 22,
      "news": [
        {
          "titel": "Mercedes droht US-Verbot ab 2030 wegen fast 20 % chinesischer Beteiligung.",
          "einordnung": "Aktionäre müssen das Risiko eines möglichen US-Verbots aufgrund der chinesischen Beteiligung genau beobachten, da dies erhebliche Auswirkungen auf den wichtigen US-Markt hätte.",
          "url": "https://finance.yahoo.com/economy/policy/articles/mercedes-faces-2030-us-ban-185049949.html",
          "quelle": "GuruFocus.com",
          "datum": "20.07.2026"
        },
        {
          "titel": "Mercedes versucht, Gesetzesentwurf zum Verbot von Autoherstellern mit China-Verbindungen abzumildern.",
          "einordnung": "Aktionäre sollten die Bemühungen des Unternehmens verfolgen, politische Risiken im Zusammenhang mit China-Verbindungen zu managen, um potenzielle negative Auswirkungen auf das Geschäft zu minimieren.",
          "url": "https://finance.yahoo.com/economy/policy/articles/mercedes-looks-soften-bill-ban-162237098.html",
          "quelle": "Bloomberg",
          "datum": "20.07.2026"
        },
        {
          "titel": "Mercedes-Benz (XTRA:MBG) enthüllt CLA 250 Plus als Konkurrenz zum Tesla Model 3.",
          "einordnung": "Aktionäre sollten die Markteinführung und den Erfolg des CLA 250 Plus genau beobachten, da er ein wichtiger Schritt im Wettbewerb mit Tesla im EV-Segment ist.",
          "url": "https://finance.yahoo.com/markets/stocks/articles/mercedes-benz-xtra-mbg-unveils-210728470.html",
          "quelle": "Simply Wall St.",
          "datum": "19.07.2026"
        },
        {
          "titel": "Yahoo Finance testet Mercedes-Benz' neues Luxus-Elektrofahrzeug, den CLA 250+.",
          "einordnung": "Positive Medienberichte über neue EV-Modelle wie den CLA 250+ können das Markenimage stärken und die Akzeptanz bei den Kunden fördern, was für Aktionäre vorteilhaft ist.",
          "url": "https://finance.yahoo.com/video/yahoo-finance-test-drives-mercedes-benzs-new-luxury-ev-the-cla-250-203949728.html",
          "quelle": "Yahoo Finance Video",
          "datum": "17.07.2026"
        }
      ],
      "fehler": null
    },
    {
      "wkn": "851995",
      "name": "PepsiCo",
      "ticker": "PEP",
      "currency": "EUR",
      "price": 118.12,
      "change_1d_pct": -1.64,
      "change_1w_pct": -2.61,
      "change_1m_pct": -4.75,
      "change_1y_pct": -1.05,
      "week52_high": 150.18,
      "week52_low": 117.31,
      "div_yield": null,
      "div_rate": 5.18,
      "market_cap": "184.2B",
      "pe_ratio": 17.7,
      "sparkline": [
        124.2935,
        123.2075,
        125.0467,
        126.3955,
        125.8787,
        126.3517,
        128.0857,
        127.9719,
        124.0045,
        124.3811,
        123.2338,
        124.4074,
        124.6001,
        122.1916,
        123.8294,
        121.4559,
        118.5833,
        123.6279,
        126.3079,
        125.4934,
        126.9735,
        124.8103,
        120.7378,
        120.3174,
        121.2895,
        118.6271,
        118.5833,
        122.1128,
        120.0897,
        118.1191
      ],
      "analyst_rating": "Halten",
      "analyst_target": 136.39,
      "analyst_count": 22,
      "news": [
        {
          "titel": "Die Geschichte hat eine Meinung zu diesem CELH-Preisniveau.",
          "einordnung": "Für PepsiCo-Aktionäre ist die Bewertung von Wettbewerbern wie Celsius Holdings (CELH) relevant, da PepsiCo eine strategische Partnerschaft und Beteiligung an diesem Unternehmen hält.",
          "url": "https://www.trefis.com/articles/607934/history-has-an-opinion-on-this-celh-price-level/2026-07-20",
          "quelle": "Trefis",
          "datum": "20.07.2026"
        },
        {
          "titel": "Ein weiterer beliebter Limonadenriese schließt Lagerbetrieb und streicht 184 Arbeitsplätze.",
          "einordnung": "PepsiCo-Aktionäre sollten solche Nachrichten im Wettbewerbsumfeld beobachten, da sie auf Effizienzmaßnahmen oder Marktveränderungen in der Getränkeindustrie hindeuten können.",
          "url": "https://www.thestreet.com/employment/pepsico-soda-giant-closes-warehouse-cuts-184-jobs",
          "quelle": "TheStreet",
          "datum": "18.07.2026"
        },
        {
          "titel": "PepsiCo, Inc. (PEP) zieht die Aufmerksamkeit von Investoren auf sich: Das sollten Sie wissen.",
          "einordnung": "Aktionäre sollten die Gründe für das erhöhte Investoreninteresse verstehen, um die aktuelle Marktposition und zukünftige Aussichten des Unternehmens besser einschätzen zu können.",
          "url": "https://finance.yahoo.com/markets/stocks/articles/pepsico-inc-pep-attracting-investor-130021453.html",
          "quelle": "Zacks",
          "datum": "17.07.2026"
        },
        {
          "titel": "Warum die PepsiCo-Aktie auf einem 1-Jahres-Tief steht.",
          "einordnung": "Aktionäre sollten die Ursachen für das 1-Jahres-Tief genau analysieren, um potenzielle Risiken oder Kaufgelegenheiten zu identifizieren.",
          "url": "https://finance.yahoo.com/markets/stocks/article/why-pepsicos-stock-is-at-a-1-year-low-134141497.html",
          "quelle": "Yahoo Finance",
          "datum": "16.07.2026"
        }
      ],
      "fehler": null
    },
    {
      "wkn": "899744",
      "name": "Realty Income",
      "ticker": "O",
      "currency": "EUR",
      "price": 57.01,
      "change_1d_pct": -0.94,
      "change_1w_pct": 1.43,
      "change_1m_pct": 7.93,
      "change_1y_pct": 21.83,
      "week52_high": 59.5,
      "week52_low": 48.92,
      "div_yield": null,
      "div_rate": 2.85,
      "market_cap": "60.7B",
      "pe_ratio": 53.35,
      "sparkline": [
        53.0546,
        52.3308,
        53.4121,
        54.1621,
        53.9877,
        54.694,
        54.1883,
        54.2144,
        52.8192,
        52.5314,
        52.8279,
        53.6563,
        54.0575,
        54.1011,
        55.0429,
        54.9731,
        54.2646,
        54.142,
        55.9111,
        55.3418,
        56.06,
        55.3768,
        55.3243,
        55.4469,
        56.2001,
        55.8498,
        55.4031,
        57.5838,
        57.5488,
        57.0058
      ],
      "analyst_rating": "Kaufen",
      "analyst_target": 59.74,
      "analyst_count": 20,
      "news": [
        {
          "titel": "Realty Income strebt Wachstum durch Partnerschaften an: Kaufen oder Halten? (Überarbeitet)",
          "einordnung": "Aktionäre sollten die Strategie des Wachstums durch Partnerschaften genau prüfen, um die langfristigen Aussichten und die Empfehlung zum Kauf oder Halten der Aktie zu bewerten.",
          "url": "https://finance.yahoo.com/real-estate/articles/realty-income-eyes-growth-via-141500652.html",
          "quelle": "Zacks",
          "datum": "20.07.2026"
        },
        {
          "titel": "Würden Sie lieber heute 55.000 $ oder in 20 Jahren 110.000 $ verdienen?",
          "einordnung": "Dieser Titel regt zum Nachdenken über den Zeitwert des Geldes und langfristige Investitionsstrategien an, was für Realty Income-Aktionäre bei der Bewertung von Dividenden und Wachstum relevant ist.",
          "url": "https://247wallst.com/personal-finance/2026/07/19/would-you-rather-earn-55000-today-or-110000-in-20-years/",
          "quelle": "24/7 Wall St.",
          "datum": "19.07.2026"
        },
        {
          "titel": "2 passive Einkommensaktien, die ich für das nächste Jahrzehnt halten möchte.",
          "einordnung": "Für Realty Income-Aktionäre ist dies eine Bestätigung des Potenzials für langfristiges passives Einkommen, was die Attraktivität der Aktie als Halteposition unterstreicht.",
          "url": "https://www.fool.com/investing/2026/07/19/2-passive-income-stocks-i-plan-to-hold-for-the-nex/",
          "quelle": "Motley Fool",
          "datum": "19.07.2026"
        },
        {
          "titel": "Das Portfolio, mit dem Sie die Inflation ignorieren können",
          "einordnung": "Dieser Titel deutet auf eine potenzielle Anlagestrategie hin, die darauf abzielt, das Vermögen von Aktionären vor Inflationsdruck zu schützen.",
          "url": "https://247wallst.com/personal-finance/2026/07/19/the-portfolio-that-lets-you-ignore-inflation/",
          "quelle": "24/7 Wall St.",
          "datum": "19.07.2026"
        }
      ],
      "fehler": null
    },
    {
      "wkn": "852147",
      "name": "Rio Tinto",
      "ticker": "RIO",
      "currency": "EUR",
      "price": 77.71,
      "change_1d_pct": -1.58,
      "change_1w_pct": -1.25,
      "change_1m_pct": -13.58,
      "change_1y_pct": 50.56,
      "week52_high": 98.6,
      "week52_low": 51.15,
      "div_yield": null,
      "div_rate": 3.52,
      "market_cap": "144.3B",
      "pe_ratio": 14.57,
      "sparkline": [
        88.1843,
        88.3945,
        88.8236,
        86.7567,
        90.7679,
        92.2655,
        92.7385,
        92.6071,
        89.9184,
        87.6501,
        87.0195,
        83.709,
        82.3515,
        83.2973,
        82.0975,
        82.5792,
        83.1397,
        81.7559,
        82.693,
        81.9574,
        79.9168,
        77.771,
        78.3753,
        79.2949,
        78.6906,
        81.7034,
        81.9924,
        79.4088,
        78.9534,
        77.7097
      ],
      "analyst_rating": "Kaufen",
      "analyst_target": 92.38,
      "analyst_count": 8,
      "news": [
        {
          "titel": "Rio Tinto (LSE:RIO) liefert Rekord-Eisenerzlieferungen und senkt die Kupferkosten für 2026",
          "einordnung": "Dies sind positive Nachrichten für Aktionäre, da Rekordlieferungen und Kostensenkungen auf verbesserte Rentabilität und Effizienz hindeuten.",
          "url": "https://finance.yahoo.com/markets/stocks/articles/rio-tinto-lse-rio-delivers-071226796.html",
          "quelle": "Simply Wall St.",
          "datum": "17.07.2026"
        },
        {
          "titel": "Rio Tinto meldet einen sequenziellen Anstieg der Eisenerzlieferungen im 2. Quartal um 18%",
          "einordnung": "Ein signifikanter Anstieg der Lieferungen im Quartalsvergleich ist ein positives Zeichen für die operative Leistung und den Umsatz von Rio Tinto.",
          "url": "https://finance.yahoo.com/markets/commodities/articles/rio-tinto-reports-18-sequential-150000082.html",
          "quelle": "Zacks",
          "datum": "16.07.2026"
        },
        {
          "titel": "BHP meldet Rekord-Eisenerzproduktion für GJ26 dank starker WAIO-Leistung",
          "einordnung": "Dieser Titel bezieht sich auf einen Konkurrenten, deutet aber auf eine starke Marktnachfrage nach Eisenerz hin, was auch für Rio Tinto positiv sein könnte.",
          "url": "https://finance.yahoo.com/markets/commodities/articles/bhp-reports-record-fy26-iron-150000072.html",
          "quelle": "Zacks",
          "datum": "16.07.2026"
        },
        {
          "titel": "Fortschritte beim Kupfer- und Goldprojekt in der Mongolei bestätigen Rio Tinto PLC ADR (RIO) als Top-Dividendenaktie",
          "einordnung": "Projektfortschritte und die Einstufung als Top-Dividendenaktie sind sehr positive Signale für Aktionäre, die auf langfristiges Wachstum und Erträge abzielen.",
          "url": "https://finance.yahoo.com/markets/stocks/articles/mongolia-copper-gold-project-progress-133425921.html",
          "quelle": "Insider Monkey",
          "datum": "16.07.2026"
        }
      ],
      "fehler": null
    },
    {
      "wkn": "A3C99G",
      "name": "Shell",
      "ticker": "SHELL.AS",
      "currency": "EUR",
      "price": 37.91,
      "change_1d_pct": -0.34,
      "change_1w_pct": 3.85,
      "change_1m_pct": 9.77,
      "change_1y_pct": 30.88,
      "week52_high": 41.33,
      "week52_low": 29.55,
      "div_yield": null,
      "div_rate": 1.37,
      "market_cap": "210.0B",
      "pe_ratio": 13.44,
      "sparkline": [
        36.84,
        37.54,
        37.92,
        37.31,
        35.68,
        35.5,
        35.11,
        34.21,
        34.535,
        34.935,
        34.865,
        34.255,
        34.04,
        33.7,
        33.72,
        34.065,
        33.595,
        33.965,
        33.885,
        34.16,
        35.275,
        36.15,
        35.74,
        35.725,
        36.505,
        36.865,
        36.92,
        37.25,
        38.04,
        37.91
      ],
      "analyst_rating": "Kaufen",
      "analyst_target": 42.56,
      "analyst_count": 7,
      "news": [
        {
          "titel": "2 Kaufempfehlungen, 1 Halten: Mizuho beginnt die Berichterstattung über drei große Ölaktien",
          "einordnung": "Neue Analystenbewertungen können die Marktstimmung beeinflussen; Kaufempfehlungen sind generell positiv für den Aktienkurs.",
          "url": "https://finance.yahoo.com/energy/articles/2-buy-calls-1-hold-134358660.html",
          "quelle": "Investing.com",
          "datum": "20.07.2026"
        },
        {
          "titel": "International Paper erweitert den Vorstand mit zwei neuen Ernennungen",
          "einordnung": "Dieser Titel betrifft International Paper und ist für Shell-Aktionäre nicht direkt relevant.",
          "url": "https://www.packaging-gateway.com/news/international-paper-expands-board/",
          "quelle": "Packaging Gateway",
          "datum": "20.07.2026"
        },
        {
          "titel": "Boohoo von neuer £10 Mio. Klage wegen „Sweatshops“ in Leicester betroffen",
          "einordnung": "Dieser Titel betrifft Boohoo und ist für Shell-Aktionäre nicht direkt relevant.",
          "url": "https://www.telegraph.co.uk/business/2026/07/19/boohoo-hit-by-new-10m-legal-claim-over-leicester-sweatshops/",
          "quelle": "The Telegraph",
          "datum": "19.07.2026"
        },
        {
          "titel": "Shell (SHEL) steigt, während der Markt fällt: Einige Fakten, die zu beachten sind",
          "einordnung": "Die Outperformance des Marktes ist ein starkes positives Signal für Aktionäre, das auf die Widerstandsfähigkeit oder spezifische Stärken des Unternehmens hindeutet.",
          "url": "https://finance.yahoo.com/markets/stocks/articles/shell-shel-ascends-while-market-221503167.html",
          "quelle": "Zacks",
          "datum": "17.07.2026"
        }
      ],
      "fehler": null
    },
    {
      "wkn": "723133",
      "name": "Sixt",
      "ticker": "SIX2.DE",
      "currency": "EUR",
      "price": 70.95,
      "change_1d_pct": 0.71,
      "change_1w_pct": 1.65,
      "change_1m_pct": -3.01,
      "change_1y_pct": -20.21,
      "week52_high": 98.2,
      "week52_low": 57.7,
      "div_yield": null,
      "div_rate": 3.2,
      "market_cap": "3.3B",
      "pe_ratio": 11.12,
      "sparkline": [
        68.9045,
        70.0537,
        69.3354,
        71.3944,
        71.7296,
        71.2029,
        72.4,
        73.25,
        73.15,
        71.2,
        70.55,
        66.85,
        67.55,
        66.15,
        65.0,
        63.7,
        64.95,
        65.3,
        66.25,
        68.6,
        68.15,
        66.9,
        67.95,
        71.4,
        69.8,
        68.85,
        70.2,
        70.5,
        70.45,
        70.95
      ],
      "analyst_rating": "Starker Kauf",
      "analyst_target": 96.0,
      "analyst_count": 7,
      "news": [
        {
          "titel": "Kaufen Sie Sixt SE (ETR:SIX2) nicht überstürzt, nur weil sie ex-Dividende geht",
          "einordnung": "Dieser Hinweis warnt Aktionäre davor, nur wegen der bevorstehenden Dividendenausschüttung zu kaufen, und legt nahe, eine umfassendere Analyse durchzuführen.",
          "url": "https://finance.yahoo.com/markets/stocks/articles/dont-race-buy-sixt-se-061259094.html",
          "quelle": "Simply Wall St.",
          "datum": "14.06.2026"
        },
        {
          "titel": "Ecos (India) Mobility & Hospitality Ltd (NSE:ECOSMOBLTY) Q4 2026 Earnings Call Highlights: ...",
          "einordnung": "Dieser Titel bezieht sich auf ein anderes Unternehmen und ist für Sixt-Aktionäre nicht direkt relevant.",
          "url": "https://finance.yahoo.com/markets/stocks/articles/ecos-india-mobility-hospitality-ltd-010150184.html",
          "quelle": "GuruFocus.com",
          "datum": "30.05.2026"
        },
        {
          "titel": "Sixt SE (ETR:SIX2) hat gerade die Ergebnisse des ersten Quartals gemeldet: Haben Analysten ihre Meinung zur Aktie geändert?",
          "einordnung": "Die Reaktion der Analysten auf die jüngsten Quartalsergebnisse ist entscheidend für die kurzfristige Kursentwicklung und die Marktstimmung.",
          "url": "https://finance.yahoo.com/markets/stocks/articles/sixt-se-etr-six2-just-060916116.html",
          "quelle": "Simply Wall St.",
          "datum": "16.05.2026"
        },
        {
          "titel": "Eine Betrachtung der Bewertung von Sixt (XTRA:SIX2) nach der jüngsten Aktienkursvolatilität",
          "einordnung": "Eine Neubewertung nach Kursvolatilität ist wichtig für Aktionäre, um die aktuelle Attraktivität der Aktie zu beurteilen.",
          "url": "https://finance.yahoo.com/markets/stocks/articles/look-sixt-xtra-six2-valuation-090954777.html",
          "quelle": "Simply Wall St.",
          "datum": "05.05.2026"
        }
      ],
      "fehler": null
    },
    {
      "wkn": "852654",
      "name": "Texas Instruments",
      "ticker": "TXN",
      "currency": "EUR",
      "price": 249.39,
      "change_1d_pct": 0.26,
      "change_1w_pct": -4.63,
      "change_1m_pct": -5.67,
      "change_1y_pct": 36.43,
      "week52_high": 292.54,
      "week52_low": 133.76,
      "div_yield": null,
      "div_rate": 4.97,
      "market_cap": "259.2B",
      "pe_ratio": 48.68,
      "sparkline": [
        249.6555,
        254.7702,
        252.7822,
        246.9844,
        260.2002,
        263.7209,
        274.4232,
        267.7408,
        264.3865,
        282.7608,
        291.0108,
        266.5585,
        265.4637,
        273.0832,
        249.9796,
        250.0234,
        261.0497,
        261.3475,
        256.6795,
        265.8053,
        256.8721,
        263.8961,
        270.2106,
        272.7767,
        261.4876,
        267.6007,
        263.7822,
        255.0505,
        248.7447,
        249.3927
      ],
      "analyst_rating": "Kaufen",
      "analyst_target": 265.89,
      "analyst_count": 32,
      "news": [
        {
          "titel": "Tesla, Alphabet, Intel, GM: Diese Woche stehen wichtige Gewinnberichte an",
          "einordnung": "Obwohl Texas Instruments nicht direkt genannt wird, sind die Ergebnisse großer Tech- und Automobilunternehmen wichtige Indikatoren für die Nachfrage nach Halbleitern.",
          "url": "https://finance.yahoo.com/video/tesla-alphabet-intel-gm-earnings-000000527.html",
          "quelle": "Yahoo Finance Video",
          "datum": "20.07.2026"
        },
        {
          "titel": "S&P 500, Nasdaq steigen mit Chip-Schub; Iran und Megacap-Gewinne im Fokus",
          "einordnung": "Ein 'Chip-Schub' ist ein positives Zeichen für den gesamten Halbleitersektor, einschließlich Texas Instruments, und deutet auf eine starke Nachfrage hin.",
          "url": "https://finance.yahoo.com/markets/stocks/articles/wall-st-futures-edge-higher-095551303.html",
          "quelle": "Reuters",
          "datum": "20.07.2026"
        },
        {
          "titel": "Die Tech-Branche steht vor einem Moment der Wahrheit, da die Gewinnberichte die Rallye auf die Probe stellen",
          "einordnung": "Die bevorstehenden Gewinnberichte sind entscheidend, um zu sehen, ob die aktuelle Tech-Rallye nachhaltig ist, was auch Texas Instruments betreffen wird.",
          "url": "https://www.barrons.com/articles/tech-earnings-week-qqq-stock-market-outlook-47c5a64d?siteid=yhoof2&yptr=yahoo",
          "quelle": "Barrons.com",
          "datum": "20.07.2026"
        },
        {
          "titel": "Ausblick auf die Woche: Die Wall Street bereitet sich auf Volatilität vor, da die Gewinnberichte der Big Tech an Fahrt aufnehmen",
          "einordnung": "Erhöhte Volatilität und die Ergebnisse von Big Tech können den gesamten Technologiesektor, einschließlich Texas Instruments, beeinflussen.",
          "url": "https://www.proactiveinvestors.com/companies/news/1095711/week-ahead-wall-street-gears-up-for-volatility-as-big-tech-earnings-kick-into-high-gear-1095711.html",
          "quelle": "Proactive",
          "datum": "20.07.2026"
        }
      ],
      "fehler": null
    },
    {
      "wkn": "869561",
      "name": "UnitedHealth",
      "ticker": "UNH",
      "currency": "EUR",
      "price": 370.02,
      "change_1d_pct": -0.84,
      "change_1w_pct": -1.54,
      "change_1m_pct": 5.75,
      "change_1y_pct": 53.76,
      "week52_high": 404.29,
      "week52_low": 205.46,
      "div_yield": null,
      "div_rate": 8.13,
      "market_cap": "383.7B",
      "pe_ratio": 31.79,
      "sparkline": [
        347.869,
        354.0519,
        359.6513,
        354.8269,
        353.1636,
        355.75,
        359.9888,
        357.0199,
        349.9084,
        351.1608,
        356.1703,
        358.4212,
        355.3996,
        363.9212,
        374.7461,
        367.6784,
        364.0088,
        373.5637,
        372.5303,
        366.0756,
        375.0088,
        372.7405,
        378.0653,
        371.8822,
        375.797,
        372.3814,
        366.5398,
        370.7962,
        373.1696,
        370.0167
      ],
      "analyst_rating": "Kaufen",
      "analyst_target": 413.07,
      "analyst_count": 26,
      "news": [
        {
          "titel": "UnitedHealth Group (UNH) ist eine großartige Momentum-Aktie: Sollten Sie kaufen?",
          "einordnung": "Die Einstufung als Momentum-Aktie deutet auf eine starke kurzfristige Kursentwicklung hin, was für wachstumsorientierte Aktionäre interessant sein kann.",
          "url": "https://finance.yahoo.com/markets/stocks/articles/unitedhealth-group-unh-great-momentum-160002331.html",
          "quelle": "Zacks",
          "datum": "20.07.2026"
        },
        {
          "titel": "Das wahre Risiko in der UnitedHealth-Aktie",
          "einordnung": "Dieser Titel warnt Aktionäre vor potenziellen internen Risiken, die eine genauere Untersuchung erfordern, um fundierte Entscheidungen zu treffen.",
          "url": "https://www.trefis.com/articles/607940/the-real-risk-inside-unitedhealth-stock/2026-07-20",
          "quelle": "Trefis",
          "datum": "20.07.2026"
        },
        {
          "titel": "Tempus kauft Krebs-Test-Hersteller Personalis für 1,5 Mrd. $",
          "einordnung": "Dieser Titel betrifft eine Akquisition durch Tempus und ist für UnitedHealth-Aktionäre nicht direkt relevant.",
          "url": "https://www.medtechdive.com/news/tempus-to-buy-cancer-test-maker-personalis-for-15b/825684/",
          "quelle": "MedTech Dive",
          "datum": "20.07.2026"
        },
        {
          "titel": "UNH-Aktie setzt starke Monatsentwicklung fort: Wall Street feiert 'beeindruckendes' Q2 und sieht über 20% weiteres Aufwärtspotenzial.",
          "einordnung": "Die beeindruckenden Quartalszahlen und das prognostizierte Kurspotenzial von über 20% sind sehr positive Nachrichten für Ihre UNH-Aktien.",
          "url": "https://stocktwits.com/news-articles/markets/equity/unh-wall-street-impressive-q2-more-room-to-run/cZZLvPfR7MU",
          "quelle": "Stocktwits",
          "datum": "20.07.2026"
        }
      ],
      "fehler": null
    }
  ]
}