{
  "aktualisiert": "2026-06-18T20:14:42.865886+00:00",
  "aktien": [
    {
      "wkn": "A1J84E",
      "name": "AbbVie",
      "ticker": "ABBV",
      "currency": "EUR",
      "price": 188.95,
      "change_1d_pct": -2.09,
      "change_1w_pct": -3.63,
      "change_1m_pct": 1.33,
      "change_1y_pct": 20.71,
      "week52_high": 213.55,
      "week52_low": 158.52,
      "div_yield": null,
      "div_rate": 6.04,
      "market_cap": "382.7B",
      "pe_ratio": 105.66,
      "sparkline": [
        176.8239,
        175.8121,
        176.885,
        181.3163,
        181.8745,
        183.8547,
        183.5232,
        182.6683,
        186.4628,
        185.1893,
        187.1084,
        188.1551,
        185.9046,
        187.8934,
        190.711,
        189.9172,
        185.7388,
        187.8934,
        189.4025,
        196.2152,
        198.2127,
        194.584,
        196.6339,
        196.2239,
        196.0669,
        198.6489,
        193.293,
        194.0606,
        192.9789,
        188.9489
      ],
      "analyst_rating": "Kaufen",
      "analyst_target": 221.17,
      "analyst_count": 29,
      "news": [
        {
          "titel": "AbbVie (ABBV) erhält neue SKINVIVE-Zulassung, während CLL-Studienergebnisse beeindrucken.",
          "einordnung": "Positive Nachrichten über neue Produktzulassungen und vielversprechende Studienergebnisse stärken das zukünftige Umsatzpotenzial und die Marktposition von AbbVie.",
          "url": "https://finance.yahoo.com/healthcare/articles/abbvie-abbv-lands-skinvive-approval-111353011.html",
          "quelle": "Simply Wall St.",
          "datum": "18.06.2026"
        },
        {
          "titel": "Die Billionen-Dollar-Frage der Eli Lilly Aktie.",
          "einordnung": "Dieser Titel bezieht sich auf einen Konkurrenten und deutet auf eine allgemeine Branchenbewertung hin, die indirekt auch AbbVie betreffen könnte, indem sie die Erwartungen an große Pharmaunternehmen beeinflusst.",
          "url": "https://www.trefis.com/articles/603350/eli-lilly-stocks-trillion-dollar-question/2026-06-17",
          "quelle": "Trefis",
          "datum": "17.06.2026"
        },
        {
          "titel": "AbbVie Inc. (ABBV) präsentiert Daten zu einer Venetoclax-basierten Kombinationstherapie mit fester Dauer.",
          "einordnung": "Die Präsentation neuer Daten zu Therapien unterstreicht die Forschungs- und Entwicklungsaktivitäten von AbbVie und kann zukünftige Produktpipeline-Erfolge signalisieren.",
          "url": "https://finance.yahoo.com/healthcare/articles/abbvie-inc-abbv-presents-data-173447428.html",
          "quelle": "Insider Monkey",
          "datum": "17.06.2026"
        },
        {
          "titel": "Die Zahl, die die Johnson & Johnson Aktie auf die Probe stellen könnte.",
          "einordnung": "Ähnlich wie bei Eli Lilly bezieht sich dieser Titel auf einen Konkurrenten und könnte auf branchenweite Herausforderungen oder Trends hindeuten, die auch AbbVie beeinflussen könnten.",
          "url": "https://www.trefis.com/articles/603355/the-number-that-could-test-johnson-johnson-stock/2026-06-17",
          "quelle": "Trefis",
          "datum": "17.06.2026"
        }
      ],
      "fehler": null
    },
    {
      "wkn": "A2ANT0",
      "name": "Ahold Delhaize",
      "ticker": "AD.AS",
      "currency": "EUR",
      "price": 34.52,
      "change_1d_pct": -2.46,
      "change_1w_pct": -4.64,
      "change_1m_pct": -8.17,
      "change_1y_pct": 0.15,
      "week52_high": 42.54,
      "week52_low": 32.13,
      "div_yield": null,
      "div_rate": null,
      "market_cap": "30.4B",
      "pe_ratio": 13.7,
      "sparkline": [
        37.19,
        36.9,
        36.72,
        36.5,
        36.51,
        36.8,
        37.63,
        38.05,
        37.59,
        37.05,
        36.65,
        36.62,
        36.27,
        36.7,
        36.4,
        36.17,
        35.66,
        34.94,
        35.26,
        35.22,
        35.85,
        35.37,
        35.75,
        36.18,
        36.2,
        36.37,
        36.01,
        36.21,
        35.39,
        34.52
      ],
      "analyst_rating": "Halten",
      "analyst_target": 39.82,
      "analyst_count": 17,
      "news": [
        {
          "titel": "Ahold Delhaize nominiert ehemaligen Amazon-Manager als US-CEO.",
          "einordnung": "Die Ernennung eines erfahrenen Managers von Amazon könnte auf eine strategische Neuausrichtung und Stärkung der Wettbewerbsfähigkeit von Ahold Delhaize im US-Markt hindeuten.",
          "url": "https://www.grocerydive.com/news/ahold-delhaize-usa-ceo-nominee-former-amazon-fresh-veteran-claire-peters/823251/",
          "quelle": "Grocery Dive",
          "datum": "18.06.2026"
        },
        {
          "titel": "Lebensmittelkette zahlt hohe Strafe, wegen überhöhter Preisangaben angeklagt.",
          "einordnung": "Eine hohe Strafe und Anschuldigungen wegen Preismanipulation können das Markenimage und die finanzielle Performance von Ahold Delhaize kurzfristig belasten.",
          "url": "https://www.thestreet.com/retail/grocery-chain-ahold-delhaize-fined-price-reporting-inflation",
          "quelle": "TheStreet",
          "datum": "17.06.2026"
        },
        {
          "titel": "Wie Investoren auf die 40-Millionen-Dollar-Apotheken-Vergleichszahlung von Koninklijke Ahold Delhaize (ENXTAM:AD) reagieren könnten.",
          "einordnung": "Eine Vergleichszahlung kann zwar kurzfristig die Gewinne schmälern, aber auch rechtliche Unsicherheiten beseitigen und den Weg für zukünftiges Wachstum ebnen.",
          "url": "https://finance.yahoo.com/markets/stocks/articles/investors-may-respond-koninklijke-ahold-231317367.html",
          "quelle": "Simply Wall St.",
          "datum": "13.06.2026"
        },
        {
          "titel": "Die Ahold Delhaize (ENXTAM:AD) Aktie und die Erklärung der 10,9%igen Unterbewertungs-Narrative.",
          "einordnung": "Eine mögliche Unterbewertung der Aktie könnte für Anleger eine Kaufgelegenheit darstellen, wenn die Fundamentaldaten des Unternehmens stark sind und das Potenzial für eine Wertsteigerung besteht.",
          "url": "https://finance.yahoo.com/markets/stocks/articles/ahold-delhaize-enxtam-ad-stock-061033846.html",
          "quelle": "Simply Wall St.",
          "datum": "13.06.2026"
        }
      ],
      "fehler": null
    },
    {
      "wkn": "840400",
      "name": "Allianz",
      "ticker": "ALV.DE",
      "currency": "EUR",
      "price": 400.0,
      "change_1d_pct": -0.05,
      "change_1w_pct": 4.36,
      "change_1m_pct": 3.71,
      "change_1y_pct": 23.9,
      "week52_high": 401.6,
      "week52_low": 333.2,
      "div_yield": null,
      "div_rate": null,
      "market_cap": "151.7B",
      "pe_ratio": 12.92,
      "sparkline": [
        369.1,
        371.7,
        368.2,
        372.3,
        380.3,
        374.5,
        381.4,
        382.6,
        385.7,
        385.9,
        385.6,
        391.0,
        388.9,
        389.4,
        380.9,
        381.6,
        374.9,
        376.7,
        368.6,
        371.3,
        372.8,
        374.1,
        377.9,
        381.5,
        383.3,
        386.4,
        394.7,
        399.0,
        400.2,
        400.0
      ],
      "analyst_rating": "Kaufen",
      "analyst_target": 398.01,
      "analyst_count": 17,
      "news": [
        {
          "titel": "HSBC kurz davor, Käufer für das Versicherungsgeschäft in Singapur zu wählen.",
          "einordnung": "Dieser Titel deutet auf eine Konsolidierung im Versicherungssektor hin, die für Allianz als potenziellen Käufer oder Konkurrenten relevant sein könnte.",
          "url": "https://finance.yahoo.com/markets/stocks/articles/hsbc-close-picking-buyer-singapore-130400684.html",
          "quelle": "Zacks",
          "datum": "16.06.2026"
        },
        {
          "titel": "Allianz führt das Rennen um das Versicherungsgeschäft von HSBC in Singapur an – Bericht.",
          "einordnung": "Ein potenzieller Erwerb des HSBC-Geschäfts in Singapur würde die Marktposition der Allianz in Asien stärken und Wachstumschancen eröffnen.",
          "url": "https://www.lifeinsuranceinternational.com/news/allianz-race-hsbc-singapore-insurance/",
          "quelle": "Life Insurance International",
          "datum": "15.06.2026"
        },
        {
          "titel": "Die Wall Street erhält Zugang zu neuen Katastrophenmodellen zur Vorhersage von Kriegen.",
          "einordnung": "Neue Risikomodelle könnten für Versicherer wie die Allianz relevant sein, um potenzielle Verluste aus geopolitischen Ereignissen besser einschätzen und managen zu können.",
          "url": "https://finance.yahoo.com/economy/policy/articles/wall-street-gaining-access-catastrophe-090000532.html",
          "quelle": "Bloomberg",
          "datum": "15.06.2026"
        },
        {
          "titel": "Trump ernennt Anwalt, der ihm bei der Verteidigung half, zum obersten Aufseher der Wall Street.",
          "einordnung": "Eine neue Besetzung an der Spitze der Finanzaufsicht könnte zukünftige Regulierungen und die Geschäftsumgebung für Finanzdienstleister wie die Allianz beeinflussen.",
          "url": "https://finance.yahoo.com/economy/policy/articles/trump-taps-lawyer-helped-defend-221337087.html",
          "quelle": "Bloomberg",
          "datum": "13.06.2026"
        }
      ],
      "fehler": null
    },
    {
      "wkn": "850471",
      "name": "Boeing",
      "ticker": "BA",
      "currency": "EUR",
      "price": 194.33,
      "change_1d_pct": -1.26,
      "change_1w_pct": 0.52,
      "change_1m_pct": 3.61,
      "change_1y_pct": 12.09,
      "week52_high": 221.87,
      "week52_low": 154.2,
      "div_yield": null,
      "div_rate": null,
      "market_cap": "175.6B",
      "pe_ratio": 88.06,
      "sparkline": [
        201.5275,
        207.0491,
        207.7906,
        206.6217,
        209.8754,
        199.9399,
        192.3334,
        192.4381,
        187.5532,
        193.8251,
        191.5658,
        191.0511,
        190.9465,
        195.6569,
        199.5648,
        201.6321,
        195.6569,
        189.8997,
        183.6889,
        189.6555,
        187.937,
        188.347,
        187.1171,
        182.3107,
        193.3279,
        191.0773,
        199.7131,
        198.4395,
        196.8171,
        194.331
      ],
      "analyst_rating": "Kaufen",
      "analyst_target": 235.52,
      "analyst_count": 25,
      "news": [
        {
          "titel": "Weltraum-ETFs der alten Garde legen seit dem SpaceX-Börsengang gegenüber New-Age-Aktien zu.",
          "einordnung": "Dieser Titel deutet auf eine Verschiebung der Anlegerpräferenzen innerhalb des Weltraumsektors hin, was auch für etablierte Akteure wie Boeing relevant sein könnte.",
          "url": "https://finance.yahoo.com/video/old-age-space-etfs-gain-over-new-age-stocks-since-spacex-ipo-202022510.html",
          "quelle": "Yahoo Finance Video",
          "datum": "17.06.2026"
        },
        {
          "titel": "Das übersehene Signal in den Lieferverzögerungen der GE-Aktie.",
          "einordnung": "Lieferkettenprobleme bei einem großen Industrieunternehmen wie GE könnten auf branchenweite Herausforderungen hindeuten, die auch Boeing betreffen könnten.",
          "url": "https://www.trefis.com/articles/603583/the-overlooked-signal-in-ge-stocks-shipping-delays/2026-06-18",
          "quelle": "Trefis",
          "datum": "18.06.2026"
        },
        {
          "titel": "Reicht der große Auftragsbestand der GE-Aktie aus, um einen Abschwung zu überfliegen?",
          "einordnung": "Ein großer Auftragsbestand ist ein positives Zeichen für die zukünftige Stabilität eines Unternehmens, und diese Frage bei GE könnte auch für Boeing relevant sein, das ebenfalls einen großen Auftragsbestand hat.",
          "url": "https://www.trefis.com/articles/603566/is-ge-stocks-large-backlog-enough-to-out-fly-a-slowdown/2026-06-18",
          "quelle": "Trefis",
          "datum": "18.06.2026"
        },
        {
          "titel": "Ist Boeing (BA) ein Kauf, da Wall Street Analysten optimistisch wirken?",
          "einordnung": "Der Optimismus von Analysten deutet auf ein positives Sentiment für die Boeing-Aktie hin, was auf zukünftige Kursgewinne hindeuten könnte.",
          "url": "https://finance.yahoo.com/markets/stocks/articles/boeing-ba-buy-wall-street-133004162.html",
          "quelle": "Zacks",
          "datum": "18.06.2026"
        }
      ],
      "fehler": null
    },
    {
      "wkn": "850501",
      "name": "Bristol-Myers Squibb",
      "ticker": "BMY",
      "currency": "EUR",
      "price": 47.11,
      "change_1d_pct": -2.3,
      "change_1w_pct": -5.08,
      "change_1m_pct": -7.37,
      "change_1y_pct": 21.02,
      "week52_high": 54.86,
      "week52_low": 37.09,
      "div_yield": null,
      "div_rate": 2.2,
      "market_cap": "110.3B",
      "pe_ratio": 15.13,
      "sparkline": [
        49.0669,
        48.9884,
        48.5609,
        49.2413,
        49.189,
        49.5205,
        49.7211,
        49.9915,
        50.8638,
        51.0644,
        51.9455,
        51.867,
        50.6196,
        50.1747,
        49.6426,
        49.8781,
        47.9329,
        47.5055,
        47.7323,
        49.3722,
        49.9566,
        48.4737,
        49.2675,
        48.4999,
        49.6339,
        49.8345,
        49.0582,
        48.779,
        48.2207,
        47.1129
      ],
      "analyst_rating": "none",
      "analyst_target": 55.02,
      "analyst_count": 25,
      "news": [
        {
          "titel": "Kardigan-Aktien schießen nach Nasdaq-Debüt in die Höhe.",
          "einordnung": "Dieser Titel bezieht sich auf ein anderes Unternehmen, könnte aber auf das allgemeine Investitionsklima im Biotech-Sektor hindeuten, das auch Bristol Myers Squibb beeinflusst.",
          "url": "https://finance.yahoo.com/markets/stocks/articles/kardigan-shares-soar-nasdaq-debut-180332003.html",
          "quelle": "Investing.com",
          "datum": "18.06.2026"
        },
        {
          "titel": "Die Bristol Myers Squibb (BMY) Aktie könnte aufgrund von Pipeline- und Margenhoffnungen um 12,2% unterbewertet sein.",
          "einordnung": "Eine potenzielle Unterbewertung, gestützt durch eine vielversprechende Produktpipeline und Margenverbesserungen, könnte die Aktie für Anleger attraktiv machen.",
          "url": "https://finance.yahoo.com/markets/stocks/articles/bristol-myers-squibb-bmy-stock-232051243.html",
          "quelle": "Simply Wall St.",
          "datum": "17.06.2026"
        },
        {
          "titel": "Bristol Myers Squibb (BMY) enthüllt Studienerfolg bei Myelom und neue Führung im Golfraum.",
          "einordnung": "Ein erfolgreicher Studienabschluss stärkt die Produktpipeline und das zukünftige Umsatzpotenzial, während neue Führungskräfte auf strategische Anpassungen hindeuten können.",
          "url": "https://finance.yahoo.com/healthcare/articles/bristol-myers-squibb-bmy-unveils-221505394.html",
          "quelle": "Simply Wall St.",
          "datum": "17.06.2026"
        },
        {
          "titel": "Die Bristol Myers Squibb (BMY) Aktie bewegt sich um -1,14%: Was Sie wissen sollten.",
          "einordnung": "Eine geringfügige Kursbewegung ist oft Teil der normalen Marktdynamik und erfordert keine sofortige Reaktion, sollte aber im Kontext der Gesamtentwicklung betrachtet werden.",
          "url": "https://finance.yahoo.com/markets/stocks/articles/bristol-myers-squibb-bmy-stock-214505113.html",
          "quelle": "Zacks",
          "datum": "17.06.2026"
        }
      ],
      "fehler": null
    },
    {
      "wkn": "916018",
      "name": "Brit. American Tobacco",
      "ticker": "BTI",
      "currency": "EUR",
      "price": 51.38,
      "change_1d_pct": -0.99,
      "change_1w_pct": -4.06,
      "change_1m_pct": -10.84,
      "change_1y_pct": 27.35,
      "week52_high": 58.71,
      "week52_low": 40.46,
      "div_yield": null,
      "div_rate": 2.91,
      "market_cap": "127.2B",
      "pe_ratio": 12.53,
      "sparkline": [
        50.6632,
        50.8376,
        52.7218,
        55.5132,
        57.0048,
        58.1824,
        56.778,
        57.8771,
        57.6241,
        56.9612,
        57.3363,
        57.0135,
        56.6472,
        55.8621,
        54.8851,
        53.8994,
        53.2103,
        52.7393,
        51.1342,
        50.4626,
        52.0938,
        52.0676,
        52.2944,
        53.315,
        53.5505,
        54.3617,
        53.2626,
        53.5418,
        51.8931,
        51.3785
      ],
      "analyst_rating": "Starker Kauf",
      "analyst_target": 58.92,
      "analyst_count": 5,
      "news": [
        {
          "titel": "3 Tabakaktien, die man inmitten von Marktwiderständen im Auge behalten sollte",
          "einordnung": "Dieser Titel deutet auf potenzielle Widerstandsfähigkeit oder Chancen in der Tabakbranche trotz allgemeiner Marktprobleme hin.",
          "url": "https://finance.yahoo.com/markets/stocks/articles/3-tobacco-stocks-keep-eye-140200603.html",
          "quelle": "Zacks",
          "datum": "18.06.2026"
        },
        {
          "titel": "Europäische Aktien, die in den USA als American Depositary Receipts gehandelt werden, steigen im Mittwochshandel",
          "einordnung": "Dies ist eine allgemeine positive Nachricht für europäische ADRs, einschließlich BTI, die auf eine verbesserte Anlegerstimmung hindeutet.",
          "url": "https://finance.yahoo.com/markets/world-indices/articles/european-equities-traded-us-american-151044153.html",
          "quelle": "MT Newswires",
          "datum": "17.06.2026"
        },
        {
          "titel": "Kursziel für British American Tobacco (BTI) bei Morgan Stanley angehoben",
          "einordnung": "Eine Kurszielanhebung durch eine große Bank ist ein positives Signal für die Aktie und deutet auf Vertrauen in zukünftige Wertsteigerungen hin.",
          "url": "https://finance.yahoo.com/markets/stocks/articles/british-american-tobacco-bti-price-053320525.html",
          "quelle": "Insider Monkey",
          "datum": "14.06.2026"
        },
        {
          "titel": "Ist es zu spät, British American Tobacco (LSE:BATS) nach starken mehrjährigen Gewinnen noch in Betracht zu ziehen?",
          "einordnung": "Dieser Titel regt zur Überlegung an, ob die Aktie nach einer guten Performance immer noch ein attraktives Investment ist oder ob das Potenzial bereits ausgeschöpft ist.",
          "url": "https://finance.yahoo.com/markets/stocks/articles/too-consider-british-american-tobacco-061217117.html",
          "quelle": "Simply Wall St.",
          "datum": "11.06.2026"
        }
      ],
      "fehler": null
    },
    {
      "wkn": "878841",
      "name": "Cisco Systems",
      "ticker": "CSCO",
      "currency": "EUR",
      "price": 104.27,
      "change_1d_pct": 1.88,
      "change_1w_pct": -1.88,
      "change_1m_pct": 3.61,
      "change_1y_pct": 84.4,
      "week52_high": 113.72,
      "week52_low": 57.33,
      "div_yield": null,
      "div_rate": 1.47,
      "market_cap": "471.2B",
      "pe_ratio": 39.85,
      "sparkline": [
        80.3912,
        84.238,
        86.1135,
        86.6107,
        88.8612,
        100.7768,
        103.1146,
        103.699,
        100.646,
        99.7475,
        103.1059,
        105.0336,
        103.2193,
        104.3881,
        103.4897,
        105.0424,
        105.8362,
        111.6544,
        110.346,
        113.399,
        106.1066,
        108.296,
        104.99,
        103.6292,
        106.2723,
        105.6355,
        104.8243,
        104.3009,
        102.347,
        104.2747
      ],
      "analyst_rating": "Kaufen",
      "analyst_target": 110.82,
      "analyst_count": 21,
      "news": [
        {
          "titel": "Intel springt hoch, nachdem Trump sagt, Apple und Intel hätten US-Chip-Deal erreicht",
          "einordnung": "Obwohl es um Intel geht, könnte ein solcher Deal die gesamte US-Chip- und Technologiebranche beeinflussen, was indirekt auch für Cisco relevant sein könnte.",
          "url": "https://finance.yahoo.com/video/intel-jumps-after-trump-says-apple-intel-reached-us-chip-deal-144520733.html",
          "quelle": "Yahoo Finance Video",
          "datum": "18.06.2026"
        },
        {
          "titel": "Entwickelt sich die Aktie von Zebra Technologies schlechter als der Nasdaq?",
          "einordnung": "Dieser Titel vergleicht die Performance eines Wettbewerbers oder Branchenkollegen mit dem Gesamtmarkt, was indirekt Einblicke in die relative Stärke des Sektors geben kann.",
          "url": "https://www.barchart.com/story/news/2536280/is-zebra-technologies-stock-underperforming-the-nasdaq",
          "quelle": "Barchart",
          "datum": "18.06.2026"
        },
        {
          "titel": "Nvidia beansprucht Platz 1 im 10-Milliarden-Dollar-Markt für KI-Netzwerke",
          "einordnung": "Dies zeigt die Dominanz eines wichtigen Akteurs in einem wachsenden Technologiemarkt, was für Anleger in verwandten Bereichen wie Cisco von Interesse ist.",
          "url": "https://finance.yahoo.com/technology/ai/articles/nvidia-claims-no-1-spot-121540877.html",
          "quelle": "GuruFocus.com",
          "datum": "18.06.2026"
        },
        {
          "titel": "Zacks Investment Ideas hebt Dell und Cisco hervor",
          "einordnung": "Die Erwähnung in einer Investment-Highlight-Liste deutet auf eine positive Einschätzung der Aktien durch Analysten hin.",
          "url": "https://finance.yahoo.com/markets/stocks/articles/zacks-investment-ideas-feature-highlights-061100086.html",
          "quelle": "Zacks",
          "datum": "18.06.2026"
        }
      ],
      "fehler": null
    },
    {
      "wkn": "A0MW32",
      "name": "CME Group",
      "ticker": "CME",
      "currency": "EUR",
      "price": 214.92,
      "change_1d_pct": -2.44,
      "change_1w_pct": -6.03,
      "change_1m_pct": -18.09,
      "change_1y_pct": -6.58,
      "week52_high": 287.13,
      "week52_low": 213.33,
      "div_yield": null,
      "div_rate": 4.54,
      "market_cap": "89.0B",
      "pe_ratio": 21.41,
      "sparkline": [
        248.9286,
        244.0689,
        245.2231,
        247.974,
        257.8496,
        258.3442,
        259.3509,
        264.7833,
        262.3969,
        251.7663,
        251.046,
        252.7296,
        245.1884,
        242.2031,
        240.7452,
        237.3782,
        223.6843,
        217.4101,
        219.2411,
        222.209,
        223.3719,
        218.7118,
        223.2565,
        230.1127,
        228.6996,
        235.111,
        232.1016,
        228.1937,
        220.2906,
        214.9173
      ],
      "analyst_rating": "Kaufen",
      "analyst_target": 266.87,
      "analyst_count": 15,
      "news": [
        {
          "titel": "Aktien im Fokus: Intel, Accenture, Apple, SpaceX",
          "einordnung": "Dieser Titel listet Unternehmen auf, die aufgrund aktueller Entwicklungen oder Erwartungen besondere Aufmerksamkeit verdienen.",
          "url": "https://www.wsj.com/livecoverage/stock-market-today-dow-sp-500-nasdaq-06-18-2026/card/stocks-to-watch-intel-apple-smith-wesson-CPWrDsktYLV7juQ6yYSl?siteid=yhoof2&yptr=yahoo",
          "quelle": "The Wall Street Journal",
          "datum": "18.06.2026"
        },
        {
          "titel": "CME Group verklagt CFTC wegen Genehmigung von Perpetual Futures",
          "einordnung": "Eine Klage gegen eine Regulierungsbehörde deutet auf einen wichtigen Rechtsstreit hin, der die Geschäftsstrategie und das Wettbewerbsumfeld der CME Group beeinflussen könnte.",
          "url": "https://www.bankless.com/read/news/cme-group-sues-cftc-over-perpetual-futures-approval",
          "quelle": "Bankless",
          "datum": "18.06.2026"
        },
        {
          "titel": "CME Group verklagt CFTC wegen Perpetual-Future-Entscheidung, die 'rechtswidrig war'",
          "einordnung": "Dieser Titel unterstreicht die rechtliche Auseinandersetzung der CME Group mit der CFTC, die potenziell weitreichende Auswirkungen auf den Derivatemarkt haben könnte.",
          "url": "https://finance.yahoo.com/markets/options/articles/cme-group-sues-cftc-over-162736648.html",
          "quelle": "MT Newswires",
          "datum": "18.06.2026"
        },
        {
          "titel": "Warum die CME Group (CME) eine Top-Dividendenaktie für Ihr Portfolio ist",
          "einordnung": "Dieser Titel hebt die CME Group als attraktive Option für dividendenorientierte Anleger hervor, was auf finanzielle Stabilität und regelmäßige Ausschüttungen hindeutet.",
          "url": "https://finance.yahoo.com/markets/stocks/articles/why-cme-group-cme-top-154502016.html",
          "quelle": "Zacks",
          "datum": "18.06.2026"
        }
      ],
      "fehler": null
    },
    {
      "wkn": "547030",
      "name": "CTS Eventim",
      "ticker": "EVD.DE",
      "currency": "EUR",
      "price": 52.8,
      "change_1d_pct": -1.4,
      "change_1w_pct": 6.32,
      "change_1m_pct": -3.54,
      "change_1y_pct": -47.16,
      "week52_high": 107.0,
      "week52_low": 48.68,
      "div_yield": null,
      "div_rate": 1.44,
      "market_cap": "5.1B",
      "pe_ratio": 17.2,
      "sparkline": [
        54.3989,
        53.9115,
        53.8627,
        52.4979,
        54.4964,
        54.1552,
        54.0577,
        54.7401,
        54.7401,
        54.4964,
        54.8376,
        55.8125,
        55.5688,
        55.91,
        56.15,
        62.15,
        61.15,
        57.8,
        55.15,
        55.8,
        54.3,
        51.4,
        50.9,
        50.0,
        49.66,
        50.45,
        53.0,
        54.7,
        53.55,
        52.8
      ],
      "analyst_rating": "Kaufen",
      "analyst_target": 88.62,
      "analyst_count": 12,
      "news": [
        {
          "titel": "Umsatz übertroffen: CTS Eventim AG & Co. KGaA übertrifft Analystenschätzungen um 14%",
          "einordnung": "Ein deutliches Übertreffen der Umsatzerwartungen ist ein starkes positives Signal für die finanzielle Performance des Unternehmens.",
          "url": "https://finance.yahoo.com/markets/stocks/articles/revenue-beat-cts-eventim-ag-070015855.html",
          "quelle": "Simply Wall St.",
          "datum": "31.05.2026"
        },
        {
          "titel": "CTS Eventim Aktien springen nach US-Tourneen und Olympischen Winterspielen, die die Gewinne antreiben",
          "einordnung": "Dieser Titel erklärt den Grund für den Kursanstieg und zeigt, dass Großveranstaltungen und internationale Expansion das Geschäft positiv beeinflussen.",
          "url": "https://www.wsj.com/business/cts-eventim-shares-jump-after-u-s-tours-winter-olympics-drive-earnings-5e4e932e?siteid=yhoof2&yptr=yahoo",
          "quelle": "The Wall Street Journal",
          "datum": "29.05.2026"
        },
        {
          "titel": "CTS Eventim AG & Co. KGaA (CEVMF) Q1 2026 Earnings Call Highlights: Starkes Umsatzwachstum ...",
          "einordnung": "Die Hervorhebung von starkem Umsatzwachstum in einem Earnings Call ist ein positives Zeichen für die Geschäftsentwicklung und zukünftige Aussichten.",
          "url": "https://finance.yahoo.com/markets/stocks/articles/cts-eventim-ag-co-kgaa-010021245.html",
          "quelle": "GuruFocus.com",
          "datum": "29.05.2026"
        },
        {
          "titel": "CTS Eventim AG & Co. KGaA Q1 Earnings Call Highlights",
          "einordnung": "Dieser Titel kündigt wichtige Informationen aus dem Quartalsbericht an, die für die Bewertung der Unternehmensleistung entscheidend sind.",
          "url": "https://www.marketbeat.com/instant-alerts/cts-eventim-ag-co-kgaa-q1-earnings-call-highlights-2026-05-28/?utm_source=yahoofinance&utm_medium=yahoofinance",
          "quelle": "MarketBeat",
          "datum": "28.05.2026"
        }
      ],
      "fehler": null
    },
    {
      "wkn": "887891",
      "name": "Fastenal",
      "ticker": "FAST",
      "currency": "EUR",
      "price": 40.03,
      "change_1d_pct": 2.25,
      "change_1w_pct": -1.08,
      "change_1m_pct": 5.32,
      "change_1y_pct": 14.44,
      "week52_high": 44.16,
      "week52_low": 33.99,
      "div_yield": null,
      "div_rate": null,
      "market_cap": "52.7B",
      "pe_ratio": 40.61,
      "sparkline": [
        38.6952,
        38.5295,
        37.7706,
        37.788,
        38.1806,
        38.3638,
        37.7357,
        38.3812,
        38.0061,
        38.1021,
        37.9712,
        38.3289,
        38.7737,
        39.0965,
        39.0441,
        38.5557,
        38.3725,
        39.018,
        40.5271,
        41.1377,
        40.8149,
        40.1258,
        40.6317,
        40.152,
        40.466,
        40.623,
        40.213,
        40.1694,
        39.1488,
        40.0298
      ],
      "analyst_rating": "Halten",
      "analyst_target": 40.7,
      "analyst_count": 12,
      "news": [
        {
          "titel": "3 den Markt übertreffende Aktien, die es wert sind, untersucht zu werden",
          "einordnung": "Dieser Titel deutet darauf hin, dass Fastenal (als eine der drei) eine überdurchschnittliche Performance gezeigt hat und weiteres Potenzial bieten könnte.",
          "url": "https://finance.yahoo.com/markets/stocks/articles/3-market-beating-stocks-worth-133328367.html",
          "quelle": "StockStory",
          "datum": "18.06.2026"
        },
        {
          "titel": "Darum bevorzugen Hedgefonds Fastenal Co. (FAST)",
          "einordnung": "Das Interesse von Hedgefonds an einer Aktie kann auf verborgene Werte oder ein starkes Vertrauen in die zukünftige Entwicklung hindeuten.",
          "url": "https://finance.yahoo.com/markets/stocks/articles/why-hedge-funds-fancy-fastenal-155519156.html",
          "quelle": "Insider Monkey",
          "datum": "17.06.2026"
        },
        {
          "titel": "Zacks Branchenausblick hebt W.W. Grainger, MSC Industrial, Kion, Fastenal und EquipmentShare.com hervor",
          "einordnung": "Die Erwähnung in einem positiven Branchenausblick von Zacks deutet auf eine gute Positionierung von Fastenal im Wettbewerbsumfeld hin.",
          "url": "https://finance.yahoo.com/markets/stocks/articles/zacks-industry-outlook-highlights-w-083000034.html",
          "quelle": "Zacks",
          "datum": "16.06.2026"
        },
        {
          "titel": "Mit EPS-Wachstum und mehr: Fastenal (NASDAQ:FAST) bietet einen interessanten Fall",
          "einordnung": "Dieser Titel hebt das Gewinnwachstum pro Aktie (EPS) als einen Hauptgrund hervor, warum Fastenal eine attraktive Investition sein könnte.",
          "url": "https://finance.yahoo.com/markets/stocks/articles/eps-growth-more-fastenal-nasdaq-120011587.html",
          "quelle": "Simply Wall St.",
          "datum": "11.06.2026"
        }
      ],
      "fehler": null
    },
    {
      "wkn": "853260",
      "name": "Johnson & Johnson",
      "ticker": "JNJ",
      "currency": "EUR",
      "price": 199.23,
      "change_1d_pct": -2.48,
      "change_1w_pct": -4.17,
      "change_1m_pct": -0.12,
      "change_1y_pct": 56.29,
      "week52_high": 219.57,
      "week52_low": 130.01,
      "div_yield": null,
      "div_rate": null,
      "market_cap": "549.8B",
      "pe_ratio": 26.47,
      "sparkline": [
        192.9856,
        191.9535,
        192.0489,
        194.5034,
        199.846,
        200.1756,
        196.6283,
        198.5451,
        199.4818,
        198.892,
        200.9822,
        203.2459,
        200.786,
        201.7543,
        201.3268,
        196.5554,
        194.9678,
        194.4269,
        194.7323,
        199.0327,
        203.0453,
        202.5132,
        206.7351,
        208.0348,
        207.8953,
        210.1109,
        205.5662,
        205.1475,
        204.2927,
        199.2333
      ],
      "analyst_rating": "Kaufen",
      "analyst_target": 220.58,
      "analyst_count": 23,
      "news": [
        {
          "titel": "Nasdaq, US-Aktien rutschen ab, da die Fed eine mögliche Zinserhöhung prognostiziert",
          "einordnung": "Eine mögliche Zinserhöhung durch die Fed könnte die Attraktivität von Aktien wie J&J im Vergleich zu festverzinslichen Anlagen mindern.",
          "url": "https://finance.yahoo.com/video/nasdaq-us-stocks-slide-as-fed-forecasts-possible-rate-hike-201525166.html",
          "quelle": "Yahoo Finance Video",
          "datum": "17.06.2026"
        },
        {
          "titel": "Dieses 2-Millionen-Dollar-Portfolio zahlt ein sechsstelliges Einkommen, ohne eine einzige Mietimmobilie zu besitzen",
          "einordnung": "Dieser Titel deutet auf Strategien für passives Einkommen durch Dividendenaktien hin, was für J&J-Aktionäre interessant sein könnte, die auf regelmäßige Ausschüttungen setzen.",
          "url": "https://247wallst.com/personal-finance/2026/06/18/this-2-million-portfolio-pays-a-six-figure-income-without-owning-a-single-rental-property/",
          "quelle": "24/7 Wall St.",
          "datum": "18.06.2026"
        },
        {
          "titel": "50 Jahre Dividendenanhebungen: Diese Aktien haben es geschafft",
          "einordnung": "J&J ist bekannt für seine lange Historie von Dividendenanhebungen, was diesen Titel für bestehende und potenzielle Aktionäre als Zeichen von Stabilität und Verlässlichkeit hervorhebt.",
          "url": "https://www.barrons.com/articles/50-years-of-dividend-hikes-stocks-58af205d?siteid=yhoof2&yptr=yahoo",
          "quelle": "Barrons.com",
          "datum": "18.06.2026"
        },
        {
          "titel": "Johnson & Johnson investiert über 1 Milliarde Dollar in Kontaktlinsen-Produktionsanlage in Florida",
          "einordnung": "Diese Investition signalisiert J&Js Engagement für Wachstum und Kapazitätserweiterung im Medizintechnikbereich, was langfristig positive Auswirkungen auf den Umsatz haben könnte.",
          "url": "https://finance.yahoo.com/healthcare/articles/johnson-johnson-invest-over-1-011618935.html",
          "quelle": "Insider Monkey",
          "datum": "18.06.2026"
        }
      ],
      "fehler": null
    },
    {
      "wkn": "A0RLRP",
      "name": "Koei Tecmo",
      "ticker": "3635.T",
      "currency": "EUR",
      "price": 7.74,
      "change_1d_pct": -2.15,
      "change_1w_pct": -3.08,
      "change_1m_pct": -6.68,
      "change_1y_pct": -37.48,
      "week52_high": 13.03,
      "week52_low": 7.72,
      "div_yield": null,
      "div_rate": 0.26,
      "market_cap": "478.6B",
      "pe_ratio": 10.88,
      "sparkline": [
        8.3098,
        8.2828,
        8.3422,
        8.2828,
        7.9908,
        8.2071,
        8.0692,
        8.399,
        8.299,
        8.2665,
        8.2774,
        8.1098,
        8.107,
        8.2233,
        8.0962,
        8.007,
        8.1936,
        8.2314,
        7.9746,
        7.8421,
        7.9503,
        8.007,
        8.0124,
        8.0395,
        7.9908,
        7.9097,
        7.8259,
        7.9178,
        7.9151,
        7.7448
      ],
      "analyst_rating": "Kaufen",
      "analyst_target": 10.89,
      "analyst_count": 9,
      "news": [
        {
          "titel": "Koei Tecmo (TSE:3635): Bewertung nach neuem Verkauf von eigenen Aktien und Details zum Aktienangebot",
          "einordnung": "Der Verkauf eigener Aktien und neue Aktienangebote können die Bewertung des Unternehmens beeinflussen und erfordern eine genaue Analyse der Auswirkungen auf den Aktienkurs und die Verwässerung.",
          "url": "https://finance.yahoo.com/news/koei-tecmo-tse-3635-assessing-112338756.html",
          "quelle": "Simply Wall St.",
          "datum": "15.09.2025"
        }
      ],
      "fehler": null
    },
    {
      "wkn": "856958",
      "name": "McDonald's",
      "ticker": "MCD",
      "currency": "EUR",
      "price": 243.08,
      "change_1d_pct": -1.81,
      "change_1w_pct": -2.14,
      "change_1m_pct": -0.09,
      "change_1y_pct": -0.71,
      "week52_high": 298.11,
      "week52_low": 237.13,
      "div_yield": null,
      "div_rate": null,
      "market_cap": "198.0B",
      "pe_ratio": 22.99,
      "sparkline": [
        245.8044,
        238.9164,
        237.92,
        238.1279,
        238.8731,
        238.2405,
        239.4709,
        244.7387,
        243.2918,
        242.8326,
        246.2203,
        244.5654,
        241.9575,
        243.3958,
        240.8398,
        241.9055,
        239.2282,
        241.0688,
        238.3909,
        237.8937,
        244.1044,
        242.3075,
        246.2067,
        246.4422,
        248.4049,
        248.4398,
        249.5825,
        251.1613,
        247.5762,
        243.0839
      ],
      "analyst_rating": "Kaufen",
      "analyst_target": 288.98,
      "analyst_count": 31,
      "news": [
        {
          "titel": "EU-Cloud-Untersuchung nimmt Microsoft, Amazon ins Visier",
          "einordnung": "Dieser Titel hat keine direkte Relevanz für McDonald's-Aktionäre, da er sich auf den Cloud-Markt und nicht auf das Kerngeschäft von McDonald's bezieht.",
          "url": "https://finance.yahoo.com/technology/articles/eu-cloud-probe-puts-microsoft-175953201.html",
          "quelle": "GuruFocus.com",
          "datum": "18.06.2026"
        },
        {
          "titel": "McDonald's kombiniert Wertangebote mit Markenaktivierungen: Zahlt es sich aus?",
          "einordnung": "Diese Strategie zielt darauf ab, Kundenbindung und Umsatz zu steigern, was für Aktionäre ein wichtiger Indikator für zukünftiges Wachstum und Rentabilität ist.",
          "url": "https://finance.yahoo.com/markets/stocks/articles/mcdonalds-blends-value-brand-activations-135700319.html",
          "quelle": "Zacks",
          "datum": "18.06.2026"
        },
        {
          "titel": "Trump liebt den Aktienmarkt, aber die Rally braucht mehr als den Iran-Schub. Und 5 weitere Dinge, die man heute wissen sollte.",
          "einordnung": "Dieser Titel bietet einen allgemeinen Marktkommentar und hat keine spezifische Relevanz für McDonald's-Aktionäre, außer im Kontext des Gesamtmarktes.",
          "url": "https://www.barrons.com/articles/trump-stock-market-iran-things-to-know-today-41df643b?siteid=yhoof2&yptr=yahoo",
          "quelle": "Barrons.com",
          "datum": "18.06.2026"
        },
        {
          "titel": "McDonald's (MCD) verzeichnet einen deutlicheren Rückgang als der breitere Markt: Einige Fakten, die man kennen sollte",
          "einordnung": "Ein stärkerer Rückgang als der Gesamtmarkt könnte auf spezifische Herausforderungen für McDonald's hindeuten und erfordert eine genauere Analyse der Gründe.",
          "url": "https://finance.yahoo.com/markets/stocks/articles/mcdonalds-mcd-sees-more-significant-215003860.html",
          "quelle": "Zacks",
          "datum": "17.06.2026"
        }
      ],
      "fehler": null
    },
    {
      "wkn": "710000",
      "name": "Mercedes-Benz",
      "ticker": "MBG.DE",
      "currency": "EUR",
      "price": 44.6,
      "change_1d_pct": -4.6,
      "change_1w_pct": -5.98,
      "change_1m_pct": -10.82,
      "change_1y_pct": -2.48,
      "week52_high": 62.34,
      "week52_low": 43.97,
      "div_yield": null,
      "div_rate": 3.5,
      "market_cap": "42.7B",
      "pe_ratio": 8.76,
      "sparkline": [
        50.13,
        50.26,
        50.22,
        50.76,
        51.02,
        50.35,
        49.97,
        49.54,
        50.01,
        49.76,
        50.12,
        50.76,
        50.92,
        52.51,
        52.71,
        52.19,
        51.44,
        51.67,
        49.955,
        49.075,
        47.995,
        48.355,
        47.705,
        47.11,
        47.435,
        48.015,
        49.375,
        48.88,
        46.75,
        44.6
      ],
      "analyst_rating": "Kaufen",
      "analyst_target": 60.78,
      "analyst_count": 23,
      "news": [
        {
          "titel": "BYD plant Europa-Start, nachdem der Great Tang über 150.000 Bestellungen erreicht hat",
          "einordnung": "Der Markteintritt von BYD in Europa könnte den Wettbewerb für Mercedes-Benz im Premium- und Elektrofahrzeugsegment verschärfen.",
          "url": "https://finance.yahoo.com/technology/articles/byd-plans-europe-launch-great-163102247.html",
          "quelle": "GuruFocus.com",
          "datum": "18.06.2026"
        },
        {
          "titel": "Motorsport-F1-Sponsoring könnte BYD einen risikoärmeren Weg zu globaler Bekanntheit ebnen",
          "einordnung": "Eine erhöhte globale Bekanntheit von BYD durch F1-Sponsoring könnte den Wettbewerbsdruck auf etablierte Marken wie Mercedes-Benz weiter erhöhen.",
          "url": "https://finance.yahoo.com/news/motor-racing-f1-sponsorship-could-041811535.html",
          "quelle": "Reuters",
          "datum": "18.06.2026"
        },
        {
          "titel": "Chinas brutaler Auto-Preiskrieg fordert sein bisher größtes Opfer: BMW",
          "einordnung": "Der aggressive Preiskrieg in China ist ein Warnsignal für Mercedes-Benz, da er die Margen und Marktanteile im wichtigen chinesischen Markt unter Druck setzen könnte.",
          "url": "https://www.barrons.com/articles/bmw-stock-china-guidance-e935f652?siteid=yhoof2&yptr=yahoo",
          "quelle": "Barrons.com",
          "datum": "17.06.2026"
        },
        {
          "titel": "BMW warnt vor 18% Rückgang der China-Verkäufe, Gewinnausblick sinkt",
          "einordnung": "Die negativen Nachrichten von BMW aus China sind ein Indikator für die schwierige Marktlage, die auch Mercedes-Benz betreffen könnte und die Gewinnaussichten beeinflusst.",
          "url": "https://finance.yahoo.com/markets/stocks/articles/bmw-warns-china-sales-down-193406349.html",
          "quelle": "GuruFocus.com",
          "datum": "17.06.2026"
        }
      ],
      "fehler": null
    },
    {
      "wkn": "851995",
      "name": "PepsiCo",
      "ticker": "PEP",
      "currency": "EUR",
      "price": 123.88,
      "change_1d_pct": 0.3,
      "change_1w_pct": -1.19,
      "change_1m_pct": -4.56,
      "change_1y_pct": 14.39,
      "week52_high": 149.58,
      "week52_low": 111.31,
      "div_yield": null,
      "div_rate": null,
      "market_cap": "194.1B",
      "pe_ratio": 22.3,
      "sparkline": [
        134.9123,
        133.4708,
        128.9734,
        131.0797,
        128.8525,
        128.3346,
        128.7231,
        128.6713,
        129.8021,
        128.8698,
        128.49,
        129.9747,
        125.7536,
        127.5318,
        126.2802,
        124.4674,
        122.1626,
        122.577,
        123.0431,
        122.7064,
        123.7968,
        122.7152,
        124.547,
        125.8903,
        125.3757,
        125.8467,
        127.5739,
        127.4605,
        123.509,
        123.884
      ],
      "analyst_rating": "Halten",
      "analyst_target": 146.98,
      "analyst_count": 22,
      "news": [
        {
          "titel": "3 Dividenden-Aristokraten: Kaufen, Verkaufen oder Halten?",
          "einordnung": "PepsiCo ist oft ein Dividenden-Aristokrat, und dieser Titel regt Aktionäre an, die aktuelle Bewertung und Strategie für solche stabilen Dividendenzahler zu überdenken.",
          "url": "https://247wallst.com/investing/2026/06/18/3-dividend-aristocrats-buy-sell-or-hold/",
          "quelle": "24/7 Wall St.",
          "datum": "18.06.2026"
        },
        {
          "titel": "Asahi bringt Milchgetränkemarke Calpis in Indien auf den Markt",
          "einordnung": "Der Markteintritt eines Konkurrenten wie Asahi in Indien könnte den Wettbewerb für PepsiCo in einem wichtigen Wachstumsmarkt verschärfen.",
          "url": "https://www.just-drinks.com/news/asahi-india-calpis-yogurt-launch/",
          "quelle": "Just Drinks",
          "datum": "18.06.2026"
        },
        {
          "titel": "50 Jahre Dividendenanhebungen: Diese Aktien haben es geschafft",
          "einordnung": "PepsiCo ist ein klassischer Dividenden-Aristokrat, und dieser Titel unterstreicht die Attraktivität des Unternehmens für langfristig orientierte, dividendenfokussierte Aktionäre.",
          "url": "https://www.barrons.com/articles/50-years-of-dividend-hikes-stocks-58af205d?siteid=yhoof2&yptr=yahoo",
          "quelle": "Barrons.com",
          "datum": "18.06.2026"
        },
        {
          "titel": "Yum verkauft Pizza Hut für 2,7 Milliarden Dollar, um sich auf KFC und Taco Bell zu konzentrieren",
          "einordnung": "Dieser Titel hat keine direkte Relevanz für PepsiCo-Aktionäre, da er sich auf die strategische Neuausrichtung eines Wettbewerbers im Fast-Food-Sektor bezieht.",
          "url": "https://finance.yahoo.com/markets/stocks/articles/yum-sells-pizza-hut-2-190451912.html",
          "quelle": "GuruFocus.com",
          "datum": "16.06.2026"
        }
      ],
      "fehler": null
    },
    {
      "wkn": "899744",
      "name": "Realty Income",
      "ticker": "O",
      "currency": "EUR",
      "price": 52.55,
      "change_1d_pct": -0.54,
      "change_1w_pct": -2.69,
      "change_1m_pct": -2.54,
      "change_1y_pct": 11.24,
      "week52_high": 59.26,
      "week52_low": 48.73,
      "div_yield": null,
      "div_rate": 2.83,
      "market_cap": "56.2B",
      "pe_ratio": 49.38,
      "sparkline": [
        53.6626,
        53.7755,
        54.1577,
        54.3053,
        53.4282,
        53.8103,
        53.0808,
        53.5932,
        53.9232,
        54.0535,
        54.0448,
        53.8624,
        54.2358,
        54.01,
        53.5758,
        53.4545,
        51.9455,
        52.2595,
        52.0938,
        52.1199,
        53.0707,
        52.3467,
        53.4284,
        54.1786,
        54.0041,
        54.7107,
        54.2047,
        54.2309,
        52.8352,
        52.5517
      ],
      "analyst_rating": "Kaufen",
      "analyst_target": 59.45,
      "analyst_count": 20,
      "news": [
        {
          "titel": "Unsere höchste Überzeugungseinschätzung für Realty Income deutet auf 30% Aufwärtspotenzial hin",
          "einordnung": "Eine solche Einschätzung von Analysten kann das Vertrauen der Aktionäre stärken und auf ein attraktives Kurspotenzial für Realty Income hindeuten.",
          "url": "https://247wallst.com/investing/2026/06/18/our-highest-conviction-call-on-realty-income-points-to-30-upside/",
          "quelle": "24/7 Wall St.",
          "datum": "18.06.2026"
        },
        {
          "titel": "Dieses 2-Millionen-Dollar-Portfolio zahlt ein sechsstelliges Einkommen, ohne eine einzige Mietimmobilie zu besitzen",
          "einordnung": "Dieser Titel ist relevant für Realty Income, da das Unternehmen als REIT eine Alternative zu direkten Immobilieninvestitionen bietet, um passives Einkommen zu generieren.",
          "url": "https://247wallst.com/personal-finance/2026/06/18/this-2-million-portfolio-pays-a-six-figure-income-without-owning-a-single-rental-property/",
          "quelle": "24/7 Wall St.",
          "datum": "18.06.2026"
        },
        {
          "titel": "Warum Mietimmobilien besitzen, wenn Dividendeneinnahmen Ihnen 10.000 Dollar im Monat zahlen können?",
          "einordnung": "Dieser Titel hebt die Attraktivität von Dividendenaktien wie Realty Income als Alternative zu physischen Mietobjekten hervor, um ein hohes passives Einkommen zu erzielen.",
          "url": "https://247wallst.com/personal-finance/2026/06/08/why-own-rental-property-when-dividend-income-can-pay-you-10000-a-month/",
          "quelle": "24/7 Wall St.",
          "datum": "17.06.2026"
        },
        {
          "titel": "Besorgt über einen Markteinbruch? Diese 3 Dividendenaktien könnten helfen, Ihr Risiko zu reduzieren.",
          "einordnung": "Dieser Titel deutet auf defensive Anlagestrategien hin, die in volatilen Marktphasen Stabilität durch Dividenden bieten könnten.",
          "url": "https://www.fool.com/investing/2026/06/17/worried-about-a-market-crash-these-3-dividend-stoc/",
          "quelle": "Motley Fool",
          "datum": "17.06.2026"
        }
      ],
      "fehler": null
    },
    {
      "wkn": "852147",
      "name": "Rio Tinto",
      "ticker": "RIO",
      "currency": "EUR",
      "price": 87.28,
      "change_1d_pct": -2.54,
      "change_1w_pct": -3.45,
      "change_1m_pct": -0.85,
      "change_1y_pct": 88.5,
      "week52_high": 98.2,
      "week52_low": 48.53,
      "div_yield": null,
      "div_rate": null,
      "market_cap": "162.7B",
      "pe_ratio": 16.46,
      "sparkline": [
        89.9429,
        91.923,
        94.1212,
        95.5168,
        97.7325,
        95.5954,
        90.4488,
        90.1348,
        88.0325,
        90.1173,
        91.3821,
        90.9198,
        93.2838,
        92.9959,
        92.8738,
        92.804,
        95.0458,
        97.4097,
        94.0863,
        91.9404,
        87.8319,
        88.0412,
        88.4687,
        86.41,
        90.4052,
        91.8968,
        92.3678,
        92.237,
        89.559,
        87.2823
      ],
      "analyst_rating": "Kaufen",
      "analyst_target": 89.73,
      "analyst_count": 7,
      "news": [
        {
          "titel": "Rio Tinto nimmt Kupferexporte aus Oyu Tolgoi nach kurzem Protest wieder auf.",
          "einordnung": "Die Wiederaufnahme der Exporte ist eine positive Nachricht, die auf eine Beilegung kurzfristiger operativer Störungen und eine Stabilisierung der Einnahmen hindeutet.",
          "url": "https://finance.yahoo.com/markets/commodities/articles/rio-tinto-restarts-oyu-tolgoi-180051875.html",
          "quelle": "GuruFocus.com",
          "datum": "18.06.2026"
        },
        {
          "titel": "Werden hohe Betriebskosten das Wachstumspotenzial von USAR behindern?",
          "einordnung": "Dieser Titel wirft die Frage auf, ob die Kostenstruktur die zukünftige Expansion des Unternehmens beeinträchtigen könnte, was für die langfristige Profitabilität relevant ist.",
          "url": "https://finance.yahoo.com/markets/stocks/articles/high-operating-expenses-hinder-usars-163500566.html",
          "quelle": "Zacks",
          "datum": "18.06.2026"
        },
        {
          "titel": "Protest blockiert Kupferlieferungen aus Rio Tintos Mine Oyu Tolgoi.",
          "einordnung": "Eine Blockade der Lieferungen ist eine negative Nachricht, die kurzfristig zu Produktionsausfällen und Einnahmeverlusten führen kann.",
          "url": "https://www.mining-technology.com/news/protest-blocks-copper-shipments-oyu-tolgoi/",
          "quelle": "Mining Technology",
          "datum": "18.06.2026"
        },
        {
          "titel": "Southern Cross Electrical Engineering (ASX:SXE) Aktien könnten nach Vertragsgewinnen um 42 % überbewertet sein.",
          "einordnung": "Dieser Titel warnt davor, dass trotz positiver Nachrichten der Aktienkurs bereits eine hohe Bewertung erreicht haben könnte, was ein Risiko für Neueinsteiger darstellt.",
          "url": "https://finance.yahoo.com/markets/stocks/articles/southern-cross-electrical-engineering-asx-081644622.html",
          "quelle": "Simply Wall St.",
          "datum": "18.06.2026"
        }
      ],
      "fehler": null
    },
    {
      "wkn": "A3C99G",
      "name": "Shell",
      "ticker": "SHELL.AS",
      "currency": "EUR",
      "price": 34.21,
      "change_1d_pct": -2.56,
      "change_1w_pct": -9.78,
      "change_1m_pct": -8.07,
      "change_1y_pct": 14.08,
      "week52_high": 41.33,
      "week52_low": 29.55,
      "div_yield": null,
      "div_rate": 1.34,
      "market_cap": "189.7B",
      "pe_ratio": 12.35,
      "sparkline": [
        35.5172,
        35.8537,
        36.0318,
        35.9378,
        35.9625,
        36.2248,
        37.4519,
        37.536,
        37.2144,
        37.455,
        37.11,
        36.69,
        36.94,
        36.035,
        36.215,
        35.975,
        36.955,
        37.215,
        37.825,
        37.315,
        37.395,
        37.45,
        36.84,
        37.54,
        37.92,
        37.31,
        35.68,
        35.5,
        35.11,
        34.21
      ],
      "analyst_rating": "none",
      "analyst_target": 42.53,
      "analyst_count": 7,
      "news": [
        {
          "titel": "Der Tank leert sich: Die großen Ölkonzerne laufen auf Reserve.",
          "einordnung": "Dieser Titel deutet auf Herausforderungen für die Ölindustrie hin, möglicherweise aufgrund sinkender Nachfrage oder schwindender Reserven, was langfristige Risiken für Shell birgt.",
          "url": "https://www.marketbeat.com/articles/draining-the-tank-big-oil-runs-on-fumes/?utm_source=yahoofinance&utm_medium=yahoofinance",
          "quelle": "MarketBeat",
          "datum": "17.06.2026"
        },
        {
          "titel": "3 Top-Dividendenaktien zur Maximierung Ihres Renteneinkommens.",
          "einordnung": "Dieser Titel positioniert Shell (implizit, wenn es eine der 3 ist) als attraktive Einkommensaktie, die für langfristige Anleger interessant sein könnte.",
          "url": "https://finance.yahoo.com/markets/stocks/articles/3-top-dividend-stocks-maximize-131003812.html",
          "quelle": "Zacks",
          "datum": "17.06.2026"
        },
        {
          "titel": "Shell (LSE:SHEL) plant den Ausstieg aus dem Windgeschäft für 1 Milliarde Dollar, während es das Laden von Elektrofahrzeugen unterstützt.",
          "einordnung": "Diese Nachricht zeigt eine strategische Neuausrichtung von Shell weg von bestimmten erneuerbaren Energien hin zu anderen, was die zukünftige Geschäftsstrategie beeinflusst.",
          "url": "https://finance.yahoo.com/energy/articles/shell-lse-shel-plans-1-221321141.html",
          "quelle": "Simply Wall St.",
          "datum": "16.06.2026"
        },
        {
          "titel": "C3.ai (AI) erweitert Shell-Partnerschaft für agentenbasiertes Asset Management.",
          "einordnung": "Die Erweiterung der Partnerschaft deutet auf Shells Engagement in der Digitalisierung und Effizienzsteigerung hin, was langfristig Kosten senken und die Produktivität steigern könnte.",
          "url": "https://finance.yahoo.com/technology/ai/articles/c3-ai-ai-expands-shell-190815669.html",
          "quelle": "Simply Wall St.",
          "datum": "16.06.2026"
        }
      ],
      "fehler": null
    },
    {
      "wkn": "723133",
      "name": "Sixt",
      "ticker": "SIX2.DE",
      "currency": "EUR",
      "price": 73.25,
      "change_1d_pct": -3.11,
      "change_1w_pct": 5.65,
      "change_1m_pct": 6.53,
      "change_1y_pct": 1.64,
      "week52_high": 98.7,
      "week52_low": 57.7,
      "div_yield": null,
      "div_rate": 3.2,
      "market_cap": "3.4B",
      "pe_ratio": 11.48,
      "sparkline": [
        67.1807,
        66.7976,
        66.0794,
        68.282,
        69.096,
        68.0426,
        67.8032,
        67.8032,
        68.7608,
        68.1862,
        69.1918,
        70.2452,
        70.7241,
        70.8677,
        71.3466,
        73.2619,
        70.6762,
        70.0058,
        70.1495,
        69.6227,
        68.0426,
        70.1495,
        68.9045,
        70.0537,
        69.3354,
        71.3944,
        71.7296,
        71.2029,
        72.4,
        73.25
      ],
      "analyst_rating": "none",
      "analyst_target": 96.0,
      "analyst_count": 7,
      "news": [
        {
          "titel": "Kaufen Sie Sixt SE (ETR:SIX2) nicht überstürzt, nur weil sie ex-Dividende geht.",
          "einordnung": "Dieser Titel warnt Anleger davor, eine Aktie nur wegen der bevorstehenden Dividendenausschüttung zu kaufen, und mahnt zur Vorsicht bei der Bewertung.",
          "url": "https://finance.yahoo.com/markets/stocks/articles/dont-race-buy-sixt-se-061259094.html",
          "quelle": "Simply Wall St.",
          "datum": "14.06.2026"
        },
        {
          "titel": "Ecos (India) Mobility & Hospitality Ltd (NSE:ECOSMOBLTY) Q4 2026 Gewinnmitteilung Höhepunkte: ...",
          "einordnung": "Dieser Titel bezieht sich auf ein anderes Unternehmen und ist für Sixt-Aktionäre nicht direkt relevant, es sei denn, es gibt eine indirekte Branchenverbindung.",
          "url": "https://finance.yahoo.com/markets/stocks/articles/ecos-india-mobility-hospitality-ltd-010150184.html",
          "quelle": "GuruFocus.com",
          "datum": "30.05.2026"
        },
        {
          "titel": "Sixt SE (ETR:SIX2) hat gerade die Ergebnisse des ersten Quartals gemeldet: Haben Analysten ihre Meinung zur Aktie geändert?",
          "einordnung": "Die Veröffentlichung der Quartalsergebnisse ist ein wichtiger Indikator für die finanzielle Gesundheit des Unternehmens und kann die zukünftige Kursentwicklung beeinflussen.",
          "url": "https://finance.yahoo.com/markets/stocks/articles/sixt-se-etr-six2-just-060916116.html",
          "quelle": "Simply Wall St.",
          "datum": "16.05.2026"
        },
        {
          "titel": "Eine Betrachtung der Sixt (XTRA:SIX2) Bewertung nach der jüngsten Aktienkursvolatilität.",
          "einordnung": "Dieser Titel legt nahe, dass die jüngsten Kursschwankungen eine Neubewertung der Aktie erforderlich machen, was Chancen oder Risiken bergen kann.",
          "url": "https://finance.yahoo.com/markets/stocks/articles/look-sixt-xtra-six2-valuation-090954777.html",
          "quelle": "Simply Wall St.",
          "datum": "05.05.2026"
        }
      ],
      "fehler": null
    },
    {
      "wkn": "852654",
      "name": "Texas Instruments",
      "ticker": "TXN",
      "currency": "EUR",
      "price": 281.63,
      "change_1d_pct": 6.95,
      "change_1w_pct": 8.67,
      "change_1m_pct": 6.8,
      "change_1y_pct": 67.47,
      "week52_high": 289.18,
      "week52_low": 133.23,
      "div_yield": null,
      "div_rate": null,
      "market_cap": "293.8B",
      "pe_ratio": 55.28,
      "sparkline": [
        248.8148,
        251.0479,
        259.7361,
        257.4768,
        267.2204,
        268.8167,
        264.0714,
        262.2134,
        263.705,
        265.9468,
        260.2856,
        269.7239,
        283.4016,
        276.9116,
        275.6032,
        266.6447,
        255.7584,
        268.7731,
        269.1831,
        266.3742,
        248.6578,
        253.7521,
        251.772,
        245.9973,
        259.1603,
        262.667,
        273.3265,
        266.6708,
        263.3299,
        281.6308
      ],
      "analyst_rating": "Kaufen",
      "analyst_target": 256.03,
      "analyst_count": 33,
      "news": [
        {
          "titel": "Der wahre Preis von Broadcom-Aktien ist nicht das, was er scheint.",
          "einordnung": "Dieser Titel warnt vor einer möglichen Fehlbewertung einer Konkurrenzaktie, was indirekt auf die relative Attraktivität von Texas Instruments hinweisen könnte.",
          "url": "https://www.trefis.com/articles/603595/the-real-price-tag-on-broadcom-stock-is-not-what-it-seems/2026-06-18",
          "quelle": "Trefis",
          "datum": "18.06.2026"
        },
        {
          "titel": "Kann die Treo-Plattform von onsemi neue Chancen im Automobilsektor erschließen?",
          "einordnung": "Dieser Titel beleuchtet Innovationen eines Wettbewerbers im Automobilsektor, einem wichtigen Markt für Texas Instruments, und könnte auf zukünftige Wettbewerbsdynamiken hindeuten.",
          "url": "https://finance.yahoo.com/technology/articles/onsemis-treo-platform-unlock-automotive-141000885.html",
          "quelle": "Zacks",
          "datum": "18.06.2026"
        },
        {
          "titel": "TXN vs. LRCX: Welche Halbleiteraktie ist derzeit der bessere Kauf?",
          "einordnung": "Dieser Vergleichstitel hilft Anlegern, die relative Attraktivität von Texas Instruments gegenüber einem Wettbewerber im Halbleitersektor zu bewerten.",
          "url": "https://finance.yahoo.com/markets/stocks/articles/txn-vs-lrcx-semiconductor-stock-123800583.html",
          "quelle": "Zacks",
          "datum": "18.06.2026"
        },
        {
          "titel": "Citi erhöht das Kursziel für Texas Instruments (TXN) um 65 Dollar. Hier ist der Grund.",
          "einordnung": "Eine Kurszielerhöhung durch eine große Bank ist ein positives Signal, das auf eine verbesserte Einschätzung der zukünftigen Performance und des Wertpotenzials hindeutet.",
          "url": "https://finance.yahoo.com/markets/stocks/articles/citi-lifts-texas-instruments-txn-011339837.html",
          "quelle": "Insider Monkey",
          "datum": "18.06.2026"
        }
      ],
      "fehler": null
    },
    {
      "wkn": "869561",
      "name": "UnitedHealth",
      "ticker": "UNH",
      "currency": "EUR",
      "price": 349.86,
      "change_1d_pct": 0.39,
      "change_1w_pct": -0.54,
      "change_1m_pct": 3.63,
      "change_1y_pct": 36.36,
      "week52_high": 362.86,
      "week52_low": 204.64,
      "div_yield": null,
      "div_rate": null,
      "market_cap": "364.2B",
      "pe_ratio": 30.18,
      "sparkline": [
        320.6926,
        329.5742,
        333.4426,
        343.8074,
        347.9446,
        346.1492,
        341.6043,
        339.2451,
        337.6058,
        332.4538,
        331.7426,
        336.938,
        326.8681,
        333.0696,
        331.7859,
        329.8604,
        329.4701,
        327.7875,
        326.9895,
        343.8767,
        346.4788,
        352.6369,
        358.214,
        353.4089,
        351.7522,
        354.3283,
        358.5502,
        355.5931,
        348.51,
        349.8621
      ],
      "analyst_rating": "Kaufen",
      "analyst_target": 355.36,
      "analyst_count": 26,
      "news": [
        {
          "titel": "2 Mega-Cap-Aktien, die man genauer untersuchen sollte, und 1, die wir meiden.",
          "einordnung": "Dieser Titel gibt eine Kauf- oder Verkaufsempfehlung für große Unternehmen, wobei UnitedHealth entweder zu den zu untersuchenden oder zu den zu meidenden Aktien gehören könnte.",
          "url": "https://finance.yahoo.com/markets/stocks/articles/2-mega-cap-stocks-research-153328998.html",
          "quelle": "StockStory",
          "datum": "18.06.2026"
        },
        {
          "titel": "Darum fiel die UnitedHealth Group (UNH) stärker als der breitere Markt.",
          "einordnung": "Ein stärkerer Kursrückgang als der Gesamtmarkt ist ein Warnsignal, das auf spezifische negative Entwicklungen oder Bedenken bezüglich des Unternehmens hindeutet.",
          "url": "https://finance.yahoo.com/markets/stocks/articles/heres-why-unitedhealth-group-unh-215005067.html",
          "quelle": "Zacks",
          "datum": "17.06.2026"
        },
        {
          "titel": "UnitedHealth-Aktie erhält eine Kurszielerhöhung. Die Wall Street mag den bisherigen Turnaround.",
          "einordnung": "Eine Kurszielerhöhung und positive Einschätzungen der Wall Street sind gute Nachrichten, die auf eine verbesserte Unternehmensentwicklung und zukünftiges Wachstumspotenzial hindeuten.",
          "url": "https://www.barrons.com/articles/unitedhealth-stock-price-buy-rating-b0508382?siteid=yhoof2&yptr=yahoo",
          "quelle": "Barrons.com",
          "datum": "17.06.2026"
        },
        {
          "titel": "Darum hat der SGA Global Growth Fund seine Anteile an UnitedHealth (UNH) verkauft",
          "einordnung": "Aktionäre sollten den Verkauf der Anteile durch einen großen Fonds als mögliches Signal für eine Neubewertung der Unternehmensperspektiven oder eine strategische Umschichtung interpretieren.",
          "url": "https://finance.yahoo.com/healthcare/articles/why-sga-global-growth-fund-125228589.html",
          "quelle": "Insider Monkey",
          "datum": "17.06.2026"
        }
      ],
      "fehler": null
    }
  ]
}