{
  "aktualisiert": "2026-03-23T20:11:44.515781+00:00",
  "aktien": [
    {
      "wkn": "A1J84E",
      "name": "AbbVie",
      "ticker": "ABBV",
      "currency": "EUR",
      "price": 176.39,
      "change_1d_pct": -0.06,
      "change_1w_pct": -7.46,
      "change_1m_pct": -8.84,
      "change_1y_pct": 1.26,
      "week52_high": 210.71,
      "week52_low": 141.49,
      "div_yield": null,
      "div_rate": 5.96,
      "market_cap": "362.4B",
      "pe_ratio": 86.11,
      "sparkline": [
        192.1599,
        191.4541,
        190.12,
        195.8092,
        199.252,
        200.4226,
        196.8593,
        193.0981,
        193.494,
        197.5134,
        196.6183,
        195.31,
        193.3907,
        199.7513,
        201.6276,
        201.2833,
        203.2887,
        199.9837,
        198.0557,
        195.7662,
        195.3875,
        195.9642,
        193.976,
        189.0786,
        190.602,
        189.1474,
        179.3182,
        177.5022,
        176.5038,
        176.3919
      ],
      "analyst_rating": "Kaufen",
      "analyst_target": 214.43,
      "analyst_count": 29,
      "news": [],
      "fehler": null
    },
    {
      "wkn": "A2ANT0",
      "name": "Ahold Delhaize",
      "ticker": "AD.AS",
      "currency": "EUR",
      "price": 40.06,
      "change_1d_pct": -1.93,
      "change_1w_pct": -5.18,
      "change_1m_pct": 0.02,
      "change_1y_pct": 22.07,
      "week52_high": 42.54,
      "week52_low": 32.13,
      "div_yield": null,
      "div_rate": 1.46,
      "market_cap": "35.5B",
      "pe_ratio": 16.02,
      "sparkline": [
        34.71,
        38.72,
        39.5,
        39.82,
        39.59,
        39.67,
        39.69,
        40.0,
        40.05,
        41.25,
        41.33,
        41.1,
        40.98,
        41.77,
        41.32,
        40.61,
        41.42,
        40.77,
        40.87,
        41.07,
        41.25,
        40.88,
        41.63,
        42.11,
        42.25,
        42.5,
        41.83,
        41.2,
        40.85,
        40.06
      ],
      "analyst_rating": "Kaufen",
      "analyst_target": 39.98,
      "analyst_count": 16,
      "news": [],
      "fehler": null
    },
    {
      "wkn": "840400",
      "name": "Allianz",
      "ticker": "ALV.DE",
      "currency": "EUR",
      "price": 349.7,
      "change_1d_pct": 0.6,
      "change_1w_pct": -2.73,
      "change_1m_pct": -7.78,
      "change_1y_pct": 3.81,
      "week52_high": 396.0,
      "week52_low": 286.6,
      "div_yield": null,
      "div_rate": 17.1,
      "market_cap": "133.0B",
      "pe_ratio": 12.64,
      "sparkline": [
        377.4,
        366.8,
        367.0,
        366.9,
        369.2,
        372.4,
        372.5,
        373.4,
        379.2,
        378.8,
        378.5,
        381.5,
        384.7,
        382.2,
        370.4,
        355.4,
        359.0,
        353.2,
        347.6,
        344.2,
        354.4,
        351.9,
        350.5,
        354.1,
        359.5,
        362.1,
        358.6,
        353.2,
        347.6,
        349.7
      ],
      "analyst_rating": "Kaufen",
      "analyst_target": 396.75,
      "analyst_count": 18,
      "news": [],
      "fehler": null
    },
    {
      "wkn": "850471",
      "name": "Boeing",
      "ticker": "BA",
      "currency": "EUR",
      "price": 170.79,
      "change_1d_pct": 1.7,
      "change_1w_pct": -7.05,
      "change_1m_pct": -14.48,
      "change_1y_pct": 9.69,
      "week52_high": 218.92,
      "week52_low": 110.93,
      "div_yield": null,
      "div_rate": null,
      "market_cap": "155.9B",
      "pe_ratio": 80.01,
      "sparkline": [
        210.6219,
        208.7972,
        203.349,
        206.0086,
        209.1157,
        210.0452,
        205.647,
        201.1542,
        199.7082,
        198.3397,
        200.8788,
        198.2709,
        197.4532,
        195.8351,
        197.7372,
        192.9001,
        195.6457,
        191.127,
        198.9164,
        193.6575,
        187.426,
        184.2759,
        176.2369,
        180.6523,
        183.7336,
        181.4528,
        177.2956,
        173.1556,
        167.9398,
        170.7887
      ],
      "analyst_rating": "Kaufen",
      "analyst_target": 234.33,
      "analyst_count": 24,
      "news": [],
      "fehler": null
    },
    {
      "wkn": "850501",
      "name": "Bristol-Myers Squibb",
      "ticker": "BMY",
      "currency": "EUR",
      "price": 49.06,
      "change_1d_pct": -0.84,
      "change_1w_pct": -4.54,
      "change_1m_pct": -6.03,
      "change_1y_pct": -1.92,
      "week52_high": 54.13,
      "week52_low": 36.6,
      "div_yield": null,
      "div_rate": 2.17,
      "market_cap": "116.1B",
      "pe_ratio": 16.47,
      "sparkline": [
        52.3047,
        52.3822,
        51.5818,
        51.5215,
        52.2789,
        51.9432,
        51.4096,
        51.9002,
        52.2101,
        52.7179,
        53.0191,
        52.7609,
        52.5888,
        53.6819,
        53.656,
        52.6921,
        53.6474,
        52.2789,
        51.8916,
        52.1842,
        51.7539,
        51.6248,
        50.7383,
        50.8502,
        51.3924,
        51.3924,
        51.0998,
        50.0153,
        49.473,
        49.0599
      ],
      "analyst_rating": "Halten",
      "analyst_target": 53.98,
      "analyst_count": 25,
      "news": [],
      "fehler": null
    },
    {
      "wkn": "916018",
      "name": "Brit. American Tobacco",
      "ticker": "BTI",
      "currency": "EUR",
      "price": 49.85,
      "change_1d_pct": 0.96,
      "change_1w_pct": -4.96,
      "change_1m_pct": -6.7,
      "change_1y_pct": 50.85,
      "week52_high": 54.41,
      "week52_low": 32.67,
      "div_yield": null,
      "div_rate": 2.87,
      "market_cap": "126.5B",
      "pe_ratio": 12.51,
      "sparkline": [
        52.6318,
        51.8055,
        51.926,
        52.167,
        51.2116,
        50.7038,
        50.6694,
        52.4941,
        53.4323,
        53.4495,
        53.2859,
        54.2499,
        53.9401,
        53.9229,
        53.4667,
        51.9949,
        52.5113,
        50.4284,
        49.8087,
        50.2046,
        51.1342,
        50.919,
        51.5473,
        51.5818,
        52.4511,
        52.1154,
        49.9981,
        50.5403,
        49.3784,
        49.8517
      ],
      "analyst_rating": "Kaufen",
      "analyst_target": 52.42,
      "analyst_count": 5,
      "news": [],
      "fehler": null
    },
    {
      "wkn": "878841",
      "name": "Cisco Systems",
      "ticker": "CSCO",
      "currency": "EUR",
      "price": 67.85,
      "change_1d_pct": 1.52,
      "change_1w_pct": -0.08,
      "change_1m_pct": -0.46,
      "change_1y_pct": 32.44,
      "week52_high": 75.91,
      "week52_low": 44.85,
      "div_yield": null,
      "div_rate": 1.45,
      "market_cap": "311.5B",
      "pe_ratio": 28.36,
      "sparkline": [
        74.6915,
        74.2698,
        73.6243,
        64.5525,
        66.1448,
        66.1448,
        67.2895,
        67.6166,
        68.1674,
        66.9108,
        67.2551,
        68.0986,
        67.2207,
        68.3912,
        68.3568,
        67.9609,
        69.6048,
        68.8646,
        67.6854,
        65.5939,
        66.8764,
        67.2207,
        66.9108,
        67.4186,
        67.9092,
        68.2277,
        66.7903,
        67.5736,
        66.8334,
        67.8533
      ],
      "analyst_rating": "Kaufen",
      "analyst_target": 76.44,
      "analyst_count": 21,
      "news": [],
      "fehler": null
    },
    {
      "wkn": "A0MW32",
      "name": "CME Group",
      "ticker": "CME",
      "currency": "EUR",
      "price": 263.86,
      "change_1d_pct": -0.25,
      "change_1w_pct": -2.32,
      "change_1m_pct": 1.88,
      "change_1y_pct": 21.05,
      "week52_high": 283.31,
      "week52_low": 213.91,
      "div_yield": null,
      "div_rate": 4.48,
      "market_cap": "110.2B",
      "pe_ratio": 27.47,
      "sparkline": [
        258.2674,
        257.8639,
        254.2661,
        253.56,
        254.7621,
        254.8966,
        254.325,
        255.4682,
        258.9819,
        263.9499,
        268.1781,
        258.3683,
        266.0094,
        268.5732,
        274.4238,
        273.3058,
        268.9935,
        266.312,
        266.5558,
        268.2286,
        263.6668,
        261.0761,
        267.8412,
        268.022,
        270.1135,
        269.6831,
        265.8702,
        267.4281,
        264.5103,
        263.8562
      ],
      "analyst_rating": "Halten",
      "analyst_target": 264.11,
      "analyst_count": 14,
      "news": [],
      "fehler": null
    },
    {
      "wkn": "547030",
      "name": "CTS Eventim",
      "ticker": "EVD.DE",
      "currency": "EUR",
      "price": 63.25,
      "change_1d_pct": 0.24,
      "change_1w_pct": -6.99,
      "change_1m_pct": -5.67,
      "change_1y_pct": -35.87,
      "week52_high": 114.1,
      "week52_low": 61.0,
      "div_yield": null,
      "div_rate": 1.66,
      "market_cap": "6.1B",
      "pe_ratio": 21.15,
      "sparkline": [
        70.0,
        67.8,
        68.05,
        66.65,
        65.25,
        65.55,
        65.15,
        65.45,
        67.05,
        65.7,
        64.7,
        63.9,
        65.55,
        68.85,
        67.2,
        65.8,
        65.8,
        67.95,
        67.6,
        67.35,
        69.2,
        69.35,
        69.2,
        69.15,
        68.0,
        67.3,
        66.5,
        65.05,
        63.1,
        63.25
      ],
      "analyst_rating": "Kaufen",
      "analyst_target": 105.17,
      "analyst_count": 12,
      "news": [],
      "fehler": null
    },
    {
      "wkn": "887891",
      "name": "Fastenal",
      "ticker": "FAST",
      "currency": "EUR",
      "price": 38.26,
      "change_1d_pct": 1.58,
      "change_1w_pct": -2.69,
      "change_1m_pct": -3.83,
      "change_1y_pct": 17.97,
      "week52_high": 43.58,
      "week52_low": 30.39,
      "div_yield": null,
      "div_rate": 0.77,
      "market_cap": "51.0B",
      "pe_ratio": 40.78,
      "sparkline": [
        40.0398,
        40.1603,
        40.4701,
        39.1963,
        39.9451,
        39.3254,
        39.575,
        39.7729,
        39.7816,
        38.7745,
        39.1274,
        38.413,
        39.3168,
        39.6266,
        39.8762,
        39.7902,
        39.9623,
        40.7111,
        39.9881,
        40.2808,
        39.8504,
        40.1,
        38.9467,
        39.1274,
        39.3168,
        39.532,
        38.8004,
        38.2925,
        37.6642,
        38.2581
      ],
      "analyst_rating": "Halten",
      "analyst_target": 38.72,
      "analyst_count": 12,
      "news": [],
      "fehler": null
    },
    {
      "wkn": "853260",
      "name": "Johnson & Johnson",
      "ticker": "JNJ",
      "currency": "EUR",
      "price": 202.63,
      "change_1d_pct": 0.02,
      "change_1w_pct": -3.2,
      "change_1m_pct": -2.4,
      "change_1y_pct": 48.19,
      "week52_high": 216.65,
      "week52_low": 121.79,
      "div_yield": null,
      "div_rate": 4.48,
      "market_cap": "567.3B",
      "pe_ratio": 21.32,
      "sparkline": [
        204.3113,
        204.063,
        206.212,
        209.3711,
        208.4294,
        208.3266,
        209.7479,
        211.3917,
        207.6075,
        210.4756,
        211.9732,
        211.0178,
        209.5546,
        213.8237,
        213.9356,
        212.3777,
        211.1297,
        206.2495,
        206.9123,
        208.7972,
        209.7612,
        209.1415,
        208.3238,
        207.8763,
        209.3136,
        204.9413,
        204.2269,
        204.5023,
        202.583,
        202.626
      ],
      "analyst_rating": "Kaufen",
      "analyst_target": 207.5,
      "analyst_count": 24,
      "news": [],
      "fehler": null
    },
    {
      "wkn": "A0RLRP",
      "name": "Koei Tecmo",
      "ticker": "3635.T",
      "currency": "EUR",
      "price": 9.53,
      "change_1d_pct": -2.39,
      "change_1w_pct": -7.03,
      "change_1m_pct": 2.36,
      "change_1y_pct": -11.99,
      "week52_high": 13.83,
      "week52_low": 8.36,
      "div_yield": null,
      "div_rate": 0.47,
      "market_cap": "585.7B",
      "pe_ratio": 16.45,
      "sparkline": [
        8.6195,
        8.4347,
        8.5869,
        8.9374,
        8.6983,
        8.3803,
        8.7472,
        9.0651,
        9.307,
        9.2499,
        9.1928,
        9.1684,
        9.3233,
        9.47,
        9.8042,
        9.7961,
        9.6901,
        9.7445,
        9.4347,
        9.7227,
        9.489,
        9.6792,
        10.2526,
        9.9727,
        10.2472,
        10.2716,
        10.0352,
        9.9618,
        9.7608,
        9.5271
      ],
      "analyst_rating": "Kaufen",
      "analyst_target": 11.66,
      "analyst_count": 9,
      "news": [],
      "fehler": null
    },
    {
      "wkn": "856958",
      "name": "McDonald's",
      "ticker": "MCD",
      "currency": "EUR",
      "price": 265.54,
      "change_1d_pct": -0.11,
      "change_1w_pct": -5.55,
      "change_1m_pct": -5.77,
      "change_1y_pct": 3.27,
      "week52_high": 294.14,
      "week52_low": 243.98,
      "div_yield": null,
      "div_rate": 6.4,
      "market_cap": "220.2B",
      "pe_ratio": 25.82,
      "sparkline": [
        278.6871,
        279.0038,
        276.6415,
        284.2334,
        280.3818,
        280.416,
        280.6472,
        279.9795,
        281.7941,
        286.3561,
        285.0637,
        285.0295,
        286.3304,
        291.9196,
        286.5787,
        285.8987,
        285.5286,
        281.8362,
        282.3612,
        284.7195,
        282.258,
        279.9082,
        278.7893,
        280.9841,
        281.1476,
        280.8464,
        271.7488,
        266.4555,
        265.8272,
        265.5466
      ],
      "analyst_rating": "Kaufen",
      "analyst_target": 295.46,
      "analyst_count": 32,
      "news": [],
      "fehler": null
    },
    {
      "wkn": "710000",
      "name": "Mercedes-Benz",
      "ticker": "MBG.DE",
      "currency": "EUR",
      "price": 51.93,
      "change_1d_pct": 2.1,
      "change_1w_pct": -3.39,
      "change_1m_pct": -12.34,
      "change_1y_pct": -3.32,
      "week52_high": 62.34,
      "week52_low": 45.6,
      "div_yield": null,
      "div_rate": 3.5,
      "market_cap": "45.9B",
      "pe_ratio": 9.72,
      "sparkline": [
        58.36,
        57.95,
        57.11,
        57.62,
        57.65,
        58.86,
        59.4,
        58.75,
        59.24,
        58.3,
        58.93,
        58.99,
        59.0,
        59.0,
        56.63,
        55.74,
        56.52,
        55.65,
        54.78,
        54.25,
        55.05,
        54.89,
        55.25,
        54.85,
        53.75,
        53.71,
        53.47,
        51.64,
        50.86,
        51.93
      ],
      "analyst_rating": "Kaufen",
      "analyst_target": 62.32,
      "analyst_count": 24,
      "news": [],
      "fehler": null
    },
    {
      "wkn": "851995",
      "name": "PepsiCo",
      "ticker": "PEP",
      "currency": "EUR",
      "price": 129.86,
      "change_1d_pct": 0.56,
      "change_1w_pct": -4.34,
      "change_1m_pct": -7.71,
      "change_1y_pct": 7.15,
      "week52_high": 147.59,
      "week52_low": 109.83,
      "div_yield": null,
      "div_rate": 4.9,
      "market_cap": "206.3B",
      "pe_ratio": 25.15,
      "sparkline": [
        142.012,
        142.4385,
        144.2982,
        142.6347,
        141.5599,
        138.1305,
        140.2376,
        140.4082,
        140.7068,
        143.5902,
        144.6309,
        144.3153,
        142.9589,
        144.8015,
        142.703,
        140.6812,
        139.8366,
        137.0897,
        137.2214,
        139.0289,
        138.3833,
        137.8411,
        136.7308,
        137.6087,
        135.7496,
        134.6996,
        132.1519,
        131.4633,
        129.1394,
        129.8624
      ],
      "analyst_rating": "Halten",
      "analyst_target": 147.51,
      "analyst_count": 21,
      "news": [],
      "fehler": null
    },
    {
      "wkn": "899744",
      "name": "Realty Income",
      "ticker": "O",
      "currency": "EUR",
      "price": 52.36,
      "change_1d_pct": -0.18,
      "change_1w_pct": -6.28,
      "change_1m_pct": -7.63,
      "change_1y_pct": 14.25,
      "week52_high": 58.48,
      "week52_low": 43.65,
      "div_yield": null,
      "div_rate": 2.78,
      "market_cap": "56.9B",
      "pe_ratio": 52.0,
      "sparkline": [
        54.0814,
        54.7758,
        55.2901,
        55.5301,
        56.2845,
        56.9959,
        55.7787,
        56.1473,
        56.6959,
        57.1588,
        57.0217,
        56.5673,
        57.0902,
        57.6669,
        58.1489,
        57.2882,
        56.8062,
        55.7734,
        55.9455,
        55.8939,
        55.8422,
        55.6959,
        55.9713,
        55.4635,
        55.8766,
        55.1623,
        54.2585,
        53.9142,
        52.4597,
        52.3693
      ],
      "analyst_rating": "Halten",
      "analyst_target": 58.4,
      "analyst_count": 20,
      "news": [],
      "fehler": null
    },
    {
      "wkn": "852147",
      "name": "Rio Tinto",
      "ticker": "RIO",
      "currency": "EUR",
      "price": 73.89,
      "change_1d_pct": 3.25,
      "change_1w_pct": -4.46,
      "change_1m_pct": -9.1,
      "change_1y_pct": 45.39,
      "week52_high": 87.39,
      "week52_low": 44.47,
      "div_yield": null,
      "div_rate": 3.46,
      "market_cap": "139.6B",
      "pe_ratio": 14.1,
      "sparkline": [
        81.0911,
        81.4177,
        83.3267,
        81.9787,
        82.1126,
        81.1163,
        82.8327,
        80.6641,
        81.2921,
        81.7777,
        82.1461,
        84.3817,
        82.9666,
        83.176,
        83.402,
        79.8017,
        80.5888,
        78.1774,
        77.6437,
        77.7642,
        78.909,
        79.2533,
        78.0655,
        75.5953,
        77.3425,
        77.2909,
        75.5006,
        73.719,
        71.5672,
        73.8911
      ],
      "analyst_rating": "Kaufen",
      "analyst_target": 82.24,
      "analyst_count": 7,
      "news": [],
      "fehler": null
    },
    {
      "wkn": "A3C99G",
      "name": "Shell",
      "ticker": "SHELL.AS",
      "currency": "EUR",
      "price": 38.8,
      "change_1d_pct": -1.95,
      "change_1w_pct": -1.78,
      "change_1m_pct": 15.24,
      "change_1y_pct": 23.55,
      "week52_high": 40.39,
      "week52_low": 26.53,
      "div_yield": null,
      "div_rate": 1.26,
      "market_cap": "218.5B",
      "pe_ratio": 14.98,
      "sparkline": [
        32.2197,
        33.1839,
        32.8329,
        32.7191,
        32.7142,
        32.4818,
        33.268,
        33.725,
        33.67,
        33.965,
        34.175,
        34.57,
        34.68,
        35.0,
        35.93,
        35.755,
        35.215,
        35.76,
        36.17,
        37.065,
        36.725,
        37.56,
        38.535,
        38.945,
        39.505,
        40.195,
        40.06,
        40.095,
        39.57,
        38.8
      ],
      "analyst_rating": "Kaufen",
      "analyst_target": 37.47,
      "analyst_count": 6,
      "news": [],
      "fehler": null
    },
    {
      "wkn": "723133",
      "name": "Sixt",
      "ticker": "SIX2.DE",
      "currency": "EUR",
      "price": 60.9,
      "change_1d_pct": 1.33,
      "change_1w_pct": -2.09,
      "change_1m_pct": -7.31,
      "change_1y_pct": -23.83,
      "week52_high": 98.7,
      "week52_low": 57.7,
      "div_yield": null,
      "div_rate": 3.2,
      "market_cap": "2.9B",
      "pe_ratio": 10.02,
      "sparkline": [
        67.8,
        66.25,
        65.6,
        65.05,
        65.05,
        67.15,
        67.0,
        65.9,
        65.7,
        64.85,
        64.45,
        64.75,
        65.75,
        65.8,
        63.3,
        60.7,
        64.45,
        67.25,
        66.5,
        64.6,
        66.2,
        64.85,
        64.6,
        62.85,
        62.2,
        62.1,
        62.2,
        61.35,
        60.1,
        60.9
      ],
      "analyst_rating": "Starker Kauf",
      "analyst_target": 94.71,
      "analyst_count": 7,
      "news": [],
      "fehler": null
    },
    {
      "wkn": "852654",
      "name": "Texas Instruments",
      "ticker": "TXN",
      "currency": "EUR",
      "price": 162.57,
      "change_1d_pct": 0.9,
      "change_1w_pct": -2.7,
      "change_1m_pct": -14.04,
      "change_1y_pct": 5.03,
      "week52_high": 199.1,
      "week52_low": 120.45,
      "div_yield": null,
      "div_rate": 4.89,
      "market_cap": "172.0B",
      "pe_ratio": 34.66,
      "sparkline": [
        188.2953,
        190.1458,
        195.0002,
        191.9361,
        194.6559,
        194.2514,
        192.2115,
        187.6756,
        189.1216,
        189.2335,
        183.6304,
        184.1037,
        183.0106,
        182.5631,
        180.5921,
        174.4381,
        174.1971,
        170.4014,
        166.3131,
        168.8693,
        169.9538,
        170.9953,
        163.576,
        164.2043,
        167.0877,
        167.3631,
        164.2043,
        162.0612,
        161.1144,
        162.569
      ],
      "analyst_rating": "Halten",
      "analyst_target": 190.69,
      "analyst_count": 32,
      "news": [],
      "fehler": null
    },
    {
      "wkn": "869561",
      "name": "UnitedHealth",
      "ticker": "UNH",
      "currency": "EUR",
      "price": 232.1,
      "change_1d_pct": -2.15,
      "change_1w_pct": -5.54,
      "change_1m_pct": -6.29,
      "change_1y_pct": -46.32,
      "week52_high": 521.89,
      "week52_low": 201.92,
      "div_yield": null,
      "div_rate": 7.61,
      "market_cap": "244.8B",
      "pe_ratio": 20.38,
      "sparkline": [
        235.4644,
        233.3464,
        238.2059,
        242.8691,
        250.4019,
        246.9003,
        246.1402,
        247.6177,
        247.6775,
        241.1354,
        233.9698,
        242.7239,
        244.8249,
        250.4702,
        251.888,
        247.0028,
        249.3514,
        246.627,
        244.6712,
        245.4458,
        243.01,
        245.5147,
        238.4569,
        242.7949,
        245.7212,
        247.5115,
        244.7228,
        241.3747,
        237.2003,
        232.105
      ],
      "analyst_rating": "Kaufen",
      "analyst_target": 310.89,
      "analyst_count": 24,
      "news": [],
      "fehler": null
    }
  ]
}